Workbook
Name Bosnia: Data!$M$4:$M$12
Name Country: Data!$M$3:$T$3
Name Croatia: Data!$O$4:$O$30
Name Czech_R.: Data!$N$4:$N$33
Name Poland: Data!$P$4:$P$8
Name Romania: Data!$Q$4:$Q$27
Name Serbia: Data!$R$4:$R$22
Name Slovakia: Data!$S$4:$S$44
Name Slovenia: Data!$T$4:$T$8

Sheet Data
G2: ACTUAL | H2: PLAN | I2: PLAN | J2: PLAN
B3: Data | D3: LINE | E3: SHOP | F3: Concatenate | G3: October YTD | H3: Nov 2022 | I3: Dec 2022 | J3: 2022 | M3: Austria
D4: Kgs put into the shop-Shop_A | E4: Paniglgasse | F4: Kgs put into the shop-Shop_APaniglgasse | G4: 3575 | H4: 300 | I4: 750 | J4: 6850 | M4: Paniglgasse
D5: Kgs put into the shop-Shop_B | E5: Paniglgasse | F5: Kgs put into the shop-Shop_BPaniglgasse | G5: 1890 | H5: 900 | I5: 600 | J5: 7250 | M5: Lerchenfelder
D6: Kgs put into the shop-Shoes_A | E6: Paniglgasse | F6: Kgs put into the shop-Shoes_APaniglgasse | G6: 312.5 | H6: 80 | I6: 160 | J6: 1520
D7: Kgs put into the shop-Shoes_B | E7: Paniglgasse | F7: Kgs put into the shop-Shoes_BPaniglgasse | G7: 0 | H7: 0 | I7: 0 | J7: 0
D8: Kgs put into the shop-HHR | E8: Paniglgasse | F8: Kgs put into the shop-HHRPaniglgasse | G8: 0 | H8: 0 | I8: 80 | J8: 800
D9: Kgs put into the shop-Mix_Summer | E9: Paniglgasse | F9: Kgs put into the shop-Mix_SummerPaniglgasse | G9: 0 | H9: 0 | I9: 0 | J9: 0
D10: Kgs put into the shop-Mix_Winter | E10: Paniglgasse | F10: Kgs put into the shop-Mix_WinterPaniglgasse | G10: 0 | H10: 0 | I10: 0 | J10: 0
D11: Kgs put into the shop-Handbag_A | E11: Paniglgasse | F11: Kgs put into the shop-Handbag_APaniglgasse | G11: 359 | H11: 40 | I11: 100 | J11: 1000
D12: Kgs put into the shop-Handbag_B | E12: Paniglgasse | F12: Kgs put into the shop-Handbag_BPaniglgasse | G12: 0 | H12: 0 | I12: 0 | J12: 0
D13: Kgs put into the shop-Things | E13: Paniglgasse | F13: Kgs put into the shop-ThingsPaniglgasse | G13: 39.5
D14: Turnover incl. VAT | E14: Paniglgasse | F14: Turnover incl. VATPaniglgasse | G14: 118687.03 | H14: 19000 | I14: 33800 | J14: 343300
D15: Income excl. VAT | E15: Paniglgasse | F15: Income excl. VATPaniglgasse | G15: 98905.858 | H15: 15833.333 | I15: 28166.667 | J15: 286083.33
D16: Cost of clothes put in the shop | E16: Paniglgasse | F16: Cost of clothes put in the shopPaniglgasse | G16: 23780.1 | H16: 3552 | I16: 5854 | J16: 57432
D17: Transport of clothes (international) | E17: Paniglgasse | F17: Transport of clothes (international)Paniglgasse | G17: 0 | H17: 400 | I17: 400 | J17: 4720
D18: Transport of clothes (local) | E18: Paniglgasse | F18: Transport of clothes (local)Paniglgasse | G18: 0 | H18: 0 | I18: 0 | J18: 0
D19: Customs brokers fees | E19: Paniglgasse | F19: Customs brokers feesPaniglgasse | G19: 0 | H19: 0 | I19: 0 | J19: 0
D20: Rent of the shop | E20: Paniglgasse | F20: Rent of the shopPaniglgasse | G20: 48594.134 | H20: 4952 | I20: 4952 | J20: 55706
D21: Electricity / heating / water | E21: Paniglgasse | F21: Electricity / heating / waterPaniglgasse | G21: 3242.44 | H21: 276 | I21: 55 | J21: 3088
D22: Maintenance, renovation | E22: Paniglgasse | F22: Maintenance, renovationPaniglgasse | G22: 3078.4 | H22: 0 | I22: 0 | J22: 9000
D23: Insurance | E23: Paniglgasse | F23: InsurancePaniglgasse | G23: 0 | H23: 0 | I23: 0 | J23: 0
D24: Acquisition of assets for buildings | E24: Paniglgasse | F24: Acquisition of assets for buildingsPaniglgasse | G24: 0 | H24: 0 | I24: 0 | J24: 2000
D25: Other (real estate fees, brokers fees, etc.) | E25: Paniglgasse | F25: Other (real estate fees, brokers fees, etc.)Paniglgasse | G25: 0 | H25: 0 | I25: 0 | J25: 0
... D59: Kgs put into the shop-Handbag_B | E59: Lerchenfelder | F59: Kgs put into the shop-Handbag_BLerchenfelder | G59: 0 | H59: 0 | I59: 0 | J59: 0
D60: Kgs put into the shop-Things | E60: Lerchenfelder | F60: Kgs put into the shop-ThingsLerchenfelder | G60: 5
D61: Turnover incl. VAT | E61: Lerchenfelder | F61: Turnover incl. VATLerchenfelder | G61: 54610 | H61: 0 | I61: 0 | J61: 0
D62: Income excl. VAT | E62: Lerchenfelder | F62: Income excl. VATLerchenfelder | G62: 45508.333 | H62: 0 | I62: 0 | J62: 0
D63: Cost of clothes put in the shop | E63: Lerchenfelder | F63: Cost of clothes put in the shopLerchenfelder | G63: 15273 | H63: 0 | I63: 0 | J63: 0
D64: Transport of clothes (international) | E64: Lerchenfelder | F64: Transport of clothes (international)Lerchenfelder | G64: 0 | H64: 0 | I64: 0 | J64: 0
D65: Transport of clothes (local) | E65: Lerchenfelder | F65: Transport of clothes (local)Lerchenfelder | G65: 0 | H65: 0 | I65: 0 | J65: 0
D66: Customs brokers fees | E66: Lerchenfelder | F66: Customs brokers feesLerchenfelder | G66: 0 | H66: 0 | I66: 0 | J66: 0
D67: Rent of the shop | E67: Lerchenfelder | F67: Rent of the shopLerchenfelder | G67: 4089.2 | H67: 0 | I67: 0 | J67: 0
D68: Electricity / heating / water | E68: Lerchenfelder | F68: Electricity / heating / waterLerchenfelder | G68: 0 | H68: 0 | I68: 0 | J68: 0
D69: Maintenance, renovation | E69: Lerchenfelder | F69: Maintenance, renovationLerchenfelder | G69: 0 | H69: 0 | I69: 0 | J69: 0
D70: Insurance | E70: Lerchenfelder | F70: InsuranceLerchenfelder | G70: 0 | H70: 0 | I70: 0 | J70: 0
D71: Acquisition of assets for buildings | E71: Lerchenfelder | F71: Acquisition of assets for buildingsLerchenfelder | G71: 0 | H71: 0 | I71: 0 | J71: 0
D72: Other (real estate fees, brokers fees, etc.) | E72: Lerchenfelder | F72: Other (real estate fees, brokers fees, etc.)Lerchenfelder | G72: 0 | H72: 0 | I72: 0 | J72: 0
... D97: Leasing of staff | E97: Lerchenfelder | F97: Leasing of staffLerchenfelder | G97: 0 | H97: 0 | I97: 0 | J97: 0

Sheet Data_Live
H2: BW | I2: BP | J2: BQ | K2: BR | V2: BW | W2: BP | X2: BQ | Y2: BR
C3: !!! | D3: Temporary employees - renamed to - Temporry employees | H3: BU | V3: BU
C4: !!! | H4: BO | Q4: Check operating result | V4: BO
H7: ACTUAL | I7: PLAN | J7: PLAN | K7: PLAN | R7: Operating result from WR | V7: ACTUAL | W7: PLAN | X7: PLAN | Y7: PLAN | AD7: Operating result Paste values | AI7: Check operating values
D8: Line | E8: SHOP | F8: Country | G8: Concatenate | H8: October YTD | I8: Nov 2022 | J8: Dec 2022 | K8: 2022 | M8: ACT | N8: BGT | R8: Line | S8: SHOP | T8: Country | U8: Concatenate | V8: October YTD | W8: Nov 2022 | X8: Dec 2022 | Y8: 2022 | AA8: ACT | AB8: BGT | AP8: SHOPS (List): | AQ8: Country | AS8: Country | AT8: File-path
C9: =VLOOKUP($F9,$AS:$AT,2,FALSE) -> [AT_WR_43_2022_SHOPS.xlsx] | D9: Kgs put into the shop-Shop_A | E9: =AP9 -> Paniglgasse | F9: =VLOOKUP($E9,$AP:$AQ,2,FALSE) -> AT | G9: =D9&E9 -> Kgs put into the shop-Shop_APaniglgasse | H9: =IFERROR(INDIRECT(CONCATENATE("'",$C9,$E9,"'","!",$H$2,$M9))+INDIRECT(CONCATENATE("'",$C9,$E9,"'","!",$H$3,$M9))+INDIRECT(CONCATENATE("'",$C9,$E9,"'","!",$H$4,$M9)),"") | I9: =IFERROR(IF(I$7="PLAN",INDIRECT(CONCATENATE("'",$C9,$E9,"'","!",$I$2,$N9)),INDIRECT(CONCATENATE("'",$C9,$E9,"'","!",$I$2,$M9))),"") | J9: =IFERROR(IF(J$7="PLAN",INDIRECT(CONCATENATE("'",$C9,$E9,"'","!",$J$2,$N9)),INDIRECT(CONCATENATE("'",$C9,$E9,"'","!",$J$2,$M9))),"") | K9: =IFERROR(IF(K$7="PLAN",INDIRECT(CONCATENATE("'",$C9,$E9,"'","!",$K$2,$N9)),INDIRECT(CONCATENATE("'",$C9,$E9,"'","!",$K$2,$M9))),"") | M9: 37 | N9: 283 | AP9: Paniglgasse | AQ9: AT
C10: =VLOOKUP($F10,$AS:$AT,2,FALSE) -> [AT_WR_43_2022_SHOPS.xlsx] | D10: Kgs put into the shop-Shop_B | E10: =E9 -> Paniglgasse | F10: =VLOOKUP($E10,$AP:$AQ,2,FALSE) -> AT | G10: =D10&E10 -> Kgs put into the shop-Shop_BPaniglgasse | H10: =IFERROR(INDIRECT(CONCATENATE("'",$C10,$E10,"'","!",$H$2,$M10))+INDIRECT(CONCATENATE("'",$C10,$E10,"'","!",$H$3,$M10))+INDIRECT(CONCATENATE("'",$C10,$E10,"'","!",$H$4,$M10)),"") | I10: =IFERROR(IF(I$7="PLAN",INDIRECT(CONCATENATE("'",$C10,$E10,"'","!",$I$2,$N10)),INDIRECT(CONCATENATE("'",$C10,$E10,"'","!",$I$2,$M10))),"") | J10: =IFERROR(IF(J$7="PLAN",INDIRECT(CONCATENATE("'",$C10,$E10,"'","!",$J$2,$N10)),INDIRECT(CONCATENATE("'",$C10,$E10,"'","!",$J$2,$M10))),"") | K10: =IFERROR(IF(K$7="PLAN",INDIRECT(CONCATENATE("'",$C10,$E10,"'","!",$K$2,$N10)),INDIRECT(CONCATENATE("'",$C10,$E10,"'","!",$K$2,$M10))),"") | M10: 38 | N10: 284 | AP10: Lerchenfelder | AQ10: AT | AS10: AT | AT10: [AT_WR_43_2022_SHOPS.xlsx]
C11: =VLOOKUP($F11,$AS:$AT,2,FALSE) -> [AT_WR_43_2022_SHOPS.xlsx] | D11: Kgs put into the shop-Shoes_A | E11: =E10 -> Paniglgasse | F11: =VLOOKUP($E11,$AP:$AQ,2,FALSE) -> AT | G11: =D11&E11 -> Kgs put into the shop-Shoes_APaniglgasse | H11: =IFERROR(INDIRECT(CONCATENATE("'",$C11,$E11,"'","!",$H$2,$M11))+INDIRECT(CONCATENATE("'",$C11,$E11,"'","!",$H$3,$M11))+INDIRECT(CONCATENATE("'",$C11,$E11,"'","!",$H$4,$M11)),"") | I11: =IFERROR(IF(I$7="PLAN",INDIRECT(CONCATENATE("'",$C11,$E11,"'","!",$I$2,$N11)),INDIRECT(CONCATENATE("'",$C11,$E11,"'","!",$I$2,$M11))),"") | J11: =IFERROR(IF(J$7="PLAN",INDIRECT(CONCATENATE("'",$C11,$E11,"'","!",$J$2,$N11)),INDIRECT(CONCATENATE("'",$C11,$E11,"'","!",$J$2,$M11))),"") | K11: =IFERROR(IF(K$7="PLAN",INDIRECT(CONCATENATE("'",$C11,$E11,"'","!",$K$2,$N11)),INDIRECT(CONCATENATE("'",$C11,$E11,"'","!",$K$2,$M11))),"") | M11: 40 | N11: 285
C12: =VLOOKUP($F12,$AS:$AT,2,FALSE) -> [AT_WR_43_2022_SHOPS.xlsx] | D12: Kgs put into the shop-Shoes_B | E12: =E11 -> Paniglgasse | F12: =VLOOKUP($E12,$AP:$AQ,2,FALSE) -> AT | G12: =D12&E12 -> Kgs put into the shop-Shoes_BPaniglgasse | H12: =IFERROR(INDIRECT(CONCATENATE("'",$C12,$E12,"'","!",$H$2,$M12))+INDIRECT(CONCATENATE("'",$C12,$E12,"'","!",$H$3,$M12))+INDIRECT(CONCATENATE("'",$C12,$E12,"'","!",$H$4,$M12)),"") | I12: =IFERROR(IF(I$7="PLAN",INDIRECT(CONCATENATE("'",$C12,$E12,"'","!",$I$2,$N12)),INDIRECT(CONCATENATE("'",$C12,$E12,"'","!",$I$2,$M12))),"") | J12: =IFERROR(IF(J$7="PLAN",INDIRECT(CONCATENATE("'",$C12,$E12,"'","!",$J$2,$N12)),INDIRECT(CONCATENATE("'",$C12,$E12,"'","!",$J$2,$M12))),"") | K12: =IFERROR(IF(K$7="PLAN",INDIRECT(CONCATENATE("'",$C12,$E12,"'","!",$K$2,$N12)),INDIRECT(CONCATENATE("'",$C12,$E12,"'","!",$K$2,$M12))),"") | M12: 41 | N12: 286
C13: =VLOOKUP($F13,$AS:$AT,2,FALSE) -> [AT_WR_43_2022_SHOPS.xlsx] | D13: Kgs put into the shop-HHR | E13: =E12 -> Paniglgasse | F13: =VLOOKUP($E13,$AP:$AQ,2,FALSE) -> AT | G13: =D13&E13 -> Kgs put into the shop-HHRPaniglgasse | H13: =IFERROR(INDIRECT(CONCATENATE("'",$C13,$E13,"'","!",$H$2,$M13))+INDIRECT(CONCATENATE("'",$C13,$E13,"'","!",$H$3,$M13))+INDIRECT(CONCATENATE("'",$C13,$E13,"'","!",$H$4,$M13)),"") | I13: =IFERROR(IF(I$7="PLAN",INDIRECT(CONCATENATE("'",$C13,$E13,"'","!",$I$2,$N13)),INDIRECT(CONCATENATE("'",$C13,$E13,"'","!",$I$2,$M13))),"") | J13: =IFERROR(IF(J$7="PLAN",INDIRECT(CONCATENATE("'",$C13,$E13,"'","!",$J$2,$N13)),INDIRECT(CONCATENATE("'",$C13,$E13,"'","!",$J$2,$M13))),"") | K13: =IFERROR(IF(K$7="PLAN",INDIRECT(CONCATENATE("'",$C13,$E13,"'","!",$K$2,$N13)),INDIRECT(CONCATENATE("'",$C13,$E13,"'","!",$K$2,$M13))),"") | M13: 39 | N13: 287
C14: =VLOOKUP($F14,$AS:$AT,2,FALSE) -> [AT_WR_43_2022_SHOPS.xlsx] | D14: Kgs put into the shop-Mix_Summer | E14: =E13 -> Paniglgasse | F14: =VLOOKUP($E14,$AP:$AQ,2,FALSE) -> AT | G14: =D14&E14 -> Kgs put into the shop-Mix_SummerPaniglgasse | H14: =IFERROR(INDIRECT(CONCATENATE("'",$C14,$E14,"'","!",$H$2,$M14))+INDIRECT(CONCATENATE("'",$C14,$E14,"'","!",$H$3,$M14))+INDIRECT(CONCATENATE("'",$C14,$E14,"'","!",$H$4,$M14)),"") | I14: =IFERROR(IF(I$7="PLAN",INDIRECT(CONCATENATE("'",$C14,$E14,"'","!",$I$2,$N14)),INDIRECT(CONCATENATE("'",$C14,$E14,"'","!",$I$2,$M14))),"") | J14: =IFERROR(IF(J$7="PLAN",INDIRECT(CONCATENATE("'",$C14,$E14,"'","!",$J$2,$N14)),INDIRECT(CONCATENATE("'",$C14,$E14,"'","!",$J$2,$M14))),"") | K14: =IFERROR(IF(K$7="PLAN",INDIRECT(CONCATENATE("'",$C14,$E14,"'","!",$K$2,$N14)),INDIRECT(CONCATENATE("'",$C14,$E14,"'","!",$K$2,$M14))),"") | M14: 42 | N14: 288
C15: =VLOOKUP($F15,$AS:$AT,2,FALSE) -> [AT_WR_43_2022_SHOPS.xlsx] | D15: Kgs put into the shop-Mix_Winter | E15: =E14 -> Paniglgasse | F15: =VLOOKUP($E15,$AP:$AQ,2,FALSE) -> AT | G15: =D15&E15 -> Kgs put into the shop-Mix_WinterPaniglgasse | H15: =IFERROR(INDIRECT(CONCATENATE("'",$C15,$E15,"'","!",$H$2,$M15))+INDIRECT(CONCATENATE("'",$C15,$E15,"'","!",$H$3,$M15))+INDIRECT(CONCATENATE("'",$C15,$E15,"'","!",$H$4,$M15)),"") | I15: =IFERROR(IF(I$7="PLAN",INDIRECT(CONCATENATE("'",$C15,$E15,"'","!",$I$2,$N15)),INDIRECT(CONCATENATE("'",$C15,$E15,"'","!",$I$2,$M15))),"") | J15: =IFERROR(IF(J$7="PLAN",INDIRECT(CONCATENATE("'",$C15,$E15,"'","!",$J$2,$N15)),INDIRECT(CONCATENATE("'",$C15,$E15,"'","!",$J$2,$M15))),"") | K15: =IFERROR(IF(K$7="PLAN",INDIRECT(CONCATENATE("'",$C15,$E15,"'","!",$K$2,$N15)),INDIRECT(CONCATENATE("'",$C15,$E15,"'","!",$K$2,$M15))),"") | M15: 43 | N15: 289
C16: =VLOOKUP($F16,$AS:$AT,2,FALSE) -> [AT_WR_43_2022_SHOPS.xlsx] | D16: Kgs put into the shop-Handbag_A | E16: =E15 -> Paniglgasse | F16: =VLOOKUP($E16,$AP:$AQ,2,FALSE) -> AT | G16: =D16&E16 -> Kgs put into the shop-Handbag_APaniglgasse | H16: =IFERROR(INDIRECT(CONCATENATE("'",$C16,$E16,"'","!",$H$2,$M16))+INDIRECT(CONCATENATE("'",$C16,$E16,"'","!",$H$3,$M16))+INDIRECT(CONCATENATE("'",$C16,$E16,"'","!",$H$4,$M16)),"") | I16: =IFERROR(IF(I$7="PLAN",INDIRECT(CONCATENATE("'",$C16,$E16,"'","!",$I$2,$N16)),INDIRECT(CONCATENATE("'",$C16,$E16,"'","!",$I$2,$M16))),"") | J16: =IFERROR(IF(J$7="PLAN",INDIRECT(CONCATENATE("'",$C16,$E16,"'","!",$J$2,$N16)),INDIRECT(CONCATENATE("'",$C16,$E16,"'","!",$J$2,$M16))),"") | K16: =IFERROR(IF(K$7="PLAN",INDIRECT(CONCATENATE("'",$C16,$E16,"'","!",$K$2,$N16)),INDIRECT(CONCATENATE("'",$C16,$E16,"'","!",$K$2,$M16))),"") | M16: 44 | N16: 290
C17: =VLOOKUP($F17,$AS:$AT,2,FALSE) -> [AT_WR_43_2022_SHOPS.xlsx] | D17: Kgs put into the shop-Handbag_B | E17: =E16 -> Paniglgasse | F17: =VLOOKUP($E17,$AP:$AQ,2,FALSE) -> AT | G17: =D17&E17 -> Kgs put into the shop-Handbag_BPaniglgasse | H17: =IFERROR(INDIRECT(CONCATENATE("'",$C17,$E17,"'","!",$H$2,$M17))+INDIRECT(CONCATENATE("'",$C17,$E17,"'","!",$H$3,$M17))+INDIRECT(CONCATENATE("'",$C17,$E17,"'","!",$H$4,$M17)),"") | I17: =IFERROR(IF(I$7="PLAN",INDIRECT(CONCATENATE("'",$C17,$E17,"'","!",$I$2,$N17)),INDIRECT(CONCATENATE("'",$C17,$E17,"'","!",$I$2,$M17))),"") | J17: =IFERROR(IF(J$7="PLAN",INDIRECT(CONCATENATE("'",$C17,$E17,"'","!",$J$2,$N17)),INDIRECT(CONCATENATE("'",$C17,$E17,"'","!",$J$2,$M17))),"") | K17: =IFERROR(IF(K$7="PLAN",INDIRECT(CONCATENATE("'",$C17,$E17,"'","!",$K$2,$N17)),INDIRECT(CONCATENATE("'",$C17,$E17,"'","!",$K$2,$M17))),"") | M17: 45 | N17: 291
C18: =VLOOKUP($F18,$AS:$AT,2,FALSE) -> [AT_WR_43_2022_SHOPS.xlsx] | D18: Kgs put into the shop-Things | E18: =E17 -> Paniglgasse | F18: =VLOOKUP($E18,$AP:$AQ,2,FALSE) -> AT | G18: =D18&E18 -> Kgs put into the shop-ThingsPaniglgasse | H18: =IFERROR(INDIRECT(CONCATENATE("'",$C18,$E18,"'","!",$H$2,$M18))+INDIRECT(CONCATENATE("'",$C18,$E18,"'","!",$H$3,$M18))+INDIRECT(CONCATENATE("'",$C18,$E18,"'","!",$H$4,$M18)),"") | I18: =IFERROR(IF(I$7="PLAN",INDIRECT(CONCATENATE("'",$C18,$E18,"'","!",$I$2,$N18)),INDIRECT(CONCATENATE("'",$C18,$E18,"'","!",$I$2,$M18))),"") | J18: =IFERROR(IF(J$7="PLAN",INDIRECT(CONCATENATE("'",$C18,$E18,"'","!",$J$2,$N18)),INDIRECT(CONCATENATE("'",$C18,$E18,"'","!",$J$2,$M18))),"") | K18: =IFERROR(IF(K$7="PLAN",INDIRECT(CONCATENATE("'",$C18,$E18,"'","!",$K$2,$N18)),INDIRECT(CONCATENATE("'",$C18,$E18,"'","!",$K$2,$M18))),"") | M18: 46
C19: =VLOOKUP($F19,$AS:$AT,2,FALSE) -> [AT_WR_43_2022_SHOPS.xlsx] | D19: Turnover incl. VAT | E19: =E18 -> Paniglgasse | F19: =VLOOKUP($E19,$AP:$AQ,2,FALSE) -> AT | G19: =D19&E19 -> Turnover incl. VATPaniglgasse | H19: =IFERROR(INDIRECT(CONCATENATE("'",$C19,$E19,"'","!",$H$2,$M19))+INDIRECT(CONCATENATE("'",$C19,$E19,"'","!",$H$3,$M19))+INDIRECT(CONCATENATE("'",$C19,$E19,"'","!",$H$4,$M19)),"") | I19: =IFERROR(IF(I$7="PLAN",INDIRECT(CONCATENATE("'",$C19,$E19,"'","!",$I$2,$N19)),INDIRECT(CONCATENATE("'",$C19,$E19,"'","!",$I$2,$M19))),"") | J19: =IFERROR(IF(J$7="PLAN",INDIRECT(CONCATENATE("'",$C19,$E19,"'","!",$J$2,$N19)),INDIRECT(CONCATENATE("'",$C19,$E19,"'","!",$J$2,$M19))),"") | K19: =IFERROR(IF(K$7="PLAN",INDIRECT(CONCATENATE("'",$C19,$E19,"'","!",$K$2,$N19)),INDIRECT(CONCATENATE("'",$C19,$E19,"'","!",$K$2,$M19))),"") | M19: 73 | N19: 302
C20: =VLOOKUP($F20,$AS:$AT,2,FALSE) -> [AT_WR_43_2022_SHOPS.xlsx] | D20: Income excl. VAT | E20: =E19 -> Paniglgasse | F20: =VLOOKUP($E20,$AP:$AQ,2,FALSE) -> AT | G20: =D20&E20 -> Income excl. VATPaniglgasse | H20: =IFERROR(INDIRECT(CONCATENATE("'",$C20,$E20,"'","!",$H$2,$M20))+INDIRECT(CONCATENATE("'",$C20,$E20,"'","!",$H$3,$M20))+INDIRECT(CONCATENATE("'",$C20,$E20,"'","!",$H$4,$M20)),"") | I20: =IFERROR(IF(I$7="PLAN",INDIRECT(CONCATENATE("'",$C20,$E20,"'","!",$I$2,$N20)),INDIRECT(CONCATENATE("'",$C20,$E20,"'","!",$I$2,$M20))),"") | J20: =IFERROR(IF(J$7="PLAN",INDIRECT(CONCATENATE("'",$C20,$E20,"'","!",$J$2,$N20)),INDIRECT(CONCATENATE("'",$C20,$E20,"'","!",$J$2,$M20))),"") | K20: =IFERROR(IF(K$7="PLAN",INDIRECT(CONCATENATE("'",$C20,$E20,"'","!",$K$2,$N20)),INDIRECT(CONCATENATE("'",$C20,$E20,"'","!",$K$2,$M20))),"") | M20: 74 | N20: 303
C21: =VLOOKUP($F21,$AS:$AT,2,FALSE) -> [AT_WR_43_2022_SHOPS.xlsx] | D21: Cost of clothes put in the shop | E21: =E20 -> Paniglgasse | F21: =VLOOKUP($E21,$AP:$AQ,2,FALSE) -> AT | G21: =D21&E21 -> Cost of clothes put in the shopPaniglgasse | H21: =IFERROR(INDIRECT(CONCATENATE("'",$C21,$E21,"'","!",$H$2,$M21))+INDIRECT(CONCATENATE("'",$C21,$E21,"'","!",$H$3,$M21))+INDIRECT(CONCATENATE("'",$C21,$E21,"'","!",$H$4,$M21)),"") | I21: =IFERROR(IF(I$7="PLAN",INDIRECT(CONCATENATE("'",$C21,$E21,"'","!",$I$2,$N21)),INDIRECT(CONCATENATE("'",$C21,$E21,"'","!",$I$2,$M21))),"") | J21: =IFERROR(IF(J$7="PLAN",INDIRECT(CONCATENATE("'",$C21,$E21,"'","!",$J$2,$N21)),INDIRECT(CONCATENATE("'",$C21,$E21,"'","!",$J$2,$M21))),"") | K21: =IFERROR(IF(K$7="PLAN",INDIRECT(CONCATENATE("'",$C21,$E21,"'","!",$K$2,$N21)),INDIRECT(CONCATENATE("'",$C21,$E21,"'","!",$K$2,$M21))),"") | M21: 82 | N21: 311
C22: =VLOOKUP($F22,$AS:$AT,2,FALSE) -> [AT_WR_43_2022_SHOPS.xlsx] | D22: Transport of clothes (international) | E22: =E21 -> Paniglgasse | F22: =VLOOKUP($E22,$AP:$AQ,2,FALSE) -> AT | G22: =D22&E22 -> Transport of clothes (international)Paniglgasse | H22: =IFERROR(INDIRECT(CONCATENATE("'",$C22,$E22,"'","!",$H$2,$M22))+INDIRECT(CONCATENATE("'",$C22,$E22,"'","!",$H$3,$M22))+INDIRECT(CONCATENATE("'",$C22,$E22,"'","!",$H$4,$M22)),"") | I22: =IFERROR(IF(I$7="PLAN",INDIRECT(CONCATENATE("'",$C22,$E22,"'","!",$I$2,$N22)),INDIRECT(CONCATENATE("'",$C22,$E22,"'","!",$I$2,$M22))),"") | J22: =IFERROR(IF(J$7="PLAN",INDIRECT(CONCATENATE("'",$C22,$E22,"'","!",$J$2,$N22)),INDIRECT(CONCATENATE("'",$C22,$E22,"'","!",$J$2,$M22))),"") | K22: =IFERROR(IF(K$7="PLAN",INDIRECT(CONCATENATE("'",$C22,$E22,"'","!",$K$2,$N22)),INDIRECT(CONCATENATE("'",$C22,$E22,"'","!",$K$2,$M22))),"") | M22: 83 | N22: 312
C23: =VLOOKUP($F23,$AS:$AT,2,FALSE) -> [AT_WR_43_2022_SHOPS.xlsx] | D23: Transport of clothes (local) | E23: =E22 -> Paniglgasse | F23: =VLOOKUP($E23,$AP:$AQ,2,FALSE) -> AT | G23: =D23&E23 -> Transport of clothes (local)Paniglgasse | H23: =IFERROR(INDIRECT(CONCATENATE("'",$C23,$E23,"'","!",$H$2,$M23))+INDIRECT(CONCATENATE("'",$C23,$E23,"'","!",$H$3,$M23))+INDIRECT(CONCATENATE("'",$C23,$E23,"'","!",$H$4,$M23)),"") | I23: =IFERROR(IF(I$7="PLAN",INDIRECT(CONCATENATE("'",$C23,$E23,"'","!",$I$2,$N23)),INDIRECT(CONCATENATE("'",$C23,$E23,"'","!",$I$2,$M23))),"") | J23: =IFERROR(IF(J$7="PLAN",INDIRECT(CONCATENATE("'",$C23,$E23,"'","!",$J$2,$N23)),INDIRECT(CONCATENATE("'",$C23,$E23,"'","!",$J$2,$M23))),"") | K23: =IFERROR(IF(K$7="PLAN",INDIRECT(CONCATENATE("'",$C23,$E23,"'","!",$K$2,$N23)),INDIRECT(CONCATENATE("'",$C23,$E23,"'","!",$K$2,$M23))),"") | M23: 84 | N23: 313
C24: =VLOOKUP($F24,$AS:$AT,2,FALSE) -> [AT_WR_43_2022_SHOPS.xlsx] | D24: Customs brokers fees | E24: =E23 -> Paniglgasse | F24: =VLOOKUP($E24,$AP:$AQ,2,FALSE) -> AT | G24: =D24&E24 -> Customs brokers feesPaniglgasse | H24: =IFERROR(INDIRECT(CONCATENATE("'",$C24,$E24,"'","!",$H$2,$M24))+INDIRECT(CONCATENATE("'",$C24,$E24,"'","!",$H$3,$M24))+INDIRECT(CONCATENATE("'",$C24,$E24,"'","!",$H$4,$M24)),"") | I24: =IFERROR(IF(I$7="PLAN",INDIRECT(CONCATENATE("'",$C24,$E24,"'","!",$I$2,$N24)),INDIRECT(CONCATENATE("'",$C24,$E24,"'","!",$I$2,$M24))),"") | J24: =IFERROR(IF(J$7="PLAN",INDIRECT(CONCATENATE("'",$C24,$E24,"'","!",$J$2,$N24)),INDIRECT(CONCATENATE("'",$C24,$E24,"'","!",$J$2,$M24))),"") | K24: =IFERROR(IF(K$7="PLAN",INDIRECT(CONCATENATE("'",$C24,$E24,"'","!",$K$2,$N24)),INDIRECT(CONCATENATE("'",$C24,$E24,"'","!",$K$2,$M24))),"") | M24: 85 | N24: 314
C25: =VLOOKUP($F25,$AS:$AT,2,FALSE) -> [AT_WR_43_2022_SHOPS.xlsx] | D25: Rent of the shop | E25: =E24 -> Paniglgasse | F25: =VLOOKUP($E25,$AP:$AQ,2,FALSE) -> AT | G25: =D25&E25 -> Rent of the shopPaniglgasse | H25: =IFERROR(INDIRECT(CONCATENATE("'",$C25,$E25,"'","!",$H$2,$M25))+INDIRECT(CONCATENATE("'",$C25,$E25,"'","!",$H$3,$M25))+INDIRECT(CONCATENATE("'",$C25,$E25,"'","!",$H$4,$M25)),"") | I25: =IFERROR(IF(I$7="PLAN",INDIRECT(CONCATENATE("'",$C25,$E25,"'","!",$I$2,$N25)),INDIRECT(CONCATENATE("'",$C25,$E25,"'","!",$I$2,$M25))),"") | J25: =IFERROR(IF(J$7="PLAN",INDIRECT(CONCATENATE("'",$C25,$E25,"'","!",$J$2,$N25)),INDIRECT(CONCATENATE("'",$C25,$E25,"'","!",$J$2,$M25))),"") | K25: =IFERROR(IF(K$7="PLAN",INDIRECT(CONCATENATE("'",$C25,$E25,"'","!",$K$2,$N25)),INDIRECT(CONCATENATE("'",$C25,$E25,"'","!",$K$2,$M25))),"") | M25: 88 | N25: 317
C26: =VLOOKUP($F26,$AS:$AT,2,FALSE) -> [AT_WR_43_2022_SHOPS.xlsx] | D26: Electricity / heating / water | E26: =E25 -> Paniglgasse | F26: =VLOOKUP($E26,$AP:$AQ,2,FALSE) -> AT | G26: =D26&E26 -> Electricity / heating / waterPaniglgasse | H26: =IFERROR(INDIRECT(CONCATENATE("'",$C26,$E26,"'","!",$H$2,$M26))+INDIRECT(CONCATENATE("'",$C26,$E26,"'","!",$H$3,$M26))+INDIRECT(CONCATENATE("'",$C26,$E26,"'","!",$H$4,$M26)),"") | I26: =IFERROR(IF(I$7="PLAN",INDIRECT(CONCATENATE("'",$C26,$E26,"'","!",$I$2,$N26)),INDIRECT(CONCATENATE("'",$C26,$E26,"'","!",$I$2,$M26))),"") | J26: =IFERROR(IF(J$7="PLAN",INDIRECT(CONCATENATE("'",$C26,$E26,"'","!",$J$2,$N26)),INDIRECT(CONCATENATE("'",$C26,$E26,"'","!",$J$2,$M26))),"") | K26: =IFERROR(IF(K$7="PLAN",INDIRECT(CONCATENATE("'",$C26,$E26,"'","!",$K$2,$N26)),INDIRECT(CONCATENATE("'",$C26,$E26,"'","!",$K$2,$M26))),"") | M26: 89 | N26: 318
C27: =VLOOKUP($F27,$AS:$AT,2,FALSE) -> [AT_WR_43_2022_SHOPS.xlsx] | D27: Maintenance, renovation | E27: =E26 -> Paniglgasse | F27: =VLOOKUP($E27,$AP:$AQ,2,FALSE) -> AT | G27: =D27&E27 -> Maintenance, renovationPaniglgasse | H27: =IFERROR(INDIRECT(CONCATENATE("'",$C27,$E27,"'","!",$H$2,$M27))+INDIRECT(CONCATENATE("'",$C27,$E27,"'","!",$H$3,$M27))+INDIRECT(CONCATENATE("'",$C27,$E27,"'","!",$H$4,$M27)),"") | I27: =IFERROR(IF(I$7="PLAN",INDIRECT(CONCATENATE("'",$C27,$E27,"'","!",$I$2,$N27)),INDIRECT(CONCATENATE("'",$C27,$E27,"'","!",$I$2,$M27))),"") | J27: =IFERROR(IF(J$7="PLAN",INDIRECT(CONCATENATE("'",$C27,$E27,"'","!",$J$2,$N27)),INDIRECT(CONCATENATE("'",$C27,$E27,"'","!",$J$2,$M27))),"") | K27: =IFERROR(IF(K$7="PLAN",INDIRECT(CONCATENATE("'",$C27,$E27,"'","!",$K$2,$N27)),INDIRECT(CONCATENATE("'",$C27,$E27,"'","!",$K$2,$M27))),"") | M27: 90 | N27: 319
C28: =VLOOKUP($F28,$AS:$AT,2,FALSE) -> [AT_WR_43_2022_SHOPS.xlsx] | D28: Insurance | E28: =E27 -> Paniglgasse | F28: =VLOOKUP($E28,$AP:$AQ,2,FALSE) -> AT | G28: =D28&E28 -> InsurancePaniglgasse | H28: =IFERROR(INDIRECT(CONCATENATE("'",$C28,$E28,"'","!",$H$2,$M28))+INDIRECT(CONCATENATE("'",$C28,$E28,"'","!",$H$3,$M28))+INDIRECT(CONCATENATE("'",$C28,$E28,"'","!",$H$4,$M28)),"") | I28: =IFERROR(IF(I$7="PLAN",INDIRECT(CONCATENATE("'",$C28,$E28,"'","!",$I$2,$N28)),INDIRECT(CONCATENATE("'",$C28,$E28,"'","!",$I$2,$M28))),"") | J28: =IFERROR(IF(J$7="PLAN",INDIRECT(CONCATENATE("'",$C28,$E28,"'","!",$J$2,$N28)),INDIRECT(CONCATENATE("'",$C28,$E28,"'","!",$J$2,$M28))),"") | K28: =IFERROR(IF(K$7="PLAN",INDIRECT(CONCATENATE("'",$C28,$E28,"'","!",$K$2,$N28)),INDIRECT(CONCATENATE("'",$C28,$E28,"'","!",$K$2,$M28))),"") | M28: 91 | N28: 320
C29: =VLOOKUP($F29,$AS:$AT,2,FALSE) -> [AT_WR_43_2022_SHOPS.xlsx] | D29: Acquisition of assets for buildings | E29: =E28 -> Paniglgasse | F29: =VLOOKUP($E29,$AP:$AQ,2,FALSE) -> AT | G29: =D29&E29 -> Acquisition of assets for buildingsPaniglgasse | H29: =IFERROR(INDIRECT(CONCATENATE("'",$C29,$E29,"'","!",$H$2,$M29))+INDIRECT(CONCATENATE("'",$C29,$E29,"'","!",$H$3,$M29))+INDIRECT(CONCATENATE("'",$C29,$E29,"'","!",$H$4,$M29)),"") | I29: =IFERROR(IF(I$7="PLAN",INDIRECT(CONCATENATE("'",$C29,$E29,"'","!",$I$2,$N29)),INDIRECT(CONCATENATE("'",$C29,$E29,"'","!",$I$2,$M29))),"") | J29: =IFERROR(IF(J$7="PLAN",INDIRECT(CONCATENATE("'",$C29,$E29,"'","!",$J$2,$N29)),INDIRECT(CONCATENATE("'",$C29,$E29,"'","!",$J$2,$M29))),"") | K29: =IFERROR(IF(K$7="PLAN",INDIRECT(CONCATENATE("'",$C29,$E29,"'","!",$K$2,$N29)),INDIRECT(CONCATENATE("'",$C29,$E29,"'","!",$K$2,$M29))),"") | M29: 92 | N29: 321
C30: =VLOOKUP($F30,$AS:$AT,2,FALSE) -> [AT_WR_43_2022_SHOPS.xlsx] | D30: Other (real estate fees, brokers fees, etc.) | E30: =E29 -> Paniglgasse | F30: =VLOOKUP($E30,$AP:$AQ,2,FALSE) -> AT | G30: =D30&E30 -> Other (real estate fees, brokers fees, etc.)Paniglgasse | H30: =IFERROR(INDIRECT(CONCATENATE("'",$C30,$E30,"'","!",$H$2,$M30))+INDIRECT(CONCATENATE("'",$C30,$E30,"'","!",$H$3,$M30))+INDIRECT(CONCATENATE("'",$C30,$E30,"'","!",$H$4,$M30)),"") | I30: =IFERROR(IF(I$7="PLAN",INDIRECT(CONCATENATE("'",$C30,$E30,"'","!",$I$2,$N30)),INDIRECT(CONCATENATE("'",$C30,$E30,"'","!",$I$2,$M30))),"") | J30: =IFERROR(IF(J$7="PLAN",INDIRECT(CONCATENATE("'",$C30,$E30,"'","!",$J$2,$N30)),INDIRECT(CONCATENATE("'",$C30,$E30,"'","!",$J$2,$M30))),"") | K30: =IFERROR(IF(K$7="PLAN",INDIRECT(CONCATENATE("'",$C30,$E30,"'","!",$K$2,$N30)),INDIRECT(CONCATENATE("'",$C30,$E30,"'","!",$K$2,$M30))),"") | M30: 93 | N30: 322
... C47: =VLOOKUP($F47,$AS:$AT,2,FALSE) -> [AT_WR_43_2022_SHOPS.xlsx] | D47: Deputy manager | E47: =E46 -> Paniglgasse | F47: =VLOOKUP($E47,$AP:$AQ,2,FALSE) -> AT | G47: =D47&E47 -> Deputy managerPaniglgasse | H47: =IFERROR(INDIRECT(CONCATENATE("'",$C47,$E47,"'","!",$H$2,$M47))+INDIRECT(CONCATENATE("'",$C47,$E47,"'","!",$H$3,$M47))+INDIRECT(CONCATENATE("'",$C47,$E47,"'","!",$H$4,$M47)),"") | I47: =IFERROR(IF(I$7="PLAN",INDIRECT(CONCATENATE("'",$C47,$E47,"'","!",$I$2,$N47)),INDIRECT(CONCATENATE("'",$C47,$E47,"'","!",$I$2,$M47))),"") | J47: =IFERROR(IF(J$7="PLAN",INDIRECT(CONCATENATE("'",$C47,$E47,"'","!",$J$2,$N47)),INDIRECT(CONCATENATE("'",$C47,$E47,"'","!",$J$2,$M47))),"") | K47: =IFERROR(IF(K$7="PLAN",INDIRECT(CONCATENATE("'",$C47,$E47,"'","!",$K$2,$N47)),INDIRECT(CONCATENATE("'",$C47,$E47,"'","!",$K$2,$M47))),"") | M47: 124 | N47: 353
C48: =VLOOKUP($F48,$AS:$AT,2,FALSE) -> [AT_WR_43_2022_SHOPS.xlsx] | D48: Assistents | E48: =E46 -> Paniglgasse | F48: =VLOOKUP($E48,$AP:$AQ,2,FALSE) -> AT | G48: =D48&E48 -> AssistentsPaniglgasse | H48: =IFERROR(INDIRECT(CONCATENATE("'",$C48,$E48,"'","!",$H$2,$M48))+INDIRECT(CONCATENATE("'",$C48,$E48,"'","!",$H$3,$M48))+INDIRECT(CONCATENATE("'",$C48,$E48,"'","!",$H$4,$M48)),"") | I48: =IFERROR(IF(I$7="PLAN",INDIRECT(CONCATENATE("'",$C48,$E48,"'","!",$I$2,$N48)),INDIRECT(CONCATENATE("'",$C48,$E48,"'","!",$I$2,$M48))),"") | J48: =IFERROR(IF(J$7="PLAN",INDIRECT(CONCATENATE("'",$C48,$E48,"'","!",$J$2,$N48)),INDIRECT(CONCATENATE("'",$C48,$E48,"'","!",$J$2,$M48))),"") | K48: =IFERROR(IF(K$7="PLAN",INDIRECT(CONCATENATE("'",$C48,$E48,"'","!",$K$2,$N48)),INDIRECT(CONCATENATE("'",$C48,$E48,"'","!",$K$2,$M48))),"") | M48: 125 | N48: 354
C49: =VLOOKUP($F49,$AS:$AT,2,FALSE) -> [AT_WR_43_2022_SHOPS.xlsx] | D49: Stock keeper | E49: =E48 -> Paniglgasse | F49: =VLOOKUP($E49,$AP:$AQ,2,FALSE) -> AT | G49: =D49&E49 -> Stock keeperPaniglgasse | H49: =IFERROR(INDIRECT(CONCATENATE("'",$C49,$E49,"'","!",$H$2,$M49))+INDIRECT(CONCATENATE("'",$C49,$E49,"'","!",$H$3,$M49))+INDIRECT(CONCATENATE("'",$C49,$E49,"'","!",$H$4,$M49)),"") | I49: =IFERROR(IF(I$7="PLAN",INDIRECT(CONCATENATE("'",$C49,$E49,"'","!",$I$2,$N49)),INDIRECT(CONCATENATE("'",$C49,$E49,"'","!",$I$2,$M49))),"") | J49: =IFERROR(IF(J$7="PLAN",INDIRECT(CONCATENATE("'",$C49,$E49,"'","!",$J$2,$N49)),INDIRECT(CONCATENATE("'",$C49,$E49,"'","!",$J$2,$M49))),"") | K49: =IFERROR(IF(K$7="PLAN",INDIRECT(CONCATENATE("'",$C49,$E49,"'","!",$K$2,$N49)),INDIRECT(CONCATENATE("'",$C49,$E49,"'","!",$K$2,$M49))),"") | M49: 126 | N49: 355
C50: =VLOOKUP($F50,$AS:$AT,2,FALSE) -> [AT_WR_43_2022_SHOPS.xlsx] | D50: Temporary employees | E50: =E49 -> Paniglgasse | F50: =VLOOKUP($E50,$AP:$AQ,2,FALSE) -> AT | G50: =D50&E50 -> Temporary employeesPaniglgasse | H50: =IFERROR(INDIRECT(CONCATENATE("'",$C50,$E50,"'","!",$H$2,$M50))+INDIRECT(CONCATENATE("'",$C50,$E50,"'","!",$H$3,$M50))+INDIRECT(CONCATENATE("'",$C50,$E50,"'","!",$H$4,$M50)),"") | I50: =IFERROR(IF(I$7="PLAN",INDIRECT(CONCATENATE("'",$C50,$E50,"'","!",$I$2,$N50)),INDIRECT(CONCATENATE("'",$C50,$E50,"'","!",$I$2,$M50))),"") | J50: =IFERROR(IF(J$7="PLAN",INDIRECT(CONCATENATE("'",$C50,$E50,"'","!",$J$2,$N50)),INDIRECT(CONCATENATE("'",$C50,$E50,"'","!",$J$2,$M50))),"") | K50: =IFERROR(IF(K$7="PLAN",INDIRECT(CONCATENATE("'",$C50,$E50,"'","!",$K$2,$N50)),INDIRECT(CONCATENATE("'",$C50,$E50,"'","!",$K$2,$M50))),"") | M50: 127 | N50: 356
C51: =VLOOKUP($F51,$AS:$AT,2,FALSE) -> [AT_WR_43_2022_SHOPS.xlsx] | D51: Shop assistants bonuses | E51: =E50 -> Paniglgasse | F51: =VLOOKUP($E51,$AP:$AQ,2,FALSE) -> AT | G51: =D51&E51 -> Shop assistants bonusesPaniglgasse | H51: =IFERROR(INDIRECT(CONCATENATE("'",$C51,$E51,"'","!",$H$2,$M51))+INDIRECT(CONCATENATE("'",$C51,$E51,"'","!",$H$3,$M51))+INDIRECT(CONCATENATE("'",$C51,$E51,"'","!",$H$4,$M51)),"") | I51: =IFERROR(IF(I$7="PLAN",INDIRECT(CONCATENATE("'",$C51,$E51,"'","!",$I$2,$N51)),INDIRECT(CONCATENATE("'",$C51,$E51,"'","!",$I$2,$M51))),"") | J51: =IFERROR(IF(J$7="PLAN",INDIRECT(CONCATENATE("'",$C51,$E51,"'","!",$J$2,$N51)),INDIRECT(CONCATENATE("'",$C51,$E51,"'","!",$J$2,$M51))),"") | K51: =IFERROR(IF(K$7="PLAN",INDIRECT(CONCATENATE("'",$C51,$E51,"'","!",$K$2,$N51)),INDIRECT(CONCATENATE("'",$C51,$E51,"'","!",$K$2,$M51))),"") | M51: 128 | N51: 357
C52: =VLOOKUP($F52,$AS:$AT,2,FALSE) -> [AT_WR_43_2022_SHOPS.xlsx] | D52: Shop manager bonuses | E52: =E51 -> Paniglgasse | F52: =VLOOKUP($E52,$AP:$AQ,2,FALSE) -> AT | G52: =D52&E52 -> Shop manager bonusesPaniglgasse | H52: =IFERROR(INDIRECT(CONCATENATE("'",$C52,$E52,"'","!",$H$2,$M52))+INDIRECT(CONCATENATE("'",$C52,$E52,"'","!",$H$3,$M52))+INDIRECT(CONCATENATE("'",$C52,$E52,"'","!",$H$4,$M52)),"") | I52: =IFERROR(IF(I$7="PLAN",INDIRECT(CONCATENATE("'",$C52,$E52,"'","!",$I$2,$N52)),INDIRECT(CONCATENATE("'",$C52,$E52,"'","!",$I$2,$M52))),"") | J52: =IFERROR(IF(J$7="PLAN",INDIRECT(CONCATENATE("'",$C52,$E52,"'","!",$J$2,$N52)),INDIRECT(CONCATENATE("'",$C52,$E52,"'","!",$J$2,$M52))),"") | K52: =IFERROR(IF(K$7="PLAN",INDIRECT(CONCATENATE("'",$C52,$E52,"'","!",$K$2,$N52)),INDIRECT(CONCATENATE("'",$C52,$E52,"'","!",$K$2,$M52))),"") | M52: 129 | N52: 358
C53: =VLOOKUP($F53,$AS:$AT,2,FALSE) -> [AT_WR_43_2022_SHOPS.xlsx] | D53: Social tax | E53: =E52 -> Paniglgasse | F53: =VLOOKUP($E53,$AP:$AQ,2,FALSE) -> AT | G53: =D53&E53 -> Social taxPaniglgasse | H53: =IFERROR(INDIRECT(CONCATENATE("'",$C53,$E53,"'","!",$H$2,$M53))+INDIRECT(CONCATENATE("'",$C53,$E53,"'","!",$H$3,$M53))+INDIRECT(CONCATENATE("'",$C53,$E53,"'","!",$H$4,$M53)),"") | I53: =IFERROR(IF(I$7="PLAN",INDIRECT(CONCATENATE("'",$C53,$E53,"'","!",$I$2,$N53)),INDIRECT(CONCATENATE("'",$C53,$E53,"'","!",$I$2,$M53))),"") | J53: =IFERROR(IF(J$7="PLAN",INDIRECT(CONCATENATE("'",$C53,$E53,"'","!",$J$2,$N53)),INDIRECT(CONCATENATE("'",$C53,$E53,"'","!",$J$2,$M53))),"") | K53: =IFERROR(IF(K$7="PLAN",INDIRECT(CONCATENATE("'",$C53,$E53,"'","!",$K$2,$N53)),INDIRECT(CONCATENATE("'",$C53,$E53,"'","!",$K$2,$M53))),"") | M53: 130 | N53: 359
C54: =VLOOKUP($F54,$AS:$AT,2,FALSE) -> [AT_WR_43_2022_SHOPS.xlsx] | D54: Benefits | E54: =E53 -> Paniglgasse | F54: =VLOOKUP($E54,$AP:$AQ,2,FALSE) -> AT | G54: =D54&E54 -> BenefitsPaniglgasse | H54: =IFERROR(INDIRECT(CONCATENATE("'",$C54,$E54,"'","!",$H$2,$M54))+INDIRECT(CONCATENATE("'",$C54,$E54,"'","!",$H$3,$M54))+INDIRECT(CONCATENATE("'",$C54,$E54,"'","!",$H$4,$M54)),"") | I54: =IFERROR(IF(I$7="PLAN",INDIRECT(CONCATENATE("'",$C54,$E54,"'","!",$I$2,$N54)),INDIRECT(CONCATENATE("'",$C54,$E54,"'","!",$I$2,$M54))),"") | J54: =IFERROR(IF(J$7="PLAN",INDIRECT(CONCATENATE("'",$C54,$E54,"'","!",$J$2,$N54)),INDIRECT(CONCATENATE("'",$C54,$E54,"'","!",$J$2,$M54))),"") | K54: =IFERROR(IF(K$7="PLAN",INDIRECT(CONCATENATE("'",$C54,$E54,"'","!",$K$2,$N54)),INDIRECT(CONCATENATE("'",$C54,$E54,"'","!",$K$2,$M54))),"") | M54: 131 | N54: 360
C55: =VLOOKUP($F55,$AS:$AT,2,FALSE) -> [AT_WR_43_2022_SHOPS.xlsx] | D55: Leasing of staff | E55: =E54 -> Paniglgasse | F55: =VLOOKUP($E55,$AP:$AQ,2,FALSE) -> AT | G55: =D55&E55 -> Leasing of staffPaniglgasse | H55: =IFERROR(INDIRECT(CONCATENATE("'",$C55,$E55,"'","!",$H$2,$M55))+INDIRECT(CONCATENATE("'",$C55,$E55,"'","!",$H$3,$M55))+INDIRECT(CONCATENATE("'",$C55,$E55,"'","!",$H$4,$M55)),"") | I55: =IFERROR(IF(I$7="PLAN",INDIRECT(CONCATENATE("'",$C55,$E55,"'","!",$I$2,$N55)),INDIRECT(CONCATENATE("'",$C55,$E55,"'","!",$I$2,$M55))),"") | J55: =IFERROR(IF(J$7="PLAN",INDIRECT(CONCATENATE("'",$C55,$E55,"'","!",$J$2,$N55)),INDIRECT(CONCATENATE("'",$C55,$E55,"'","!",$J$2,$M55))),"") | K55: =IFERROR(IF(K$7="PLAN",INDIRECT(CONCATENATE("'",$C55,$E55,"'","!",$K$2,$N55)),INDIRECT(CONCATENATE("'",$C55,$E55,"'","!",$K$2,$M55))),"") | M55: 132 | N55: 361 | Q55: =VLOOKUP($F55,$AS:$AT,2,FALSE) -> [AT_WR_43_2022_SHOPS.xlsx] | R55: Operating Result | S55: =+E55 -> Paniglgasse | T55: =VLOOKUP($E55,$AP:$AQ,2,FALSE) -> AT | U55: =R55&S55 -> Operating ResultPaniglgasse | V55: =IFERROR(INDIRECT(CONCATENATE("'",$Q55,$S55,"'","!",$V$2,$AA55))+INDIRECT(CONCATENATE("'",$Q55,$S55,"'","!",$V$3,$AA55))+INDIRECT(CONCATENATE("'",$C55,$E55,"'","!",$V$4,$AA55)),"") | W55: =IFERROR(IF(W$7="PLAN",INDIRECT(CONCATENATE("'",$Q55,$S55,"'","!",$W$2,$AB55)),INDIRECT(CONCATENATE("'",$Q55,$S55,"'","!",$I$2,$AA55))),"") | X55: =IFERROR(IF(X$7="PLAN",INDIRECT(CONCATENATE("'",$Q55,$S55,"'","!",$X$2,$AB55)),INDIRECT(CONCATENATE("'",$Q55,$S55,"'","!",$X$2,$AA55))),"") | Y55: =IFERROR(IF(Y$7="PLAN",INDIRECT(CONCATENATE("'",$Q55,$S55,"'","!",$Y$2,$AB55)),INDIRECT(CONCATENATE("'",$C55,$E55,"'","!",$K$2,$AA55))),"") | AA55: 136 | AB55: 365 | AD55: -71196.983 | AE55: -4301.6827 | AF55: -4039.6513 | AG55: 8581.9543 | AI55: =+H20-SUM(H21:H55)-AD55 -> #VALUE! | AJ55: =+I20-SUM(I21:I55)-AE55 -> #VALUE! | AK55: =+J20-SUM(J21:J55)-AF55 -> #VALUE! | AL55: =+K20-SUM(K21:K55)-AG55 -> #VALUE!
C56: =VLOOKUP($F56,$AS:$AT,2,FALSE) -> [AT_WR_43_2022_SHOPS.xlsx] | D56: Kgs put into the shop-Shop_A | E56: =AP10 -> Lerchenfelder | F56: =VLOOKUP($E56,$AP:$AQ,2,FALSE) -> AT | G56: =D56&E56 -> Kgs put into the shop-Shop_ALerchenfelder | H56: =IFERROR(INDIRECT(CONCATENATE("'",$C56,$E56,"'","!",$H$2,$M56))+INDIRECT(CONCATENATE("'",$C56,$E56,"'","!",$H$3,$M56))+INDIRECT(CONCATENATE("'",$C56,$E56,"'","!",$H$4,$M56)),"") | I56: =IFERROR(IF(I$7="PLAN",INDIRECT(CONCATENATE("'",$C56,$E56,"'","!",$I$2,$N56)),INDIRECT(CONCATENATE("'",$C56,$E56,"'","!",$I$2,$M56))),"") | J56: =IFERROR(IF(J$7="PLAN",INDIRECT(CONCATENATE("'",$C56,$E56,"'","!",$J$2,$N56)),INDIRECT(CONCATENATE("'",$C56,$E56,"'","!",$J$2,$M56))),"") | K56: =IFERROR(IF(K$7="PLAN",INDIRECT(CONCATENATE("'",$C56,$E56,"'","!",$K$2,$N56)),INDIRECT(CONCATENATE("'",$C56,$E56,"'","!",$K$2,$M56))),"") | M56: 37 | N56: 283
C57: =VLOOKUP($F57,$AS:$AT,2,FALSE) -> [AT_WR_43_2022_SHOPS.xlsx] | D57: Kgs put into the shop-Shop_B | E57: =E56 -> Lerchenfelder | F57: =VLOOKUP($E57,$AP:$AQ,2,FALSE) -> AT | G57: =D57&E57 -> Kgs put into the shop-Shop_BLerchenfelder | H57: =IFERROR(INDIRECT(CONCATENATE("'",$C57,$E57,"'","!",$H$2,$M57))+INDIRECT(CONCATENATE("'",$C57,$E57,"'","!",$H$3,$M57))+INDIRECT(CONCATENATE("'",$C57,$E57,"'","!",$H$4,$M57)),"") | I57: =IFERROR(IF(I$7="PLAN",INDIRECT(CONCATENATE("'",$C57,$E57,"'","!",$I$2,$N57)),INDIRECT(CONCATENATE("'",$C57,$E57,"'","!",$I$2,$M57))),"") | J57: =IFERROR(IF(J$7="PLAN",INDIRECT(CONCATENATE("'",$C57,$E57,"'","!",$J$2,$N57)),INDIRECT(CONCATENATE("'",$C57,$E57,"'","!",$J$2,$M57))),"") | K57: =IFERROR(IF(K$7="PLAN",INDIRECT(CONCATENATE("'",$C57,$E57,"'","!",$K$2,$N57)),INDIRECT(CONCATENATE("'",$C57,$E57,"'","!",$K$2,$M57))),"") | M57: 38 | N57: 284
C58: =VLOOKUP($F58,$AS:$AT,2,FALSE) -> [AT_WR_43_2022_SHOPS.xlsx] | D58: Kgs put into the shop-Shoes_A | E58: =E57 -> Lerchenfelder | F58: =VLOOKUP($E58,$AP:$AQ,2,FALSE) -> AT | G58: =D58&E58 -> Kgs put into the shop-Shoes_ALerchenfelder | H58: =IFERROR(INDIRECT(CONCATENATE("'",$C58,$E58,"'","!",$H$2,$M58))+INDIRECT(CONCATENATE("'",$C58,$E58,"'","!",$H$3,$M58))+INDIRECT(CONCATENATE("'",$C58,$E58,"'","!",$H$4,$M58)),"") | I58: =IFERROR(IF(I$7="PLAN",INDIRECT(CONCATENATE("'",$C58,$E58,"'","!",$I$2,$N58)),INDIRECT(CONCATENATE("'",$C58,$E58,"'","!",$I$2,$M58))),"") | J58: =IFERROR(IF(J$7="PLAN",INDIRECT(CONCATENATE("'",$C58,$E58,"'","!",$J$2,$N58)),INDIRECT(CONCATENATE("'",$C58,$E58,"'","!",$J$2,$M58))),"") | K58: =IFERROR(IF(K$7="PLAN",INDIRECT(CONCATENATE("'",$C58,$E58,"'","!",$K$2,$N58)),INDIRECT(CONCATENATE("'",$C58,$E58,"'","!",$K$2,$M58))),"") | M58: 40 | N58: 285
C59: =VLOOKUP($F59,$AS:$AT,2,FALSE) -> [AT_WR_43_2022_SHOPS.xlsx] | D59: Kgs put into the shop-Shoes_B | E59: =E58 -> Lerchenfelder | F59: =VLOOKUP($E59,$AP:$AQ,2,FALSE) -> AT | G59: =D59&E59 -> Kgs put into the shop-Shoes_BLerchenfelder | H59: =IFERROR(INDIRECT(CONCATENATE("'",$C59,$E59,"'","!",$H$2,$M59))+INDIRECT(CONCATENATE("'",$C59,$E59,"'","!",$H$3,$M59))+INDIRECT(CONCATENATE("'",$C59,$E59,"'","!",$H$4,$M59)),"") | I59: =IFERROR(IF(I$7="PLAN",INDIRECT(CONCATENATE("'",$C59,$E59,"'","!",$I$2,$N59)),INDIRECT(CONCATENATE("'",$C59,$E59,"'","!",$I$2,$M59))),"") | J59: =IFERROR(IF(J$7="PLAN",INDIRECT(CONCATENATE("'",$C59,$E59,"'","!",$J$2,$N59)),INDIRECT(CONCATENATE("'",$C59,$E59,"'","!",$J$2,$M59))),"") | K59: =IFERROR(IF(K$7="PLAN",INDIRECT(CONCATENATE("'",$C59,$E59,"'","!",$K$2,$N59)),INDIRECT(CONCATENATE("'",$C59,$E59,"'","!",$K$2,$M59))),"") | M59: 41 | N59: 286
C60: =VLOOKUP($F60,$AS:$AT,2,FALSE) -> [AT_WR_43_2022_SHOPS.xlsx] | D60: Kgs put into the shop-HHR | E60: =E59 -> Lerchenfelder | F60: =VLOOKUP($E60,$AP:$AQ,2,FALSE) -> AT | G60: =D60&E60 -> Kgs put into the shop-HHRLerchenfelder | H60: =IFERROR(INDIRECT(CONCATENATE("'",$C60,$E60,"'","!",$H$2,$M60))+INDIRECT(CONCATENATE("'",$C60,$E60,"'","!",$H$3,$M60))+INDIRECT(CONCATENATE("'",$C60,$E60,"'","!",$H$4,$M60)),"") | I60: =IFERROR(IF(I$7="PLAN",INDIRECT(CONCATENATE("'",$C60,$E60,"'","!",$I$2,$N60)),INDIRECT(CONCATENATE("'",$C60,$E60,"'","!",$I$2,$M60))),"") | J60: =IFERROR(IF(J$7="PLAN",INDIRECT(CONCATENATE("'",$C60,$E60,"'","!",$J$2,$N60)),INDIRECT(CONCATENATE("'",$C60,$E60,"'","!",$J$2,$M60))),"") | K60: =IFERROR(IF(K$7="PLAN",INDIRECT(CONCATENATE("'",$C60,$E60,"'","!",$K$2,$N60)),INDIRECT(CONCATENATE("'",$C60,$E60,"'","!",$K$2,$M60))),"") | M60: 39 | N60: 287
C61: =VLOOKUP($F61,$AS:$AT,2,FALSE) -> [AT_WR_43_2022_SHOPS.xlsx] | D61: Kgs put into the shop-Mix_Summer | E61: =E60 -> Lerchenfelder | F61: =VLOOKUP($E61,$AP:$AQ,2,FALSE) -> AT | G61: =D61&E61 -> Kgs put into the shop-Mix_SummerLerchenfelder | H61: =IFERROR(INDIRECT(CONCATENATE("'",$C61,$E61,"'","!",$H$2,$M61))+INDIRECT(CONCATENATE("'",$C61,$E61,"'","!",$H$3,$M61))+INDIRECT(CONCATENATE("'",$C61,$E61,"'","!",$H$4,$M61)),"") | I61: =IFERROR(IF(I$7="PLAN",INDIRECT(CONCATENATE("'",$C61,$E61,"'","!",$I$2,$N61)),INDIRECT(CONCATENATE("'",$C61,$E61,"'","!",$I$2,$M61))),"") | J61: =IFERROR(IF(J$7="PLAN",INDIRECT(CONCATENATE("'",$C61,$E61,"'","!",$J$2,$N61)),INDIRECT(CONCATENATE("'",$C61,$E61,"'","!",$J$2,$M61))),"") | K61: =IFERROR(IF(K$7="PLAN",INDIRECT(CONCATENATE("'",$C61,$E61,"'","!",$K$2,$N61)),INDIRECT(CONCATENATE("'",$C61,$E61,"'","!",$K$2,$M61))),"") | M61: 42 | N61: 288
C62: =VLOOKUP($F62,$AS:$AT,2,FALSE) -> [AT_WR_43_2022_SHOPS.xlsx] | D62: Kgs put into the shop-Mix_Winter | E62: =E61 -> Lerchenfelder | F62: =VLOOKUP($E62,$AP:$AQ,2,FALSE) -> AT | G62: =D62&E62 -> Kgs put into the shop-Mix_WinterLerchenfelder | H62: =IFERROR(INDIRECT(CONCATENATE("'",$C62,$E62,"'","!",$H$2,$M62))+INDIRECT(CONCATENATE("'",$C62,$E62,"'","!",$H$3,$M62))+INDIRECT(CONCATENATE("'",$C62,$E62,"'","!",$H$4,$M62)),"") | I62: =IFERROR(IF(I$7="PLAN",INDIRECT(CONCATENATE("'",$C62,$E62,"'","!",$I$2,$N62)),INDIRECT(CONCATENATE("'",$C62,$E62,"'","!",$I$2,$M62))),"") | J62: =IFERROR(IF(J$7="PLAN",INDIRECT(CONCATENATE("'",$C62,$E62,"'","!",$J$2,$N62)),INDIRECT(CONCATENATE("'",$C62,$E62,"'","!",$J$2,$M62))),"") | K62: =IFERROR(IF(K$7="PLAN",INDIRECT(CONCATENATE("'",$C62,$E62,"'","!",$K$2,$N62)),INDIRECT(CONCATENATE("'",$C62,$E62,"'","!",$K$2,$M62))),"") | M62: 43 | N62: 289
C63: =VLOOKUP($F63,$AS:$AT,2,FALSE) -> [AT_WR_43_2022_SHOPS.xlsx] | D63: Kgs put into the shop-Handbag_A | E63: =E62 -> Lerchenfelder | F63: =VLOOKUP($E63,$AP:$AQ,2,FALSE) -> AT | G63: =D63&E63 -> Kgs put into the shop-Handbag_ALerchenfelder | H63: =IFERROR(INDIRECT(CONCATENATE("'",$C63,$E63,"'","!",$H$2,$M63))+INDIRECT(CONCATENATE("'",$C63,$E63,"'","!",$H$3,$M63))+INDIRECT(CONCATENATE("'",$C63,$E63,"'","!",$H$4,$M63)),"") | I63: =IFERROR(IF(I$7="PLAN",INDIRECT(CONCATENATE("'",$C63,$E63,"'","!",$I$2,$N63)),INDIRECT(CONCATENATE("'",$C63,$E63,"'","!",$I$2,$M63))),"") | J63: =IFERROR(IF(J$7="PLAN",INDIRECT(CONCATENATE("'",$C63,$E63,"'","!",$J$2,$N63)),INDIRECT(CONCATENATE("'",$C63,$E63,"'","!",$J$2,$M63))),"") | K63: =IFERROR(IF(K$7="PLAN",INDIRECT(CONCATENATE("'",$C63,$E63,"'","!",$K$2,$N63)),INDIRECT(CONCATENATE("'",$C63,$E63,"'","!",$K$2,$M63))),"") | M63: 44 | N63: 290
C64: =VLOOKUP($F64,$AS:$AT,2,FALSE) -> [AT_WR_43_2022_SHOPS.xlsx] | D64: Kgs put into the shop-Handbag_B | E64: =E63 -> Lerchenfelder | F64: =VLOOKUP($E64,$AP:$AQ,2,FALSE) -> AT | G64: =D64&E64 -> Kgs put into the shop-Handbag_BLerchenfelder | H64: =IFERROR(INDIRECT(CONCATENATE("'",$C64,$E64,"'","!",$H$2,$M64))+INDIRECT(CONCATENATE("'",$C64,$E64,"'","!",$H$3,$M64))+INDIRECT(CONCATENATE("'",$C64,$E64,"'","!",$H$4,$M64)),"") | I64: =IFERROR(IF(I$7="PLAN",INDIRECT(CONCATENATE("'",$C64,$E64,"'","!",$I$2,$N64)),INDIRECT(CONCATENATE("'",$C64,$E64,"'","!",$I$2,$M64))),"") | J64: =IFERROR(IF(J$7="PLAN",INDIRECT(CONCATENATE("'",$C64,$E64,"'","!",$J$2,$N64)),INDIRECT(CONCATENATE("'",$C64,$E64,"'","!",$J$2,$M64))),"") | K64: =IFERROR(IF(K$7="PLAN",INDIRECT(CONCATENATE("'",$C64,$E64,"'","!",$K$2,$N64)),INDIRECT(CONCATENATE("'",$C64,$E64,"'","!",$K$2,$M64))),"") | M64: 45 | N64: 291
C65: =VLOOKUP($F65,$AS:$AT,2,FALSE) -> [AT_WR_43_2022_SHOPS.xlsx] | D65: Kgs put into the shop-Things | E65: =E64 -> Lerchenfelder | F65: =VLOOKUP($E65,$AP:$AQ,2,FALSE) -> AT | G65: =D65&E65 -> Kgs put into the shop-ThingsLerchenfelder | H65: =IFERROR(INDIRECT(CONCATENATE("'",$C65,$E65,"'","!",$H$2,$M65))+INDIRECT(CONCATENATE("'",$C65,$E65,"'","!",$H$3,$M65))+INDIRECT(CONCATENATE("'",$C65,$E65,"'","!",$H$4,$M65)),"") | I65: =IFERROR(IF(I$7="PLAN",INDIRECT(CONCATENATE("'",$C65,$E65,"'","!",$I$2,$N65)),INDIRECT(CONCATENATE("'",$C65,$E65,"'","!",$I$2,$M65))),"") | J65: =IFERROR(IF(J$7="PLAN",INDIRECT(CONCATENATE("'",$C65,$E65,"'","!",$J$2,$N65)),INDIRECT(CONCATENATE("'",$C65,$E65,"'","!",$J$2,$M65))),"") | K65: =IFERROR(IF(K$7="PLAN",INDIRECT(CONCATENATE("'",$C65,$E65,"'","!",$K$2,$N65)),INDIRECT(CONCATENATE("'",$C65,$E65,"'","!",$K$2,$M65))),"") | M65: 46
C66: =VLOOKUP($F66,$AS:$AT,2,FALSE) -> [AT_WR_43_2022_SHOPS.xlsx] | D66: Turnover incl. VAT | E66: =E65 -> Lerchenfelder | F66: =VLOOKUP($E66,$AP:$AQ,2,FALSE) -> AT | G66: =D66&E66 -> Turnover incl. VATLerchenfelder | H66: =IFERROR(INDIRECT(CONCATENATE("'",$C66,$E66,"'","!",$H$2,$M66))+INDIRECT(CONCATENATE("'",$C66,$E66,"'","!",$H$3,$M66))+INDIRECT(CONCATENATE("'",$C66,$E66,"'","!",$H$4,$M66)),"") | I66: =IFERROR(IF(I$7="PLAN",INDIRECT(CONCATENATE("'",$C66,$E66,"'","!",$I$2,$N66)),INDIRECT(CONCATENATE("'",$C66,$E66,"'","!",$I$2,$M66))),"") | J66: =IFERROR(IF(J$7="PLAN",INDIRECT(CONCATENATE("'",$C66,$E66,"'","!",$J$2,$N66)),INDIRECT(CONCATENATE("'",$C66,$E66,"'","!",$J$2,$M66))),"") | K66: =IFERROR(IF(K$7="PLAN",INDIRECT(CONCATENATE("'",$C66,$E66,"'","!",$K$2,$N66)),INDIRECT(CONCATENATE("'",$C66,$E66,"'","!",$K$2,$M66))),"") | M66: 73 | N66: 302
C67: =VLOOKUP($F67,$AS:$AT,2,FALSE) -> [AT_WR_43_2022_SHOPS.xlsx] | D67: Income excl. VAT | E67: =E66 -> Lerchenfelder | F67: =VLOOKUP($E67,$AP:$AQ,2,FALSE) -> AT | G67: =D67&E67 -> Income excl. VATLerchenfelder | H67: =IFERROR(INDIRECT(CONCATENATE("'",$C67,$E67,"'","!",$H$2,$M67))+INDIRECT(CONCATENATE("'",$C67,$E67,"'","!",$H$3,$M67))+INDIRECT(CONCATENATE("'",$C67,$E67,"'","!",$H$4,$M67)),"") | I67: =IFERROR(IF(I$7="PLAN",INDIRECT(CONCATENATE("'",$C67,$E67,"'","!",$I$2,$N67)),INDIRECT(CONCATENATE("'",$C67,$E67,"'","!",$I$2,$M67))),"") | J67: =IFERROR(IF(J$7="PLAN",INDIRECT(CONCATENATE("'",$C67,$E67,"'","!",$J$2,$N67)),INDIRECT(CONCATENATE("'",$C67,$E67,"'","!",$J$2,$M67))),"") | K67: =IFERROR(IF(K$7="PLAN",INDIRECT(CONCATENATE("'",$C67,$E67,"'","!",$K$2,$N67)),INDIRECT(CONCATENATE("'",$C67,$E67,"'","!",$K$2,$M67))),"") | M67: 74 | N67: 303
C68: =VLOOKUP($F68,$AS:$AT,2,FALSE) -> [AT_WR_43_2022_SHOPS.xlsx] | D68: Cost of clothes put in the shop | E68: =E67 -> Lerchenfelder | F68: =VLOOKUP($E68,$AP:$AQ,2,FALSE) -> AT | G68: =D68&E68 -> Cost of clothes put in the shopLerchenfelder | H68: =IFERROR(INDIRECT(CONCATENATE("'",$C68,$E68,"'","!",$H$2,$M68))+INDIRECT(CONCATENATE("'",$C68,$E68,"'","!",$H$3,$M68))+INDIRECT(CONCATENATE("'",$C68,$E68,"'","!",$H$4,$M68)),"") | I68: =IFERROR(IF(I$7="PLAN",INDIRECT(CONCATENATE("'",$C68,$E68,"'","!",$I$2,$N68)),INDIRECT(CONCATENATE("'",$C68,$E68,"'","!",$I$2,$M68))),"") | J68: =IFERROR(IF(J$7="PLAN",INDIRECT(CONCATENATE("'",$C68,$E68,"'","!",$J$2,$N68)),INDIRECT(CONCATENATE("'",$C68,$E68,"'","!",$J$2,$M68))),"") | K68: =IFERROR(IF(K$7="PLAN",INDIRECT(CONCATENATE("'",$C68,$E68,"'","!",$K$2,$N68)),INDIRECT(CONCATENATE("'",$C68,$E68,"'","!",$K$2,$M68))),"") | M68: 82 | N68: 311
C69: =VLOOKUP($F69,$AS:$AT,2,FALSE) -> [AT_WR_43_2022_SHOPS.xlsx] | D69: Transport of clothes (international) | E69: =E68 -> Lerchenfelder | F69: =VLOOKUP($E69,$AP:$AQ,2,FALSE) -> AT | G69: =D69&E69 -> Transport of clothes (international)Lerchenfelder | H69: =IFERROR(INDIRECT(CONCATENATE("'",$C69,$E69,"'","!",$H$2,$M69))+INDIRECT(CONCATENATE("'",$C69,$E69,"'","!",$H$3,$M69))+INDIRECT(CONCATENATE("'",$C69,$E69,"'","!",$H$4,$M69)),"") | I69: =IFERROR(IF(I$7="PLAN",INDIRECT(CONCATENATE("'",$C69,$E69,"'","!",$I$2,$N69)),INDIRECT(CONCATENATE("'",$C69,$E69,"'","!",$I$2,$M69))),"") | J69: =IFERROR(IF(J$7="PLAN",INDIRECT(CONCATENATE("'",$C69,$E69,"'","!",$J$2,$N69)),INDIRECT(CONCATENATE("'",$C69,$E69,"'","!",$J$2,$M69))),"") | K69: =IFERROR(IF(K$7="PLAN",INDIRECT(CONCATENATE("'",$C69,$E69,"'","!",$K$2,$N69)),INDIRECT(CONCATENATE("'",$C69,$E69,"'","!",$K$2,$M69))),"") | M69: 83 | N69: 312
C70: =VLOOKUP($F70,$AS:$AT,2,FALSE) -> [AT_WR_43_2022_SHOPS.xlsx] | D70: Transport of clothes (local) | E70: =E69 -> Lerchenfelder | F70: =VLOOKUP($E70,$AP:$AQ,2,FALSE) -> AT | G70: =D70&E70 -> Transport of clothes (local)Lerchenfelder | H70: =IFERROR(INDIRECT(CONCATENATE("'",$C70,$E70,"'","!",$H$2,$M70))+INDIRECT(CONCATENATE("'",$C70,$E70,"'","!",$H$3,$M70))+INDIRECT(CONCATENATE("'",$C70,$E70,"'","!",$H$4,$M70)),"") | I70: =IFERROR(IF(I$7="PLAN",INDIRECT(CONCATENATE("'",$C70,$E70,"'","!",$I$2,$N70)),INDIRECT(CONCATENATE("'",$C70,$E70,"'","!",$I$2,$M70))),"") | J70: =IFERROR(IF(J$7="PLAN",INDIRECT(CONCATENATE("'",$C70,$E70,"'","!",$J$2,$N70)),INDIRECT(CONCATENATE("'",$C70,$E70,"'","!",$J$2,$M70))),"") | K70: =IFERROR(IF(K$7="PLAN",INDIRECT(CONCATENATE("'",$C70,$E70,"'","!",$K$2,$N70)),INDIRECT(CONCATENATE("'",$C70,$E70,"'","!",$K$2,$M70))),"") | M70: 84 | N70: 313
C71: =VLOOKUP($F71,$AS:$AT,2,FALSE) -> [AT_WR_43_2022_SHOPS.xlsx] | D71: Customs brokers fees | E71: =E70 -> Lerchenfelder | F71: =VLOOKUP($E71,$AP:$AQ,2,FALSE) -> AT | G71: =D71&E71 -> Customs brokers feesLerchenfelder | H71: =IFERROR(INDIRECT(CONCATENATE("'",$C71,$E71,"'","!",$H$2,$M71))+INDIRECT(CONCATENATE("'",$C71,$E71,"'","!",$H$3,$M71))+INDIRECT(CONCATENATE("'",$C71,$E71,"'","!",$H$4,$M71)),"") | I71: =IFERROR(IF(I$7="PLAN",INDIRECT(CONCATENATE("'",$C71,$E71,"'","!",$I$2,$N71)),INDIRECT(CONCATENATE("'",$C71,$E71,"'","!",$I$2,$M71))),"") | J71: =IFERROR(IF(J$7="PLAN",INDIRECT(CONCATENATE("'",$C71,$E71,"'","!",$J$2,$N71)),INDIRECT(CONCATENATE("'",$C71,$E71,"'","!",$J$2,$M71))),"") | K71: =IFERROR(IF(K$7="PLAN",INDIRECT(CONCATENATE("'",$C71,$E71,"'","!",$K$2,$N71)),INDIRECT(CONCATENATE("'",$C71,$E71,"'","!",$K$2,$M71))),"") | M71: 85 | N71: 314
C72: =VLOOKUP($F72,$AS:$AT,2,FALSE) -> [AT_WR_43_2022_SHOPS.xlsx] | D72: Rent of the shop | E72: =E71 -> Lerchenfelder | F72: =VLOOKUP($E72,$AP:$AQ,2,FALSE) -> AT | G72: =D72&E72 -> Rent of the shopLerchenfelder | H72: =IFERROR(INDIRECT(CONCATENATE("'",$C72,$E72,"'","!",$H$2,$M72))+INDIRECT(CONCATENATE("'",$C72,$E72,"'","!",$H$3,$M72))+INDIRECT(CONCATENATE("'",$C72,$E72,"'","!",$H$4,$M72)),"") | I72: =IFERROR(IF(I$7="PLAN",INDIRECT(CONCATENATE("'",$C72,$E72,"'","!",$I$2,$N72)),INDIRECT(CONCATENATE("'",$C72,$E72,"'","!",$I$2,$M72))),"") | J72: =IFERROR(IF(J$7="PLAN",INDIRECT(CONCATENATE("'",$C72,$E72,"'","!",$J$2,$N72)),INDIRECT(CONCATENATE("'",$C72,$E72,"'","!",$J$2,$M72))),"") | K72: =IFERROR(IF(K$7="PLAN",INDIRECT(CONCATENATE("'",$C72,$E72,"'","!",$K$2,$N72)),INDIRECT(CONCATENATE("'",$C72,$E72,"'","!",$K$2,$M72))),"") | M72: 88 | N72: 317
C73: =VLOOKUP($F73,$AS:$AT,2,FALSE) -> [AT_WR_43_2022_SHOPS.xlsx] | D73: Electricity / heating / water | E73: =E72 -> Lerchenfelder | F73: =VLOOKUP($E73,$AP:$AQ,2,FALSE) -> AT | G73: =D73&E73 -> Electricity / heating / waterLerchenfelder | H73: =IFERROR(INDIRECT(CONCATENATE("'",$C73,$E73,"'","!",$H$2,$M73))+INDIRECT(CONCATENATE("'",$C73,$E73,"'","!",$H$3,$M73))+INDIRECT(CONCATENATE("'",$C73,$E73,"'","!",$H$4,$M73)),"") | I73: =IFERROR(IF(I$7="PLAN",INDIRECT(CONCATENATE("'",$C73,$E73,"'","!",$I$2,$N73)),INDIRECT(CONCATENATE("'",$C73,$E73,"'","!",$I$2,$M73))),"") | J73: =IFERROR(IF(J$7="PLAN",INDIRECT(CONCATENATE("'",$C73,$E73,"'","!",$J$2,$N73)),INDIRECT(CONCATENATE("'",$C73,$E73,"'","!",$J$2,$M73))),"") | K73: =IFERROR(IF(K$7="PLAN",INDIRECT(CONCATENATE("'",$C73,$E73,"'","!",$K$2,$N73)),INDIRECT(CONCATENATE("'",$C73,$E73,"'","!",$K$2,$M73))),"") | M73: 89 | N73: 318
C74: =VLOOKUP($F74,$AS:$AT,2,FALSE) -> [AT_WR_43_2022_SHOPS.xlsx] | D74: Maintenance, renovation | E74: =E73 -> Lerchenfelder | F74: =VLOOKUP($E74,$AP:$AQ,2,FALSE) -> AT | G74: =D74&E74 -> Maintenance, renovationLerchenfelder | H74: =IFERROR(INDIRECT(CONCATENATE("'",$C74,$E74,"'","!",$H$2,$M74))+INDIRECT(CONCATENATE("'",$C74,$E74,"'","!",$H$3,$M74))+INDIRECT(CONCATENATE("'",$C74,$E74,"'","!",$H$4,$M74)),"") | I74: =IFERROR(IF(I$7="PLAN",INDIRECT(CONCATENATE("'",$C74,$E74,"'","!",$I$2,$N74)),INDIRECT(CONCATENATE("'",$C74,$E74,"'","!",$I$2,$M74))),"") | J74: =IFERROR(IF(J$7="PLAN",INDIRECT(CONCATENATE("'",$C74,$E74,"'","!",$J$2,$N74)),INDIRECT(CONCATENATE("'",$C74,$E74,"'","!",$J$2,$M74))),"") | K74: =IFERROR(IF(K$7="PLAN",INDIRECT(CONCATENATE("'",$C74,$E74,"'","!",$K$2,$N74)),INDIRECT(CONCATENATE("'",$C74,$E74,"'","!",$K$2,$M74))),"") | M74: 90 | N74: 319
C75: =VLOOKUP($F75,$AS:$AT,2,FALSE) -> [AT_WR_43_2022_SHOPS.xlsx] | D75: Insurance | E75: =E74 -> Lerchenfelder | F75: =VLOOKUP($E75,$AP:$AQ,2,FALSE) -> AT | G75: =D75&E75 -> InsuranceLerchenfelder | H75: =IFERROR(INDIRECT(CONCATENATE("'",$C75,$E75,"'","!",$H$2,$M75))+INDIRECT(CONCATENATE("'",$C75,$E75,"'","!",$H$3,$M75))+INDIRECT(CONCATENATE("'",$C75,$E75,"'","!",$H$4,$M75)),"") | I75: =IFERROR(IF(I$7="PLAN",INDIRECT(CONCATENATE("'",$C75,$E75,"'","!",$I$2,$N75)),INDIRECT(CONCATENATE("'",$C75,$E75,"'","!",$I$2,$M75))),"") | J75: =IFERROR(IF(J$7="PLAN",INDIRECT(CONCATENATE("'",$C75,$E75,"'","!",$J$2,$N75)),INDIRECT(CONCATENATE("'",$C75,$E75,"'","!",$J$2,$M75))),"") | K75: =IFERROR(IF(K$7="PLAN",INDIRECT(CONCATENATE("'",$C75,$E75,"'","!",$K$2,$N75)),INDIRECT(CONCATENATE("'",$C75,$E75,"'","!",$K$2,$M75))),"") | M75: 91 | N75: 320
C76: =VLOOKUP($F76,$AS:$AT,2,FALSE) -> [AT_WR_43_2022_SHOPS.xlsx] | D76: Acquisition of assets for buildings | E76: =E75 -> Lerchenfelder | F76: =VLOOKUP($E76,$AP:$AQ,2,FALSE) -> AT | G76: =D76&E76 -> Acquisition of assets for buildingsLerchenfelder | H76: =IFERROR(INDIRECT(CONCATENATE("'",$C76,$E76,"'","!",$H$2,$M76))+INDIRECT(CONCATENATE("'",$C76,$E76,"'","!",$H$3,$M76))+INDIRECT(CONCATENATE("'",$C76,$E76,"'","!",$H$4,$M76)),"") | I76: =IFERROR(IF(I$7="PLAN",INDIRECT(CONCATENATE("'",$C76,$E76,"'","!",$I$2,$N76)),INDIRECT(CONCATENATE("'",$C76,$E76,"'","!",$I$2,$M76))),"") | J76: =IFERROR(IF(J$7="PLAN",INDIRECT(CONCATENATE("'",$C76,$E76,"'","!",$J$2,$N76)),INDIRECT(CONCATENATE("'",$C76,$E76,"'","!",$J$2,$M76))),"") | K76: =IFERROR(IF(K$7="PLAN",INDIRECT(CONCATENATE("'",$C76,$E76,"'","!",$K$2,$N76)),INDIRECT(CONCATENATE("'",$C76,$E76,"'","!",$K$2,$M76))),"") | M76: 92 | N76: 321
C77: =VLOOKUP($F77,$AS:$AT,2,FALSE) -> [AT_WR_43_2022_SHOPS.xlsx] | D77: Other (real estate fees, brokers fees, etc.) | E77: =E76 -> Lerchenfelder | F77: =VLOOKUP($E77,$AP:$AQ,2,FALSE) -> AT | G77: =D77&E77 -> Other (real estate fees, brokers fees, etc.)Lerchenfelder | H77: =IFERROR(INDIRECT(CONCATENATE("'",$C77,$E77,"'","!",$H$2,$M77))+INDIRECT(CONCATENATE("'",$C77,$E77,"'","!",$H$3,$M77))+INDIRECT(CONCATENATE("'",$C77,$E77,"'","!",$H$4,$M77)),"") | I77: =IFERROR(IF(I$7="PLAN",INDIRECT(CONCATENATE("'",$C77,$E77,"'","!",$I$2,$N77)),INDIRECT(CONCATENATE("'",$C77,$E77,"'","!",$I$2,$M77))),"") | J77: =IFERROR(IF(J$7="PLAN",INDIRECT(CONCATENATE("'",$C77,$E77,"'","!",$J$2,$N77)),INDIRECT(CONCATENATE("'",$C77,$E77,"'","!",$J$2,$M77))),"") | K77: =IFERROR(IF(K$7="PLAN",INDIRECT(CONCATENATE("'",$C77,$E77,"'","!",$K$2,$N77)),INDIRECT(CONCATENATE("'",$C77,$E77,"'","!",$K$2,$M77))),"") | M77: 93 | N77: 322
... C94: =VLOOKUP($F94,$AS:$AT,2,FALSE) -> [AT_WR_43_2022_SHOPS.xlsx] | D94: Deputy manager | E94: =E93 -> Lerchenfelder | F94: =VLOOKUP($E94,$AP:$AQ,2,FALSE) -> AT | G94: =D94&E94 -> Deputy managerLerchenfelder | H94: =IFERROR(INDIRECT(CONCATENATE("'",$C94,$E94,"'","!",$H$2,$M94))+INDIRECT(CONCATENATE("'",$C94,$E94,"'","!",$H$3,$M94))+INDIRECT(CONCATENATE("'",$C94,$E94,"'","!",$H$4,$M94)),"") | I94: =IFERROR(IF(I$7="PLAN",INDIRECT(CONCATENATE("'",$C94,$E94,"'","!",$I$2,$N94)),INDIRECT(CONCATENATE("'",$C94,$E94,"'","!",$I$2,$M94))),"") | J94: =IFERROR(IF(J$7="PLAN",INDIRECT(CONCATENATE("'",$C94,$E94,"'","!",$J$2,$N94)),INDIRECT(CONCATENATE("'",$C94,$E94,"'","!",$J$2,$M94))),"") | K94: =IFERROR(IF(K$7="PLAN",INDIRECT(CONCATENATE("'",$C94,$E94,"'","!",$K$2,$N94)),INDIRECT(CONCATENATE("'",$C94,$E94,"'","!",$K$2,$M94))),"") | M94: 124 | N94: 353
C95: =VLOOKUP($F95,$AS:$AT,2,FALSE) -> [AT_WR_43_2022_SHOPS.xlsx] | D95: Assistents | E95: =E93 -> Lerchenfelder | F95: =VLOOKUP($E95,$AP:$AQ,2,FALSE) -> AT | G95: =D95&E95 -> AssistentsLerchenfelder | H95: =IFERROR(INDIRECT(CONCATENATE("'",$C95,$E95,"'","!",$H$2,$M95))+INDIRECT(CONCATENATE("'",$C95,$E95,"'","!",$H$3,$M95))+INDIRECT(CONCATENATE("'",$C95,$E95,"'","!",$H$4,$M95)),"") | I95: =IFERROR(IF(I$7="PLAN",INDIRECT(CONCATENATE("'",$C95,$E95,"'","!",$I$2,$N95)),INDIRECT(CONCATENATE("'",$C95,$E95,"'","!",$I$2,$M95))),"") | J95: =IFERROR(IF(J$7="PLAN",INDIRECT(CONCATENATE("'",$C95,$E95,"'","!",$J$2,$N95)),INDIRECT(CONCATENATE("'",$C95,$E95,"'","!",$J$2,$M95))),"") | K95: =IFERROR(IF(K$7="PLAN",INDIRECT(CONCATENATE("'",$C95,$E95,"'","!",$K$2,$N95)),INDIRECT(CONCATENATE("'",$C95,$E95,"'","!",$K$2,$M95))),"") | M95: 125 | N95: 354
C96: =VLOOKUP($F96,$AS:$AT,2,FALSE) -> [AT_WR_43_2022_SHOPS.xlsx] | D96: Stock keeper | E96: =E95 -> Lerchenfelder | F96: =VLOOKUP($E96,$AP:$AQ,2,FALSE) -> AT | G96: =D96&E96 -> Stock keeperLerchenfelder | H96: =IFERROR(INDIRECT(CONCATENATE("'",$C96,$E96,"'","!",$H$2,$M96))+INDIRECT(CONCATENATE("'",$C96,$E96,"'","!",$H$3,$M96))+INDIRECT(CONCATENATE("'",$C96,$E96,"'","!",$H$4,$M96)),"") | I96: =IFERROR(IF(I$7="PLAN",INDIRECT(CONCATENATE("'",$C96,$E96,"'","!",$I$2,$N96)),INDIRECT(CONCATENATE("'",$C96,$E96,"'","!",$I$2,$M96))),"") | J96: =IFERROR(IF(J$7="PLAN",INDIRECT(CONCATENATE("'",$C96,$E96,"'","!",$J$2,$N96)),INDIRECT(CONCATENATE("'",$C96,$E96,"'","!",$J$2,$M96))),"") | K96: =IFERROR(IF(K$7="PLAN",INDIRECT(CONCATENATE("'",$C96,$E96,"'","!",$K$2,$N96)),INDIRECT(CONCATENATE("'",$C96,$E96,"'","!",$K$2,$M96))),"") | M96: 126 | N96: 355
C97: =VLOOKUP($F97,$AS:$AT,2,FALSE) -> [AT_WR_43_2022_SHOPS.xlsx] | D97: Temporary employees | E97: =E96 -> Lerchenfelder | F97: =VLOOKUP($E97,$AP:$AQ,2,FALSE) -> AT | G97: =D97&E97 -> Temporary employeesLerchenfelder | H97: =IFERROR(INDIRECT(CONCATENATE("'",$C97,$E97,"'","!",$H$2,$M97))+INDIRECT(CONCATENATE("'",$C97,$E97,"'","!",$H$3,$M97))+INDIRECT(CONCATENATE("'",$C97,$E97,"'","!",$H$4,$M97)),"") | I97: =IFERROR(IF(I$7="PLAN",INDIRECT(CONCATENATE("'",$C97,$E97,"'","!",$I$2,$N97)),INDIRECT(CONCATENATE("'",$C97,$E97,"'","!",$I$2,$M97))),"") | J97: =IFERROR(IF(J$7="PLAN",INDIRECT(CONCATENATE("'",$C97,$E97,"'","!",$J$2,$N97)),INDIRECT(CONCATENATE("'",$C97,$E97,"'","!",$J$2,$M97))),"") | K97: =IFERROR(IF(K$7="PLAN",INDIRECT(CONCATENATE("'",$C97,$E97,"'","!",$K$2,$N97)),INDIRECT(CONCATENATE("'",$C97,$E97,"'","!",$K$2,$M97))),"") | M97: 127 | N97: 356
C98: =VLOOKUP($F98,$AS:$AT,2,FALSE) -> [AT_WR_43_2022_SHOPS.xlsx] | D98: Shop assistants bonuses | E98: =E97 -> Lerchenfelder | F98: =VLOOKUP($E98,$AP:$AQ,2,FALSE) -> AT | G98: =D98&E98 -> Shop assistants bonusesLerchenfelder | H98: =IFERROR(INDIRECT(CONCATENATE("'",$C98,$E98,"'","!",$H$2,$M98))+INDIRECT(CONCATENATE("'",$C98,$E98,"'","!",$H$3,$M98))+INDIRECT(CONCATENATE("'",$C98,$E98,"'","!",$H$4,$M98)),"") | I98: =IFERROR(IF(I$7="PLAN",INDIRECT(CONCATENATE("'",$C98,$E98,"'","!",$I$2,$N98)),INDIRECT(CONCATENATE("'",$C98,$E98,"'","!",$I$2,$M98))),"") | J98: =IFERROR(IF(J$7="PLAN",INDIRECT(CONCATENATE("'",$C98,$E98,"'","!",$J$2,$N98)),INDIRECT(CONCATENATE("'",$C98,$E98,"'","!",$J$2,$M98))),"") | K98: =IFERROR(IF(K$7="PLAN",INDIRECT(CONCATENATE("'",$C98,$E98,"'","!",$K$2,$N98)),INDIRECT(CONCATENATE("'",$C98,$E98,"'","!",$K$2,$M98))),"") | M98: 128 | N98: 357
C99: =VLOOKUP($F99,$AS:$AT,2,FALSE) -> [AT_WR_43_2022_SHOPS.xlsx] | D99: Shop manager bonuses | E99: =E98 -> Lerchenfelder | F99: =VLOOKUP($E99,$AP:$AQ,2,FALSE) -> AT | G99: =D99&E99 -> Shop manager bonusesLerchenfelder | H99: =IFERROR(INDIRECT(CONCATENATE("'",$C99,$E99,"'","!",$H$2,$M99))+INDIRECT(CONCATENATE("'",$C99,$E99,"'","!",$H$3,$M99))+INDIRECT(CONCATENATE("'",$C99,$E99,"'","!",$H$4,$M99)),"") | I99: =IFERROR(IF(I$7="PLAN",INDIRECT(CONCATENATE("'",$C99,$E99,"'","!",$I$2,$N99)),INDIRECT(CONCATENATE("'",$C99,$E99,"'","!",$I$2,$M99))),"") | J99: =IFERROR(IF(J$7="PLAN",INDIRECT(CONCATENATE("'",$C99,$E99,"'","!",$J$2,$N99)),INDIRECT(CONCATENATE("'",$C99,$E99,"'","!",$J$2,$M99))),"") | K99: =IFERROR(IF(K$7="PLAN",INDIRECT(CONCATENATE("'",$C99,$E99,"'","!",$K$2,$N99)),INDIRECT(CONCATENATE("'",$C99,$E99,"'","!",$K$2,$M99))),"") | M99: 129 | N99: 358
C100: =VLOOKUP($F100,$AS:$AT,2,FALSE) -> [AT_WR_43_2022_SHOPS.xlsx] | D100: Social tax | E100: =E99 -> Lerchenfelder | F100: =VLOOKUP($E100,$AP:$AQ,2,FALSE) -> AT | G100: =D100&E100 -> Social taxLerchenfelder | H100: =IFERROR(INDIRECT(CONCATENATE("'",$C100,$E100,"'","!",$H$2,$M100))+INDIRECT(CONCATENATE("'",$C100,$E100,"'","!",$H$3,$M100))+INDIRECT(CONCATENATE("'",$C100,$E100,"'","!",$H$4,$M100)),"") | I100: =IFERROR(IF(I$7="PLAN",INDIRECT(CONCATENATE("'",$C100,$E100,"'","!",$I$2,$N100)),INDIRECT(CONCATENATE("'",$C100,$E100,"'","!",$I$2,$M100))),"") | J100: =IFERROR(IF(J$7="PLAN",INDIRECT(CONCATENATE("'",$C100,$E100,"'","!",$J$2,$N100)),INDIRECT(CONCATENATE("'",$C100,$E100,"'","!",$J$2,$M100))),"") | K100: =IFERROR(IF(K$7="PLAN",INDIRECT(CONCATENATE("'",$C100,$E100,"'","!",$K$2,$N100)),INDIRECT(CONCATENATE("'",$C100,$E100,"'","!",$K$2,$M100))),"") | M100: 130 | N100: 359
C101: =VLOOKUP($F101,$AS:$AT,2,FALSE) -> [AT_WR_43_2022_SHOPS.xlsx] | D101: Benefits | E101: =E100 -> Lerchenfelder | F101: =VLOOKUP($E101,$AP:$AQ,2,FALSE) -> AT | G101: =D101&E101 -> BenefitsLerchenfelder | H101: =IFERROR(INDIRECT(CONCATENATE("'",$C101,$E101,"'","!",$H$2,$M101))+INDIRECT(CONCATENATE("'",$C101,$E101,"'","!",$H$3,$M101))+INDIRECT(CONCATENATE("'",$C101,$E101,"'","!",$H$4,$M101)),"") | I101: =IFERROR(IF(I$7="PLAN",INDIRECT(CONCATENATE("'",$C101,$E101,"'","!",$I$2,$N101)),INDIRECT(CONCATENATE("'",$C101,$E101,"'","!",$I$2,$M101))),"") | J101: =IFERROR(IF(J$7="PLAN",INDIRECT(CONCATENATE("'",$C101,$E101,"'","!",$J$2,$N101)),INDIRECT(CONCATENATE("'",$C101,$E101,"'","!",$J$2,$M101))),"") | K101: =IFERROR(IF(K$7="PLAN",INDIRECT(CONCATENATE("'",$C101,$E101,"'","!",$K$2,$N101)),INDIRECT(CONCATENATE("'",$C101,$E101,"'","!",$K$2,$M101))),"") | M101: 131 | N101: 360
C102: =VLOOKUP($F102,$AS:$AT,2,FALSE) -> [AT_WR_43_2022_SHOPS.xlsx] | D102: Leasing of staff | E102: =E101 -> Lerchenfelder | F102: =VLOOKUP($E102,$AP:$AQ,2,FALSE) -> AT | G102: =D102&E102 -> Leasing of staffLerchenfelder | H102: =IFERROR(INDIRECT(CONCATENATE("'",$C102,$E102,"'","!",$H$2,$M102))+INDIRECT(CONCATENATE("'",$C102,$E102,"'","!",$H$3,$M102))+INDIRECT(CONCATENATE("'",$C102,$E102,"'","!",$H$4,$M102)),"") | I102: =IFERROR(IF(I$7="PLAN",INDIRECT(CONCATENATE("'",$C102,$E102,"'","!",$I$2,$N102)),INDIRECT(CONCATENATE("'",$C102,$E102,"'","!",$I$2,$M102))),"") | J102: =IFERROR(IF(J$7="PLAN",INDIRECT(CONCATENATE("'",$C102,$E102,"'","!",$J$2,$N102)),INDIRECT(CONCATENATE("'",$C102,$E102,"'","!",$J$2,$M102))),"") | K102: =IFERROR(IF(K$7="PLAN",INDIRECT(CONCATENATE("'",$C102,$E102,"'","!",$K$2,$N102)),INDIRECT(CONCATENATE("'",$C102,$E102,"'","!",$K$2,$M102))),"") | M102: 132 | N102: 361 | Q102: =VLOOKUP($F102,$AS:$AT,2,FALSE) -> [AT_WR_43_2022_SHOPS.xlsx] | R102: Operating Result | S102: =+E102 -> Lerchenfelder | T102: =VLOOKUP($E102,$AP:$AQ,2,FALSE) -> AT | U102: =R102&S102 -> Operating ResultLerchenfelder | V102: =IFERROR(INDIRECT(CONCATENATE("'",$Q102,$S102,"'","!",$V$2,$AA102))+INDIRECT(CONCATENATE("'",$Q102,$S102,"'","!",$V$3,$AA102))+INDIRECT(CONCATENATE("'",$C102,$E102,"'","!",$V$4,$AA102)),"") | W102: =IFERROR(IF(W$7="PLAN",INDIRECT(CONCATENATE("'",$Q102,$S102,"'","!",$W$2,$AB102)),INDIRECT(CONCATENATE("'",$Q102,$S102,"'","!",$I$2,$AA102))),"") | X102: =IFERROR(IF(X$7="PLAN",INDIRECT(CONCATENATE("'",$Q102,$S102,"'","!",$X$2,$AB102)),INDIRECT(CONCATENATE("'",$Q102,$S102,"'","!",$X$2,$AA102))),"") | Y102: =IFERROR(IF(Y$7="PLAN",INDIRECT(CONCATENATE("'",$Q102,$S102,"'","!",$Y$2,$AB102)),INDIRECT(CONCATENATE("'",$C102,$E102,"'","!",$K$2,$AA102))),"") | AA102: 136 | AB102: 365 | AD102: 7854.9633 | AE102: 0 | AF102: 0 | AG102: 0 | AI102: =+H67-SUM(H68:H102)-AD102 -> #VALUE! | AJ102: =+I67-SUM(I68:I102)-AE102 -> #VALUE! | AK102: =+J67-SUM(J68:J102)-AF102 -> #VALUE! | AL102: =+K67-SUM(K68:K102)-AG102 -> #VALUE!

Sheet Info
B1: Business unit name: | D1: Textile House Austria | AE1: valid from 1.1.2025 | AI1: valid from 1.1.2025
A2: No. | B2: SHOP | C2: Cycle | D2: Size | E2: City | F2: Region | G2: Opened (date) | H2: Closed (date) | I2: Area manager | J2: CC | K2: Comparable shop | N2: Year | O2: Current quarter | P2: Exchange rate | Q2: Budget VAT rate | R2: Actual VAT rate | S2: Budget Social tax | U2: Prices for shops | V2: Prices for shops EUR | X2: Previous Year | Y2: Exchange rate | AE2: Regular shops | AF2: Prices for shops | AG2: Prices for shops EUR | AI2: Vintage shops | AJ2: Prices for shops | AK2: Prices for shops EUR
A3: 1 | B3: Paniglgasse | C3: vintage | E3: Vienna | F3: Area 1 | G3: 44613 | I3: Petra Fratričová | L3: =K3&C3 -> vintage | N3: 2025 | O3: Q1 | P3: 1 | Q3: 0.2 | R3: 0.2 | S3: 0.2276 | T3: A | U3: =V3*$P$3 -> 4.8 | V3: 4.8 | X3: 2024 | Y3: 1 | Z3: Kgs put into the shop, shop A | AE3: A | AF3: =AG3*$P$3 -> 4.8 | AG3: 4.8 | AI3: Trend A | AJ3: =AK3*$P$3 -> 5.2 | AK3: 5.2
A4: 2 | B4: Lerchenfelder | C4: vintage | E4: Vienna | F4: Area 1 | I4: Petra Fratričová | L4: =K4&C4 -> vintage | T4: B | U4: =V4*$P$3 -> 2 | V4: 2 | Z4: Kgs put into the shop, shop B | AE4: Shoes A | AF4: =AG4*$P$3 -> 4.8 | AG4: 4.8 | AI4: Trend Shoes A | AJ4: =AK4*$P$3 -> 5.2 | AK4: 5.2
A5: 3 | B5: Landstrasser_Hauptstrasse | C5: vintage | E5: Vienna | F5: Area 1 | I5: Petra Fratričová | L5: =K5&C5 -> vintage | T5: Shoes A | U5: =V5*$P$3 -> 4.8 | V5: 4.8 | Z5: Kgs put into the shop, HHR | AE5: B | AF5: =AG5*$P$3 -> 2 | AG5: 2 | AI5: Trend B | AJ5: =AK5*$P$3 -> 2.4 | AK5: 2.4
A6: 4 | B6: New shop 2 | L6: =K6&C6 | T6: Shoes B | U6: =V6*$P$3 -> 2 | V6: 2 | Z6: Kgs put into the shop, shoes A | AE6: Shoes B | AF6: =AG6*$P$3 -> 2.4 | AG6: 2.4 | AI6: Shoes B | AJ6: =AK6*$P$3 -> 2.4 | AK6: 2.4
A7: 5 | L7: =K7&C7 | T7: HHR (standard) | U7: =V7*$P$3 -> 2 | V7: 2 | Z7: Kgs put into the shop, shoes B | AE7: HHR (standard) | AF7: =AG7*$P$3 -> 2 | AG7: 2 | AI7: Trend HHR | AJ7: =AK7*$P$3 -> 2.4 | AK7: 2.4
A8: 6 | L8: =K8&C8 | T8: Mix Summer | U8: =V8*$P$3 -> 0.8 | V8: 0.8 | Z8: Kgs put into the shop, Mix Summer | AE8: HHT (heavy) | AF8: =AG8*$P$3 -> 2 | AG8: 2 | AI8: HHT (heavy) | AJ8: =AK8*$P$3 -> 0
A9: 7 | T9: Mix Winter | U9: =V9*$P$3 -> 0.7 | V9: 0.7 | Z9: Kgs put into the shop, Mix Winter | AE9: Mix Summer | AF9: =AG9*$P$3 -> 0.8 | AG9: 0.8 | AI9: Mix Summer | AJ9: =AK9*$P$3 -> 0.8 | AK9: 0.8
A10: 8 | T10: Handbag A | U10: =V10*$P$3 -> 4.8 | V10: 4.8 | Z10: Kgs put into the shop, Handbag A | AE10: Mix Winter | AF10: =AG10*$P$3 -> 0.7 | AG10: 0.7 | AI10: Mix Winter | AJ10: =AK10*$P$3 -> 0.7 | AK10: 0.7
A11: 9 | L11: =K10&C10 | T11: Handbag B | U11: =V11*$P$3 -> 2 | V11: 2 | Z11: Kgs put into the shop, Handbag B | AE11: Handbag A | AF11: =AG11*$P$3 -> 4.8 | AG11: 4.8 | AI11: Bag A Trendy | AJ11: =AK11*$P$3 -> 5.2 | AK11: 5.2
A12: 10 | L12: =K11&C11 | T12: Things | U12: =V12*$P$3 -> 4.8 | V12: 4.8 | Z12: Kgs put into the shop, things | AE12: Handbag B | AF12: =AG12*$P$3 -> 2.4 | AG12: 2.4 | AI12: Handbag B | AJ12: =AK12*$P$3 -> 2.4 | AK12: 2.4
A13: 11 | L13: =K12&C12 | AE13: return | AF13: =AG13*$P$3 -> 0.2 | AG13: 0.2 | AI13: Other Trend categories | AJ13: =AK13*$P$3 -> 5.2 | AK13: 5.2
A14: 12 | L14: =K13&C13 | AE14: hhr b | AF14: =AG14*$P$3 -> 1.3 | AG14: 1.3 | AI14: hhr b | AJ14: =AK14*$P$3 -> 1.3 | AK14: 1.3
A15: 13 | L15: =K14&C14
A16: 14 | L16: =K15&C15
A17: 15 | L17: =K16&C16
A18: 16 | L18: =K17&C17
A19: 17 | D19: ` | L19: =K18&C18
A20: 18 | L20: =K19&C19
A21: 19 | L21: =K20&C20
A22: 20 | L22: =K21&C21
A23: 21 | L23: =K22&C22
A24: 22 | L24: =K23&C23
A25: 23 | L25: =K24&C24
A26: 24 | L26: =K25&C25
A27: 25 | L27: =K26&C26
A28: 26 | L28: =K27&C27
A29: 27 | L29: =K28&C28
A30: 28 | L30: =K29&C29
A31: 29 | L31: =K30&C30
... A50: 48 | L50: =K49&C49
B51: Total | D51: =SUM(D3:D50) -> 0 | L51: =K50&C50
B52: 5 weeks | D52: =SUMIF($C$3:$C$50,$B52,$D$3:$D$50) -> 0
B53: 2 weeks | D53: =SUMIF($C$3:$C$50,$B53,$D$3:$D$50) -> 0

Sheet WK5
D1: =Info!$N$3 -> 2025 | E1: 1st Quarter | R1: 2nd Quarter | AE1: 3rd Quarter | AR1: 4th Quarter | BF1: Q1 | BI1: Q2 | BL1: Q3 | BO1: Q4
B2: =Info!$D$1 -> Textile House Austria | E2: January | I2: February | M2: March | R2: April | V2: May | Z2: June | AE2: July | AI2: August | AM2: September | AR2: October | AV2: November | AZ2: December | BF2: January | BG2: February | BH2: March | BI2: April | BJ2: May | BK2: June | BL2: July | BM2: August | BN2: September | BO2: October | BP2: November | BQ2: December | BR2: Year | BS2: Q1 | BT2: Q2 | BU2: Q3 | BV2: Q4 | BW2: H1 | BX2: H2 | BY2: Selection | BZ2: Selection
B3: 5 week | E3: Week | F3: Week | G3: Week | H3: Week | I3: Week | J3: Week | K3: Week | L3: Week | M3: Week | N3: Week | O3: Week | P3: Week | Q3: Week | R3: Week | S3: Week | T3: Week | U3: Week | V3: Week | W3: Week | X3: Week | Y3: Week | Z3: Week | AA3: Week | AB3: Week | AC3: Week | AD3: Week | AE3: Week | AF3: Week | AG3: Week | AH3: Week | AI3: Week | AJ3: Week | AK3: Week | AL3: Week | AM3: Week | AN3: Week | AO3: Week | AP3: Week | AQ3: Week | AR3: Week | AS3: Week | AT3: Week | AU3: Week | AV3: Week | AW3: Week | AX3: Week | AY3: Week | AZ3: Week | BA3: Week | BB3: Week | BC3: Week | BD3: Week | BF3: 1-4 | BG3: 5-8 | BH3: 9-13 | BI3: 14-17 | BJ3: 18-21 | BK3: 22-26 | BL3: 27-30 | BM3: 31-34 | BN3: 35-39 | BO3: 40-43 | BP3: 44-47 | BQ3: 48-52 | BR3: =$D$1 -> 2025 | BS3: 1-13 | BT3: 14-26 | BU3: 27-39 | BV3: 40-52 | BW3: 1-26 | BX3: 27-52 | BY3: YTD | BZ3: Quarter
D4: Total | E4: 1 | F4: 2 | G4: 3 | H4: 4 | I4: 5 | J4: 6 | K4: 7 | L4: 8 | M4: 9 | N4: 10 | O4: 11 | P4: 12 | Q4: 13 | R4: 14 | S4: 15 | T4: 16 | U4: 17 | V4: 18 | W4: 19 | X4: 20 | Y4: 21 | Z4: 22 | AA4: 23 | AB4: 24 | AC4: 25 | AD4: 26 | AE4: 27 | AF4: 28 | AG4: 29 | AH4: 30 | AI4: 31 | AJ4: 32 | AK4: 33 | AL4: 34 | AM4: 35 | AN4: 36 | AO4: 37 | AP4: 38 | AQ4: 39 | AR4: 40 | AS4: 41 | AT4: 42 | AU4: 43 | AV4: 44 | AW4: 45 | AX4: 46 | AY4: 47 | AZ4: 48 | BA4: 49 | BB4: 50 | BC4: 51 | BD4: 52 | BF4: 4 | BG4: 4 | BH4: 5 | BI4: 4 | BJ4: 4 | BK4: 5 | BL4: 4 | BM4: 4 | BN4: 5 | BO4: 4 | BP4: 4 | BQ4: 5
B5: Pieces stolen | D5: =SUM(E5:BD5) -> 1158 | E5: =SUM(Paniglgasse:Lerchenfelder!E5) -> 86.03 | F5: =SUM(Paniglgasse:Lerchenfelder!F5) -> -25.18 | G5: =SUM(Paniglgasse:Lerchenfelder!G5) -> -76.63 | H5: =SUM(Paniglgasse:Lerchenfelder!H5) -> 10.68 | I5: =SUM(Paniglgasse:Lerchenfelder!I5) -> -39 | J5: =SUM(Paniglgasse:Lerchenfelder!J5) -> 41.56 | K5: =SUM(Paniglgasse:Lerchenfelder!K5) -> 10 | L5: =SUM(Paniglgasse:Lerchenfelder!L5) -> 39.15 | ... BD5: =SUM(Paniglgasse:Lerchenfelder!BD5) -> 0 | BF5: =SUM(E5:H5) -> -5.1 | BG5: =SUM(I5:L5) -> 51.71 | BH5: =SUM(M5:Q5) -> 127.12 | BI5: =SUM(R5:U5) -> 389.35 | BJ5: =SUM(V5:Y5) -> 264.66 | BK5: =SUM(Z5:AD5) -> 73.39 | BL5: =SUM(AE5:AH5) -> 109.81 | BM5: =SUM(AI5:AL5) -> 114.72 | BN5: =SUM(AM5:AQ5) -> 32.34 | BO5: =SUM(AR5:AU5) -> 0 | BP5: =SUM(AV5:AY5) -> 0 | BQ5: =SUM(AZ5:BD5) -> 0 | BR5: =SUM(BF5:BQ5) -> 1158 | BS5: =SUM(BF5:BH5) -> 173.73 | BT5: =SUM(BI5:BK5) -> 727.4 | BU5: =SUM(BL5:BN5) -> 256.87 | BV5: =SUM(BO5:BQ5) -> 0 | BW5: =SUM(BF5:BK5) -> 901.13 | BX5: =SUM(BL5:BQ5) -> 256.87 | BY5: =IF(Info!$O$3="Q1",$BS5,IF(Info!$O$3="Q2",$BS5+$BT5,IF(Info!$O$3="Q3",$BS5+$BT5+$BU5,$BR5))) -> 173.73 | BZ5: =IF(Info!$O$3="Q1",$BS5,IF(Info!$O$3="Q2",$BT5,IF(Info!$O$3="Q3",$BU5,$BV5))) -> 173.73
B6: Pcs in the shop, week begin | D6: =SUM(E6:BD6) -> 135546.92 | E6: =SUM(Paniglgasse:Lerchenfelder!E6) -> 2869.15 | F6: =IF(F15=0,E32,F15) -> 2477.79 | G6: =IF(G15=0,F32,G15) -> 2360.66 | H6: =IF(H15=0,G32,H15) -> 3674.4 | I6: =IF(I15=0,H32,I15) -> 2754.08 | J6: =IF(J15=0,I32,J15) -> 2746.6 | K6: =IF(K15=0,J32,K15) -> 2811.36 | L6: =IF(L15=0,K32,L15) -> 2588.68 | M6: =IF(M15=0,L32,M15) -> 3948.89 | ... BD6: =IF(BD15=0,BC32,BD15) -> 1703.2 | BF6: =SUM(E6:H6) -> 11382 | BG6: =SUM(I6:L6) -> 10900.72 | BH6: =SUM(M6:Q6) -> 16145.63 | BI6: =SUM(R6:U6) -> 13659.79 | BJ6: =SUM(V6:Y6) -> 12952.87 | BK6: =SUM(Z6:AD6) -> 15625.07 | BL6: =SUM(AE6:AH6) -> 11613.97 | BM6: =SUM(AI6:AL6) -> 10694.05 | BN6: =SUM(AM6:AQ6) -> 10431.22 | BO6: =SUM(AR6:AU6) -> 6812.8 | BP6: =SUM(AV6:AY6) -> 6812.8 | BQ6: =SUM(AZ6:BD6) -> 8516 | BR6: =SUM(BF6:BQ6) -> 135546.92 | BS6: =SUM(BF6:BH6) -> 38428.35 | BT6: =SUM(BI6:BK6) -> 42237.73 | BU6: =SUM(BL6:BN6) -> 32739.24 | BV6: =SUM(BO6:BQ6) -> 22141.6 | BW6: =SUM(BF6:BK6) -> 80666.08 | BX6: =SUM(BL6:BQ6) -> 54880.84 | BY6: =IF(Info!$O$3="Q1",$BS6,IF(Info!$O$3="Q2",$BS6+$BT6,IF(Info!$O$3="Q3",$BS6+$BT6+$BU6,$BR6))) -> 38428.35 | BZ6: =IF(Info!$O$3="Q1",$BS6,IF(Info!$O$3="Q2",$BT6,IF(Info!$O$3="Q3",$BU6,$BV6))) -> 38428.35
B7: Pcs put into the shop, A new opening | D7: =SUM(E7:BD7) -> 24095.11 | E7: =SUM(Paniglgasse:Lerchenfelder!E7) -> 0 | F7: =SUM(Paniglgasse:Lerchenfelder!F7) -> 0 | G7: =SUM(Paniglgasse:Lerchenfelder!G7) -> 0 | H7: =SUM(Paniglgasse:Lerchenfelder!H7) -> 3296.87 | I7: =SUM(Paniglgasse:Lerchenfelder!I7) -> 0 | J7: =SUM(Paniglgasse:Lerchenfelder!J7) -> 0 | K7: =SUM(Paniglgasse:Lerchenfelder!K7) -> 0 | L7: =SUM(Paniglgasse:Lerchenfelder!L7) -> 0 | ... BD7: =SUM(Paniglgasse:Lerchenfelder!BD7) -> 0 | BF7: =SUM(E7:H7) -> 3296.87 | BG7: =SUM(I7:L7) -> 0 | BH7: =SUM(M7:Q7) -> 3535.24 | BI7: =SUM(R7:U7) -> 3622.1 | BJ7: =SUM(V7:Y7) -> 3503.92 | BK7: =SUM(Z7:AD7) -> 3727.28 | BL7: =SUM(AE7:AH7) -> 3236.33 | BM7: =SUM(AI7:AL7) -> 0 | BN7: =SUM(AM7:AQ7) -> 3173.37 | BO7: =SUM(AR7:AU7) -> 0 | BP7: =SUM(AV7:AY7) -> 0 | BQ7: =SUM(AZ7:BD7) -> 0 | BR7: =SUM(BF7:BQ7) -> 24095.11 | BS7: =SUM(BF7:BH7) -> 6832.11 | BT7: =SUM(BI7:BK7) -> 10853.3 | BU7: =SUM(BL7:BN7) -> 6409.7 | BV7: =SUM(BO7:BQ7) -> 0 | BW7: =SUM(BF7:BK7) -> 17685.41 | BX7: =SUM(BL7:BQ7) -> 6409.7 | BY7: =IF(Info!$O$3="Q1",$BS7,IF(Info!$O$3="Q2",$BS7+$BT7,IF(Info!$O$3="Q3",$BS7+$BT7+$BU7,$BR7))) -> 6832.11 | BZ7: =IF(Info!$O$3="Q1",$BS7,IF(Info!$O$3="Q2",$BT7,IF(Info!$O$3="Q3",$BU7,$BV7))) -> 6832.11
B8: Pcs put into the shop, B new opening | D8: =SUM(E8:BD8) -> 0 | E8: =SUM(Paniglgasse:Lerchenfelder!E8) -> 0 | F8: =SUM(Paniglgasse:Lerchenfelder!F8) -> 0 | G8: =SUM(Paniglgasse:Lerchenfelder!G8) -> 0 | H8: =SUM(Paniglgasse:Lerchenfelder!H8) -> 0 | I8: =SUM(Paniglgasse:Lerchenfelder!I8) -> 0 | J8: =SUM(Paniglgasse:Lerchenfelder!J8) -> 0 | K8: =SUM(Paniglgasse:Lerchenfelder!K8) -> 0 | L8: =SUM(Paniglgasse:Lerchenfelder!L8) -> 0 | ... BD8: =SUM(Paniglgasse:Lerchenfelder!BD8) -> 0 | BF8: =SUM(E8:H8) -> 0 | BG8: =SUM(I8:L8) -> 0 | BH8: =SUM(M8:Q8) -> 0 | BI8: =SUM(R8:U8) -> 0 | BJ8: =SUM(V8:Y8) -> 0 | BK8: =SUM(Z8:AD8) -> 0 | BL8: =SUM(AE8:AH8) -> 0 | BM8: =SUM(AI8:AL8) -> 0 | BN8: =SUM(AM8:AQ8) -> 0 | BO8: =SUM(AR8:AU8) -> 0 | BP8: =SUM(AV8:AY8) -> 0 | BQ8: =SUM(AZ8:BD8) -> 0 | BR8: =SUM(BF8:BQ8) -> 0 | BS8: =SUM(BF8:BH8) -> 0 | BT8: =SUM(BI8:BK8) -> 0 | BU8: =SUM(BL8:BN8) -> 0 | BV8: =SUM(BO8:BQ8) -> 0 | BW8: =SUM(BF8:BK8) -> 0 | BX8: =SUM(BL8:BQ8) -> 0 | BY8: =IF(Info!$O$3="Q1",$BS8,IF(Info!$O$3="Q2",$BS8+$BT8,IF(Info!$O$3="Q3",$BS8+$BT8+$BU8,$BR8))) -> 0 | BZ8: =IF(Info!$O$3="Q1",$BS8,IF(Info!$O$3="Q2",$BT8,IF(Info!$O$3="Q3",$BU8,$BV8))) -> 0
B9: Pcs put into the shop, shoes A new opening | D9: =SUM(E9:BD9) -> 615.8 | E9: =SUM(Paniglgasse:Lerchenfelder!E9) -> 0 | F9: =SUM(Paniglgasse:Lerchenfelder!F9) -> 0 | G9: =SUM(Paniglgasse:Lerchenfelder!G9) -> 0 | H9: =SUM(Paniglgasse:Lerchenfelder!H9) -> 48.28 | I9: =SUM(Paniglgasse:Lerchenfelder!I9) -> 0 | J9: =SUM(Paniglgasse:Lerchenfelder!J9) -> 0 | K9: =SUM(Paniglgasse:Lerchenfelder!K9) -> 0 | L9: =SUM(Paniglgasse:Lerchenfelder!L9) -> 0 | ... BD9: =SUM(Paniglgasse:Lerchenfelder!BD9) -> 0 | BF9: =SUM(E9:H9) -> 48.28 | BG9: =SUM(I9:L9) -> 0 | BH9: =SUM(M9:Q9) -> 99.16 | BI9: =SUM(R9:U9) -> 55.74 | BJ9: =SUM(V9:Y9) -> 82.9 | BK9: =SUM(Z9:AD9) -> 83.01 | BL9: =SUM(AE9:AH9) -> 126.32 | BM9: =SUM(AI9:AL9) -> 0 | BN9: =SUM(AM9:AQ9) -> 120.39 | BO9: =SUM(AR9:AU9) -> 0 | BP9: =SUM(AV9:AY9) -> 0 | BQ9: =SUM(AZ9:BD9) -> 0 | BR9: =SUM(BF9:BQ9) -> 615.8 | BS9: =SUM(BF9:BH9) -> 147.44 | BT9: =SUM(BI9:BK9) -> 221.65 | BU9: =SUM(BL9:BN9) -> 246.71 | BV9: =SUM(BO9:BQ9) -> 0 | BW9: =SUM(BF9:BK9) -> 369.09 | BX9: =SUM(BL9:BQ9) -> 246.71 | BY9: =IF(Info!$O$3="Q1",$BS9,IF(Info!$O$3="Q2",$BS9+$BT9,IF(Info!$O$3="Q3",$BS9+$BT9+$BU9,$BR9))) -> 147.44 | BZ9: =IF(Info!$O$3="Q1",$BS9,IF(Info!$O$3="Q2",$BT9,IF(Info!$O$3="Q3",$BU9,$BV9))) -> 147.44
B10: Pcs put into the shop, shoes B new opening | D10: =SUM(E10:BD10) -> 0 | E10: =SUM(Paniglgasse:Lerchenfelder!E10) -> 0 | F10: =SUM(Paniglgasse:Lerchenfelder!F10) -> 0 | G10: =SUM(Paniglgasse:Lerchenfelder!G10) -> 0 | H10: =SUM(Paniglgasse:Lerchenfelder!H10) -> 0 | I10: =SUM(Paniglgasse:Lerchenfelder!I10) -> 0 | J10: =SUM(Paniglgasse:Lerchenfelder!J10) -> 0 | K10: =SUM(Paniglgasse:Lerchenfelder!K10) -> 0 | L10: =SUM(Paniglgasse:Lerchenfelder!L10) -> 0 | ... BD10: =SUM(Paniglgasse:Lerchenfelder!BD10) -> 0 | BF10: =SUM(E10:H10) -> 0 | BG10: =SUM(I10:L10) -> 0 | BH10: =SUM(M10:Q10) -> 0 | BI10: =SUM(R10:U10) -> 0 | BJ10: =SUM(V10:Y10) -> 0 | BK10: =SUM(Z10:AD10) -> 0 | BL10: =SUM(AE10:AH10) -> 0 | BM10: =SUM(AI10:AL10) -> 0 | BN10: =SUM(AM10:AQ10) -> 0 | BO10: =SUM(AR10:AU10) -> 0 | BP10: =SUM(AV10:AY10) -> 0 | BQ10: =SUM(AZ10:BD10) -> 0 | BR10: =SUM(BF10:BQ10) -> 0 | BS10: =SUM(BF10:BH10) -> 0 | BT10: =SUM(BI10:BK10) -> 0 | BU10: =SUM(BL10:BN10) -> 0 | BV10: =SUM(BO10:BQ10) -> 0 | BW10: =SUM(BF10:BK10) -> 0 | BX10: =SUM(BL10:BQ10) -> 0 | BY10: =IF(Info!$O$3="Q1",$BS10,IF(Info!$O$3="Q2",$BS10+$BT10,IF(Info!$O$3="Q3",$BS10+$BT10+$BU10,$BR10))) -> 0 | BZ10: =IF(Info!$O$3="Q1",$BS10,IF(Info!$O$3="Q2",$BT10,IF(Info!$O$3="Q3",$BU10,$BV10))) -> 0
B11: Pcs put into the shop, HHR new opening | D11: =SUM(E11:BD11) -> 0 | E11: =SUM(Paniglgasse:Lerchenfelder!E11) -> 0 | F11: =SUM(Paniglgasse:Lerchenfelder!F11) -> 0 | G11: =SUM(Paniglgasse:Lerchenfelder!G11) -> 0 | H11: =SUM(Paniglgasse:Lerchenfelder!H11) -> 0 | I11: =SUM(Paniglgasse:Lerchenfelder!I11) -> 0 | J11: =SUM(Paniglgasse:Lerchenfelder!J11) -> 0 | K11: =SUM(Paniglgasse:Lerchenfelder!K11) -> 0 | L11: =SUM(Paniglgasse:Lerchenfelder!L11) -> 0 | ... BD11: =SUM(Paniglgasse:Lerchenfelder!BD11) -> 0 | BF11: =SUM(E11:H11) -> 0 | BG11: =SUM(I11:L11) -> 0 | BH11: =SUM(M11:Q11) -> 0 | BI11: =SUM(R11:U11) -> 0 | BJ11: =SUM(V11:Y11) -> 0 | BK11: =SUM(Z11:AD11) -> 0 | BL11: =SUM(AE11:AH11) -> 0 | BM11: =SUM(AI11:AL11) -> 0 | BN11: =SUM(AM11:AQ11) -> 0 | BO11: =SUM(AR11:AU11) -> 0 | BP11: =SUM(AV11:AY11) -> 0 | BQ11: =SUM(AZ11:BD11) -> 0 | BR11: =SUM(BF11:BQ11) -> 0 | BS11: =SUM(BF11:BH11) -> 0 | BT11: =SUM(BI11:BK11) -> 0 | BU11: =SUM(BL11:BN11) -> 0 | BV11: =SUM(BO11:BQ11) -> 0 | BW11: =SUM(BF11:BK11) -> 0 | BX11: =SUM(BL11:BQ11) -> 0 | BY11: =IF(Info!$O$3="Q1",$BS11,IF(Info!$O$3="Q2",$BS11+$BT11,IF(Info!$O$3="Q3",$BS11+$BT11+$BU11,$BR11))) -> 0 | BZ11: =IF(Info!$O$3="Q1",$BS11,IF(Info!$O$3="Q2",$BT11,IF(Info!$O$3="Q3",$BU11,$BV11))) -> 0
B12: Pcs put into the shop, Handbag A new opening | D12: =SUM(E12:BD12) -> 1470.77 | E12: =SUM(Paniglgasse:Lerchenfelder!E12) -> 0 | F12: =SUM(Paniglgasse:Lerchenfelder!F12) -> 0 | G12: =SUM(Paniglgasse:Lerchenfelder!G12) -> 0 | H12: =SUM(Paniglgasse:Lerchenfelder!H12) -> 219.89 | I12: =SUM(Paniglgasse:Lerchenfelder!I12) -> 0 | J12: =SUM(Paniglgasse:Lerchenfelder!J12) -> 0 | K12: =SUM(Paniglgasse:Lerchenfelder!K12) -> 0 | L12: =SUM(Paniglgasse:Lerchenfelder!L12) -> 0 | ... BD12: =SUM(Paniglgasse:Lerchenfelder!BD12) -> 0 | BF12: =SUM(E12:H12) -> 219.89 | BG12: =SUM(I12:L12) -> 0 | BH12: =SUM(M12:Q12) -> 204.51 | BI12: =SUM(R12:U12) -> 226.5 | BJ12: =SUM(V12:Y12) -> 188.41 | BK12: =SUM(Z12:AD12) -> 178.96 | BL12: =SUM(AE12:AH12) -> 205.9 | BM12: =SUM(AI12:AL12) -> 0 | BN12: =SUM(AM12:AQ12) -> 246.6 | BO12: =SUM(AR12:AU12) -> 0 | BP12: =SUM(AV12:AY12) -> 0 | BQ12: =SUM(AZ12:BD12) -> 0 | BR12: =SUM(BF12:BQ12) -> 1470.77 | BS12: =SUM(BF12:BH12) -> 424.4 | BT12: =SUM(BI12:BK12) -> 593.87 | BU12: =SUM(BL12:BN12) -> 452.5 | BV12: =SUM(BO12:BQ12) -> 0 | BW12: =SUM(BF12:BK12) -> 1018.27 | BX12: =SUM(BL12:BQ12) -> 452.5 | BY12: =IF(Info!$O$3="Q1",$BS12,IF(Info!$O$3="Q2",$BS12+$BT12,IF(Info!$O$3="Q3",$BS12+$BT12+$BU12,$BR12))) -> 424.4 | BZ12: =IF(Info!$O$3="Q1",$BS12,IF(Info!$O$3="Q2",$BT12,IF(Info!$O$3="Q3",$BU12,$BV12))) -> 424.4
B13: Pcs put into the shop, Handbag B new opening | D13: =SUM(E13:BD13) -> 0 | E13: =SUM(Paniglgasse:Lerchenfelder!E13) -> 0 | F13: =SUM(Paniglgasse:Lerchenfelder!F13) -> 0 | G13: =SUM(Paniglgasse:Lerchenfelder!G13) -> 0 | H13: =SUM(Paniglgasse:Lerchenfelder!H13) -> 0 | I13: =SUM(Paniglgasse:Lerchenfelder!I13) -> 0 | J13: =SUM(Paniglgasse:Lerchenfelder!J13) -> 0 | K13: =SUM(Paniglgasse:Lerchenfelder!K13) -> 0 | L13: =SUM(Paniglgasse:Lerchenfelder!L13) -> 0 | ... BD13: =SUM(Paniglgasse:Lerchenfelder!BD13) -> 0 | BF13: =SUM(E13:H13) -> 0 | BG13: =SUM(I13:L13) -> 0 | BH13: =SUM(M13:Q13) -> 0 | BI13: =SUM(R13:U13) -> 0 | BJ13: =SUM(V13:Y13) -> 0 | BK13: =SUM(Z13:AD13) -> 0 | BL13: =SUM(AE13:AH13) -> 0 | BM13: =SUM(AI13:AL13) -> 0 | BN13: =SUM(AM13:AQ13) -> 0 | BO13: =SUM(AR13:AU13) -> 0 | BP13: =SUM(AV13:AY13) -> 0 | BQ13: =SUM(AZ13:BD13) -> 0 | BR13: =SUM(BF13:BQ13) -> 0 | BS13: =SUM(BF13:BH13) -> 0 | BT13: =SUM(BI13:BK13) -> 0 | BU13: =SUM(BL13:BN13) -> 0 | BV13: =SUM(BO13:BQ13) -> 0 | BW13: =SUM(BF13:BK13) -> 0 | BX13: =SUM(BL13:BQ13) -> 0 | BY13: =IF(Info!$O$3="Q1",$BS13,IF(Info!$O$3="Q2",$BS13+$BT13,IF(Info!$O$3="Q3",$BS13+$BT13+$BU13,$BR13))) -> 0 | BZ13: =IF(Info!$O$3="Q1",$BS13,IF(Info!$O$3="Q2",$BT13,IF(Info!$O$3="Q3",$BU13,$BV13))) -> 0
B14: Pcs put into the shop, things new opening | D14: =SUM(E14:BD14) -> 756.35 | E14: =SUM(Paniglgasse:Lerchenfelder!E14) -> 0 | F14: =SUM(Paniglgasse:Lerchenfelder!F14) -> 0 | G14: =SUM(Paniglgasse:Lerchenfelder!G14) -> 0 | H14: =SUM(Paniglgasse:Lerchenfelder!H14) -> 109.36 | I14: =SUM(Paniglgasse:Lerchenfelder!I14) -> 0 | J14: =SUM(Paniglgasse:Lerchenfelder!J14) -> 0 | K14: =SUM(Paniglgasse:Lerchenfelder!K14) -> 0 | L14: =SUM(Paniglgasse:Lerchenfelder!L14) -> 0 | ... BD14: =SUM(Paniglgasse:Lerchenfelder!BD14) -> 0 | BF14: =SUM(E14:H14) -> 109.36 | BG14: =SUM(I14:L14) -> 0 | BH14: =SUM(M14:Q14) -> 109.98 | BI14: =SUM(R14:U14) -> 88.22 | BJ14: =SUM(V14:Y14) -> 65.31 | BK14: =SUM(Z14:AD14) -> 121.99 | BL14: =SUM(AE14:AH14) -> 138.99 | BM14: =SUM(AI14:AL14) -> 0 | BN14: =SUM(AM14:AQ14) -> 122.5 | BO14: =SUM(AR14:AU14) -> 0 | BP14: =SUM(AV14:AY14) -> 0 | BQ14: =SUM(AZ14:BD14) -> 0 | BR14: =SUM(BF14:BQ14) -> 756.35 | BS14: =SUM(BF14:BH14) -> 219.34 | BT14: =SUM(BI14:BK14) -> 275.52 | BU14: =SUM(BL14:BN14) -> 261.49 | BV14: =SUM(BO14:BQ14) -> 0 | BW14: =SUM(BF14:BK14) -> 494.86 | BX14: =SUM(BL14:BQ14) -> 261.49 | BY14: =IF(Info!$O$3="Q1",$BS14,IF(Info!$O$3="Q2",$BS14+$BT14,IF(Info!$O$3="Q3",$BS14+$BT14+$BU14,$BR14))) -> 219.34 | BZ14: =IF(Info!$O$3="Q1",$BS14,IF(Info!$O$3="Q2",$BT14,IF(Info!$O$3="Q3",$BU14,$BV14))) -> 219.34
B15: Pcs put into the shop, total new opening | D15: =SUM(E15:BD15) -> 26938.03 | E15: =SUM(E7:E14) -> 0 | F15: =SUM(F7:F14) -> 0 | G15: =SUM(G7:G14) -> 0 | H15: =SUM(H7:H14) -> 3674.4 | I15: =SUM(I7:I14) -> 0 | J15: =SUM(J7:J14) -> 0 | K15: =SUM(K7:K14) -> 0 | L15: =SUM(L7:L14) -> 0 | ... BD15: =SUM(BD7:BD14) -> 0 | BF15: =SUM(E15:H15) -> 3674.4 | BG15: =SUM(I15:L15) -> 0 | BH15: =SUM(M15:Q15) -> 3948.89 | BI15: =SUM(R15:U15) -> 3992.56 | BJ15: =SUM(V15:Y15) -> 3840.54 | BK15: =SUM(Z15:AD15) -> 4111.24 | BL15: =SUM(AE15:AH15) -> 3707.54 | BM15: =SUM(AI15:AL15) -> 0 | BN15: =SUM(AM15:AQ15) -> 3662.86 | BO15: =SUM(AR15:AU15) -> 0 | BP15: =SUM(AV15:AY15) -> 0 | BQ15: =SUM(AZ15:BD15) -> 0 | BR15: =SUM(BF15:BQ15) -> 26938.03 | BS15: =SUM(BF15:BH15) -> 7623.29 | BT15: =SUM(BI15:BK15) -> 11944.34 | BU15: =SUM(BL15:BN15) -> 7370.4 | BV15: =SUM(BO15:BQ15) -> 0 | BW15: =SUM(BF15:BK15) -> 19567.63 | BX15: =SUM(BL15:BQ15) -> 7370.4 | BY15: =IF(Info!$O$3="Q1",$BS15,IF(Info!$O$3="Q2",$BS15+$BT15,IF(Info!$O$3="Q3",$BS15+$BT15+$BU15,$BR15))) -> 7623.29 | BZ15: =IF(Info!$O$3="Q1",$BS15,IF(Info!$O$3="Q2",$BT15,IF(Info!$O$3="Q3",$BU15,$BV15))) -> 7623.29
B16: Pcs put into the shop, shop A | D16: =SUM(E16:BD16) -> 17664.03 | E16: =SUM(Paniglgasse:Lerchenfelder!E16) -> 593.58 | F16: =SUM(Paniglgasse:Lerchenfelder!F16) -> 0 | G16: =SUM(Paniglgasse:Lerchenfelder!G16) -> 0 | H16: =SUM(Paniglgasse:Lerchenfelder!H16) -> 575.74 | I16: =SUM(Paniglgasse:Lerchenfelder!I16) -> 1153.5 | J16: =SUM(Paniglgasse:Lerchenfelder!J16) -> 219 | K16: =SUM(Paniglgasse:Lerchenfelder!K16) -> 0 | L16: =SUM(Paniglgasse:Lerchenfelder!L16) -> 0 | ... BD16: =SUM(Paniglgasse:Lerchenfelder!BD16) -> 0 | BF16: =SUM(E16:H16) -> 1169.32 | BG16: =SUM(I16:L16) -> 1372.5 | BH16: =SUM(M16:Q16) -> 2205.07 | BI16: =SUM(R16:U16) -> 1847.05 | BJ16: =SUM(V16:Y16) -> 2319.2 | BK16: =SUM(Z16:AD16) -> 2786.93 | BL16: =SUM(AE16:AH16) -> 2129.4 | BM16: =SUM(AI16:AL16) -> 1065.03 | BN16: =SUM(AM16:AQ16) -> 2769.53 | BO16: =SUM(AR16:AU16) -> 0 | BP16: =SUM(AV16:AY16) -> 0 | BQ16: =SUM(AZ16:BD16) -> 0 | BR16: =SUM(BF16:BQ16) -> 17664.03 | BS16: =SUM(BF16:BH16) -> 4746.89 | BT16: =SUM(BI16:BK16) -> 6953.18 | BU16: =SUM(BL16:BN16) -> 5963.96 | BV16: =SUM(BO16:BQ16) -> 0 | BW16: =SUM(BF16:BK16) -> 11700.07 | BX16: =SUM(BL16:BQ16) -> 5963.96 | BY16: =IF(Info!$O$3="Q1",$BS16,IF(Info!$O$3="Q2",$BS16+$BT16,IF(Info!$O$3="Q3",$BS16+$BT16+$BU16,$BR16))) -> 4746.89 | BZ16: =IF(Info!$O$3="Q1",$BS16,IF(Info!$O$3="Q2",$BT16,IF(Info!$O$3="Q3",$BU16,$BV16))) -> 4746.89
B17: Pcs put into the shop, shop B | D17: =SUM(E17:BD17) -> 33158.72 | E17: =SUM(Paniglgasse:Lerchenfelder!E17) -> 697.9 | F17: =SUM(Paniglgasse:Lerchenfelder!F17) -> 1161.21 | G17: =SUM(Paniglgasse:Lerchenfelder!G17) -> 2234.33 | H17: =SUM(Paniglgasse:Lerchenfelder!H17) -> 0 | I17: =SUM(Paniglgasse:Lerchenfelder!I17) -> 0 | J17: =SUM(Paniglgasse:Lerchenfelder!J17) -> 1158.75 | K17: =SUM(Paniglgasse:Lerchenfelder!K17) -> 1170.76 | L17: =SUM(Paniglgasse:Lerchenfelder!L17) -> 2195.59 | ... BD17: =SUM(Paniglgasse:Lerchenfelder!BD17) -> 0 | BF17: =SUM(E17:H17) -> 4093.44 | BG17: =SUM(I17:L17) -> 4525.1 | BH17: =SUM(M17:Q17) -> 4762.36 | BI17: =SUM(R17:U17) -> 2696.56 | BJ17: =SUM(V17:Y17) -> 3311.57 | BK17: =SUM(Z17:AD17) -> 4598.39 | BL17: =SUM(AE17:AH17) -> 3483.86 | BM17: =SUM(AI17:AL17) -> 4530.37 | BN17: =SUM(AM17:AQ17) -> 1157.07 | BO17: =SUM(AR17:AU17) -> 0 | BP17: =SUM(AV17:AY17) -> 0 | BQ17: =SUM(AZ17:BD17) -> 0 | BR17: =SUM(BF17:BQ17) -> 33158.72 | BS17: =SUM(BF17:BH17) -> 13380.9 | BT17: =SUM(BI17:BK17) -> 10606.52 | BU17: =SUM(BL17:BN17) -> 9171.3 | BV17: =SUM(BO17:BQ17) -> 0 | BW17: =SUM(BF17:BK17) -> 23987.42 | BX17: =SUM(BL17:BQ17) -> 9171.3 | BY17: =IF(Info!$O$3="Q1",$BS17,IF(Info!$O$3="Q2",$BS17+$BT17,IF(Info!$O$3="Q3",$BS17+$BT17+$BU17,$BR17))) -> 13380.9 | BZ17: =IF(Info!$O$3="Q1",$BS17,IF(Info!$O$3="Q2",$BT17,IF(Info!$O$3="Q3",$BU17,$BV17))) -> 13380.9
B18: Pcs put into the shop, shoes A | D18: =SUM(E18:BD18) -> 560.53 | E18: =SUM(Paniglgasse:Lerchenfelder!E18) -> 0 | F18: =SUM(Paniglgasse:Lerchenfelder!F18) -> 0 | G18: =SUM(Paniglgasse:Lerchenfelder!G18) -> 0 | H18: =SUM(Paniglgasse:Lerchenfelder!H18) -> 30 | I18: =SUM(Paniglgasse:Lerchenfelder!I18) -> 23.38 | J18: =SUM(Paniglgasse:Lerchenfelder!J18) -> 0 | K18: =SUM(Paniglgasse:Lerchenfelder!K18) -> 29 | L18: =SUM(Paniglgasse:Lerchenfelder!L18) -> 29 | ... BD18: =SUM(Paniglgasse:Lerchenfelder!BD18) -> 0 | BF18: =SUM(E18:H18) -> 30 | BG18: =SUM(I18:L18) -> 81.38 | BH18: =SUM(M18:Q18) -> 62.36 | BI18: =SUM(R18:U18) -> 30 | BJ18: =SUM(V18:Y18) -> 75.94 | BK18: =SUM(Z18:AD18) -> 132.6 | BL18: =SUM(AE18:AH18) -> 71.76 | BM18: =SUM(AI18:AL18) -> 0 | BN18: =SUM(AM18:AQ18) -> 76.49 | BO18: =SUM(AR18:AU18) -> 0 | BP18: =SUM(AV18:AY18) -> 0 | BQ18: =SUM(AZ18:BD18) -> 0 | BR18: =SUM(BF18:BQ18) -> 560.53 | BS18: =SUM(BF18:BH18) -> 173.74 | BT18: =SUM(BI18:BK18) -> 238.54 | BU18: =SUM(BL18:BN18) -> 148.25 | BV18: =SUM(BO18:BQ18) -> 0 | BW18: =SUM(BF18:BK18) -> 412.28 | BX18: =SUM(BL18:BQ18) -> 148.25 | BY18: =IF(Info!$O$3="Q1",$BS18,IF(Info!$O$3="Q2",$BS18+$BT18,IF(Info!$O$3="Q3",$BS18+$BT18+$BU18,$BR18))) -> 173.74 | BZ18: =IF(Info!$O$3="Q1",$BS18,IF(Info!$O$3="Q2",$BT18,IF(Info!$O$3="Q3",$BU18,$BV18))) -> 173.74
B19: Pcs put into the shop, shoes B | D19: =SUM(E19:BD19) -> 0 | E19: =SUM(Paniglgasse:Lerchenfelder!E19) -> 0 | F19: =SUM(Paniglgasse:Lerchenfelder!F19) -> 0 | G19: =SUM(Paniglgasse:Lerchenfelder!G19) -> 0 | H19: =SUM(Paniglgasse:Lerchenfelder!H19) -> 0 | I19: =SUM(Paniglgasse:Lerchenfelder!I19) -> 0 | J19: =SUM(Paniglgasse:Lerchenfelder!J19) -> 0 | K19: =SUM(Paniglgasse:Lerchenfelder!K19) -> 0 | L19: =SUM(Paniglgasse:Lerchenfelder!L19) -> 0 | ... BD19: =SUM(Paniglgasse:Lerchenfelder!BD19) -> 0 | BF19: =SUM(E19:H19) -> 0 | BG19: =SUM(I19:L19) -> 0 | BH19: =SUM(M19:Q19) -> 0 | BI19: =SUM(R19:U19) -> 0 | BJ19: =SUM(V19:Y19) -> 0 | BK19: =SUM(Z19:AD19) -> 0 | BL19: =SUM(AE19:AH19) -> 0 | BM19: =SUM(AI19:AL19) -> 0 | BN19: =SUM(AM19:AQ19) -> 0 | BO19: =SUM(AR19:AU19) -> 0 | BP19: =SUM(AV19:AY19) -> 0 | BQ19: =SUM(AZ19:BD19) -> 0 | BR19: =SUM(BF19:BQ19) -> 0 | BS19: =SUM(BF19:BH19) -> 0 | BT19: =SUM(BI19:BK19) -> 0 | BU19: =SUM(BL19:BN19) -> 0 | BV19: =SUM(BO19:BQ19) -> 0 | BW19: =SUM(BF19:BK19) -> 0 | BX19: =SUM(BL19:BQ19) -> 0 | BY19: =IF(Info!$O$3="Q1",$BS19,IF(Info!$O$3="Q2",$BS19+$BT19,IF(Info!$O$3="Q3",$BS19+$BT19+$BU19,$BR19))) -> 0 | BZ19: =IF(Info!$O$3="Q1",$BS19,IF(Info!$O$3="Q2",$BT19,IF(Info!$O$3="Q3",$BU19,$BV19))) -> 0
B20: Pcs put into the shop, HHR | D20: =SUM(E20:BD20) -> 22 | E20: =SUM(Paniglgasse:Lerchenfelder!E20) -> 0 | F20: =SUM(Paniglgasse:Lerchenfelder!F20) -> 0 | G20: =SUM(Paniglgasse:Lerchenfelder!G20) -> 0 | H20: =SUM(Paniglgasse:Lerchenfelder!H20) -> 0 | I20: =SUM(Paniglgasse:Lerchenfelder!I20) -> 0 | J20: =SUM(Paniglgasse:Lerchenfelder!J20) -> 0 | K20: =SUM(Paniglgasse:Lerchenfelder!K20) -> 0 | L20: =SUM(Paniglgasse:Lerchenfelder!L20) -> 0 | ... BD20: =SUM(Paniglgasse:Lerchenfelder!BD20) -> 0 | BF20: =SUM(E20:H20) -> 0 | BG20: =SUM(I20:L20) -> 0 | BH20: =SUM(M20:Q20) -> 0 | BI20: =SUM(R20:U20) -> 0 | BJ20: =SUM(V20:Y20) -> 0 | BK20: =SUM(Z20:AD20) -> 0 | BL20: =SUM(AE20:AH20) -> 0 | BM20: =SUM(AI20:AL20) -> 22 | BN20: =SUM(AM20:AQ20) -> 0 | BO20: =SUM(AR20:AU20) -> 0 | BP20: =SUM(AV20:AY20) -> 0 | BQ20: =SUM(AZ20:BD20) -> 0 | BR20: =SUM(BF20:BQ20) -> 22 | BS20: =SUM(BF20:BH20) -> 0 | BT20: =SUM(BI20:BK20) -> 0 | BU20: =SUM(BL20:BN20) -> 22 | BV20: =SUM(BO20:BQ20) -> 0 | BW20: =SUM(BF20:BK20) -> 0 | BX20: =SUM(BL20:BQ20) -> 22 | BY20: =IF(Info!$O$3="Q1",$BS20,IF(Info!$O$3="Q2",$BS20+$BT20,IF(Info!$O$3="Q3",$BS20+$BT20+$BU20,$BR20))) -> 0 | BZ20: =IF(Info!$O$3="Q1",$BS20,IF(Info!$O$3="Q2",$BT20,IF(Info!$O$3="Q3",$BU20,$BV20))) -> 0
B21: Pcs put into the shop, Mix Summer | D21: =SUM(E21:BD21) -> 0 | E21: =SUM(Paniglgasse:Lerchenfelder!E21) -> 0 | F21: =SUM(Paniglgasse:Lerchenfelder!F21) -> 0 | G21: =SUM(Paniglgasse:Lerchenfelder!G21) -> 0 | H21: =SUM(Paniglgasse:Lerchenfelder!H21) -> 0 | I21: =SUM(Paniglgasse:Lerchenfelder!I21) -> 0 | J21: =SUM(Paniglgasse:Lerchenfelder!J21) -> 0 | K21: =SUM(Paniglgasse:Lerchenfelder!K21) -> 0 | L21: =SUM(Paniglgasse:Lerchenfelder!L21) -> 0 | ... BD21: =SUM(Paniglgasse:Lerchenfelder!BD21) -> 0 | BF21: =SUM(E21:H21) -> 0 | BG21: =SUM(I21:L21) -> 0 | BH21: =SUM(M21:Q21) -> 0 | BI21: =SUM(R21:U21) -> 0 | BJ21: =SUM(V21:Y21) -> 0 | BK21: =SUM(Z21:AD21) -> 0 | BL21: =SUM(AE21:AH21) -> 0 | BM21: =SUM(AI21:AL21) -> 0 | BN21: =SUM(AM21:AQ21) -> 0 | BO21: =SUM(AR21:AU21) -> 0 | BP21: =SUM(AV21:AY21) -> 0 | BQ21: =SUM(AZ21:BD21) -> 0 | BR21: =SUM(BF21:BQ21) -> 0 | BS21: =SUM(BF21:BH21) -> 0 | BT21: =SUM(BI21:BK21) -> 0 | BU21: =SUM(BL21:BN21) -> 0 | BV21: =SUM(BO21:BQ21) -> 0 | BW21: =SUM(BF21:BK21) -> 0 | BX21: =SUM(BL21:BQ21) -> 0 | BY21: =IF(Info!$O$3="Q1",$BS21,IF(Info!$O$3="Q2",$BS21+$BT21,IF(Info!$O$3="Q3",$BS21+$BT21+$BU21,$BR21))) -> 0 | BZ21: =IF(Info!$O$3="Q1",$BS21,IF(Info!$O$3="Q2",$BT21,IF(Info!$O$3="Q3",$BU21,$BV21))) -> 0
B22: Pcs put into the shop, Mix Winter | D22: =SUM(E22:BD22) -> 0 | E22: =SUM(Paniglgasse:Lerchenfelder!E22) -> 0 | F22: =SUM(Paniglgasse:Lerchenfelder!F22) -> 0 | G22: =SUM(Paniglgasse:Lerchenfelder!G22) -> 0 | H22: =SUM(Paniglgasse:Lerchenfelder!H22) -> 0 | I22: =SUM(Paniglgasse:Lerchenfelder!I22) -> 0 | J22: =SUM(Paniglgasse:Lerchenfelder!J22) -> 0 | K22: =SUM(Paniglgasse:Lerchenfelder!K22) -> 0 | L22: =SUM(Paniglgasse:Lerchenfelder!L22) -> 0 | ... BD22: =SUM(Paniglgasse:Lerchenfelder!BD22) -> 0 | BF22: =SUM(E22:H22) -> 0 | BG22: =SUM(I22:L22) -> 0 | BH22: =SUM(M22:Q22) -> 0 | BI22: =SUM(R22:U22) -> 0 | BJ22: =SUM(V22:Y22) -> 0 | BK22: =SUM(Z22:AD22) -> 0 | BL22: =SUM(AE22:AH22) -> 0 | BM22: =SUM(AI22:AL22) -> 0 | BN22: =SUM(AM22:AQ22) -> 0 | BO22: =SUM(AR22:AU22) -> 0 | BP22: =SUM(AV22:AY22) -> 0 | BQ22: =SUM(AZ22:BD22) -> 0 | BR22: =SUM(BF22:BQ22) -> 0 | BS22: =SUM(BF22:BH22) -> 0 | BT22: =SUM(BI22:BK22) -> 0 | BU22: =SUM(BL22:BN22) -> 0 | BV22: =SUM(BO22:BQ22) -> 0 | BW22: =SUM(BF22:BK22) -> 0 | BX22: =SUM(BL22:BQ22) -> 0 | BY22: =IF(Info!$O$3="Q1",$BS22,IF(Info!$O$3="Q2",$BS22+$BT22,IF(Info!$O$3="Q3",$BS22+$BT22+$BU22,$BR22))) -> 0 | BZ22: =IF(Info!$O$3="Q1",$BS22,IF(Info!$O$3="Q2",$BT22,IF(Info!$O$3="Q3",$BU22,$BV22))) -> 0
B23: Pcs put into the shop, Handbag A | D23: =SUM(E23:BD23) -> 853.16 | E23: =SUM(Paniglgasse:Lerchenfelder!E23) -> 0 | F23: =SUM(Paniglgasse:Lerchenfelder!F23) -> 0 | G23: =SUM(Paniglgasse:Lerchenfelder!G23) -> 0 | H23: =SUM(Paniglgasse:Lerchenfelder!H23) -> 5.88 | I23: =SUM(Paniglgasse:Lerchenfelder!I23) -> 0 | J23: =SUM(Paniglgasse:Lerchenfelder!J23) -> 87.32 | K23: =SUM(Paniglgasse:Lerchenfelder!K23) -> 0 | L23: =SUM(Paniglgasse:Lerchenfelder!L23) -> 0 | ... BD23: =SUM(Paniglgasse:Lerchenfelder!BD23) -> 0 | BF23: =SUM(E23:H23) -> 5.88 | BG23: =SUM(I23:L23) -> 87.32 | BH23: =SUM(M23:Q23) -> 41 | BI23: =SUM(R23:U23) -> 37 | BJ23: =SUM(V23:Y23) -> 182.57 | BK23: =SUM(Z23:AD23) -> 182.54 | BL23: =SUM(AE23:AH23) -> 151.34 | BM23: =SUM(AI23:AL23) -> 0 | BN23: =SUM(AM23:AQ23) -> 165.51 | BO23: =SUM(AR23:AU23) -> 0 | BP23: =SUM(AV23:AY23) -> 0 | BQ23: =SUM(AZ23:BD23) -> 0 | BR23: =SUM(BF23:BQ23) -> 853.16 | BS23: =SUM(BF23:BH23) -> 134.2 | BT23: =SUM(BI23:BK23) -> 402.11 | BU23: =SUM(BL23:BN23) -> 316.85 | BV23: =SUM(BO23:BQ23) -> 0 | BW23: =SUM(BF23:BK23) -> 536.31 | BX23: =SUM(BL23:BQ23) -> 316.85 | BY23: =IF(Info!$O$3="Q1",$BS23,IF(Info!$O$3="Q2",$BS23+$BT23,IF(Info!$O$3="Q3",$BS23+$BT23+$BU23,$BR23))) -> 134.2 | BZ23: =IF(Info!$O$3="Q1",$BS23,IF(Info!$O$3="Q2",$BT23,IF(Info!$O$3="Q3",$BU23,$BV23))) -> 134.2
B24: Pcs put into the shop, Handbag B | D24: =SUM(E24:BD24) -> 86 | E24: =SUM(Paniglgasse:Lerchenfelder!E24) -> 0 | F24: =SUM(Paniglgasse:Lerchenfelder!F24) -> 0 | G24: =SUM(Paniglgasse:Lerchenfelder!G24) -> 0 | H24: =SUM(Paniglgasse:Lerchenfelder!H24) -> 0 | I24: =SUM(Paniglgasse:Lerchenfelder!I24) -> 0 | J24: =SUM(Paniglgasse:Lerchenfelder!J24) -> 0 | K24: =SUM(Paniglgasse:Lerchenfelder!K24) -> 0 | L24: =SUM(Paniglgasse:Lerchenfelder!L24) -> 0 | ... BD24: =SUM(Paniglgasse:Lerchenfelder!BD24) -> 0 | BF24: =SUM(E24:H24) -> 0 | BG24: =SUM(I24:L24) -> 0 | BH24: =SUM(M24:Q24) -> 0 | BI24: =SUM(R24:U24) -> 0 | BJ24: =SUM(V24:Y24) -> 0 | BK24: =SUM(Z24:AD24) -> 0 | BL24: =SUM(AE24:AH24) -> 0 | BM24: =SUM(AI24:AL24) -> 86 | BN24: =SUM(AM24:AQ24) -> 0 | BO24: =SUM(AR24:AU24) -> 0 | BP24: =SUM(AV24:AY24) -> 0 | BQ24: =SUM(AZ24:BD24) -> 0 | BR24: =SUM(BF24:BQ24) -> 86 | BS24: =SUM(BF24:BH24) -> 0 | BT24: =SUM(BI24:BK24) -> 0 | BU24: =SUM(BL24:BN24) -> 86 | BV24: =SUM(BO24:BQ24) -> 0 | BW24: =SUM(BF24:BK24) -> 0 | BX24: =SUM(BL24:BQ24) -> 86 | BY24: =IF(Info!$O$3="Q1",$BS24,IF(Info!$O$3="Q2",$BS24+$BT24,IF(Info!$O$3="Q3",$BS24+$BT24+$BU24,$BR24))) -> 0 | BZ24: =IF(Info!$O$3="Q1",$BS24,IF(Info!$O$3="Q2",$BT24,IF(Info!$O$3="Q3",$BU24,$BV24))) -> 0
B25: Pcs put into the shop, things | D25: =SUM(E25:BD25) -> 240.58 | E25: =SUM(Paniglgasse:Lerchenfelder!E25) -> 0 | F25: =SUM(Paniglgasse:Lerchenfelder!F25) -> 0 | G25: =SUM(Paniglgasse:Lerchenfelder!G25) -> 0 | H25: =SUM(Paniglgasse:Lerchenfelder!H25) -> 17.1 | I25: =SUM(Paniglgasse:Lerchenfelder!I25) -> 0 | J25: =SUM(Paniglgasse:Lerchenfelder!J25) -> 0 | K25: =SUM(Paniglgasse:Lerchenfelder!K25) -> 27.14 | L25: =SUM(Paniglgasse:Lerchenfelder!L25) -> 0 | ... BD25: =SUM(Paniglgasse:Lerchenfelder!BD25) -> 0 | BF25: =SUM(E25:H25) -> 17.1 | BG25: =SUM(I25:L25) -> 27.14 | BH25: =SUM(M25:Q25) -> 60.32 | BI25: =SUM(R25:U25) -> 5.1 | BJ25: =SUM(V25:Y25) -> 27.59 | BK25: =SUM(Z25:AD25) -> 47.33 | BL25: =SUM(AE25:AH25) -> 56 | BM25: =SUM(AI25:AL25) -> 0 | BN25: =SUM(AM25:AQ25) -> 0 | BO25: =SUM(AR25:AU25) -> 0 | BP25: =SUM(AV25:AY25) -> 0 | BQ25: =SUM(AZ25:BD25) -> 0 | BR25: =SUM(BF25:BQ25) -> 240.58 | BS25: =SUM(BF25:BH25) -> 104.56 | BT25: =SUM(BI25:BK25) -> 80.02 | BU25: =SUM(BL25:BN25) -> 56 | BV25: =SUM(BO25:BQ25) -> 0 | BW25: =SUM(BF25:BK25) -> 184.58 | BX25: =SUM(BL25:BQ25) -> 56 | BY25: =IF(Info!$O$3="Q1",$BS25,IF(Info!$O$3="Q2",$BS25+$BT25,IF(Info!$O$3="Q3",$BS25+$BT25+$BU25,$BR25))) -> 104.56 | BZ25: =IF(Info!$O$3="Q1",$BS25,IF(Info!$O$3="Q2",$BT25,IF(Info!$O$3="Q3",$BU25,$BV25))) -> 104.56
B26: Pcs put into the shop, Old extra | D26: =SUM(E26:BD26) -> 0 | E26: =SUM(Paniglgasse:Lerchenfelder!E26) -> 0 | F26: =SUM(Paniglgasse:Lerchenfelder!F26) -> 0 | G26: =SUM(Paniglgasse:Lerchenfelder!G26) -> 0 | H26: =SUM(Paniglgasse:Lerchenfelder!H26) -> 0 | I26: =SUM(Paniglgasse:Lerchenfelder!I26) -> 0 | J26: =SUM(Paniglgasse:Lerchenfelder!J26) -> 0 | K26: =SUM(Paniglgasse:Lerchenfelder!K26) -> 0 | L26: =SUM(Paniglgasse:Lerchenfelder!L26) -> 0 | ... BD26: =SUM(Paniglgasse:Lerchenfelder!BD26) -> 0 | BF26: =SUM(E26:H26) -> 0 | BG26: =SUM(I26:L26) -> 0 | BH26: =SUM(M26:Q26) -> 0 | BI26: =SUM(R26:U26) -> 0 | BJ26: =SUM(V26:Y26) -> 0 | BK26: =SUM(Z26:AD26) -> 0 | BL26: =SUM(AE26:AH26) -> 0 | BM26: =SUM(AI26:AL26) -> 0 | BN26: =SUM(AM26:AQ26) -> 0 | BO26: =SUM(AR26:AU26) -> 0 | BP26: =SUM(AV26:AY26) -> 0 | BQ26: =SUM(AZ26:BD26) -> 0 | BR26: =SUM(BF26:BQ26) -> 0 | BS26: =SUM(BF26:BH26) -> 0 | BT26: =SUM(BI26:BK26) -> 0 | BU26: =SUM(BL26:BN26) -> 0 | BV26: =SUM(BO26:BQ26) -> 0 | BW26: =SUM(BF26:BK26) -> 0 | BX26: =SUM(BL26:BQ26) -> 0 | BY26: =IF(Info!$O$3="Q1",$BS26,IF(Info!$O$3="Q2",$BS26+$BT26,IF(Info!$O$3="Q3",$BS26+$BT26+$BU26,$BR26))) -> 0 | BZ26: =IF(Info!$O$3="Q1",$BS26,IF(Info!$O$3="Q2",$BT26,IF(Info!$O$3="Q3",$BU26,$BV26))) -> 0
B27: Pcs put into the shop, total | D27: =SUM(E27:BD27) -> 79523.05 | E27: =SUM(E15:E26) -> 1291.48 | F27: =SUM(F15:F26) -> 1161.21 | G27: =SUM(G15:G26) -> 2234.33 | H27: =SUM(H15:H26) -> 4303.12 | I27: =SUM(I15:I26) -> 1176.88 | J27: =SUM(J15:J26) -> 1465.07 | K27: =SUM(K15:K26) -> 1226.9 | L27: =SUM(L15:L26) -> 2224.59 | ... BD27: =SUM(BD15:BD26) -> 0 | BF27: =SUM(E27:H27) -> 8990.14 | BG27: =SUM(I27:L27) -> 6093.44 | BH27: =SUM(M27:Q27) -> 11080 | BI27: =SUM(R27:U27) -> 8608.27 | BJ27: =SUM(V27:Y27) -> 9757.41 | BK27: =SUM(Z27:AD27) -> 11859.03 | BL27: =SUM(AE27:AH27) -> 9599.9 | BM27: =SUM(AI27:AL27) -> 5703.4 | BN27: =SUM(AM27:AQ27) -> 7831.46 | BO27: =SUM(AR27:AU27) -> 0 | BP27: =SUM(AV27:AY27) -> 0 | BQ27: =SUM(AZ27:BD27) -> 0 | BR27: =SUM(BF27:BQ27) -> 79523.05 | BS27: =SUM(BF27:BH27) -> 26163.58 | BT27: =SUM(BI27:BK27) -> 30224.71 | BU27: =SUM(BL27:BN27) -> 23134.76 | BV27: =SUM(BO27:BQ27) -> 0 | BW27: =SUM(BF27:BK27) -> 56388.29 | BX27: =SUM(BL27:BQ27) -> 23134.76 | BY27: =IF(Info!$O$3="Q1",$BS27,IF(Info!$O$3="Q2",$BS27+$BT27,IF(Info!$O$3="Q3",$BS27+$BT27+$BU27,$BR27))) -> 26163.58 | BZ27: =IF(Info!$O$3="Q1",$BS27,IF(Info!$O$3="Q2",$BT27,IF(Info!$O$3="Q3",$BU27,$BV27))) -> 26163.58
B28: Pcs put into the shop, total (excl. total new opening) | D28: =SUM(E28:BD28) -> 52585.02 | E28: =E27-E15 -> 1291.48 | F28: =F27-F15 -> 1161.21 | G28: =G27-G15 -> 2234.33 | H28: =H27-H15 -> 628.72 | I28: =I27-I15 -> 1176.88 | J28: =J27-J15 -> 1465.07 | K28: =K27-K15 -> 1226.9 | L28: =L27-L15 -> 2224.59 | ... BD28: =BD27-BD15 -> 0 | BF28: =SUM(E28:H28) -> 5315.74 | BG28: =SUM(I28:L28) -> 6093.44 | BH28: =SUM(M28:Q28) -> 7131.11 | BI28: =SUM(R28:U28) -> 4615.71 | BJ28: =SUM(V28:Y28) -> 5916.87 | BK28: =SUM(Z28:AD28) -> 7747.79 | BL28: =SUM(AE28:AH28) -> 5892.36 | BM28: =SUM(AI28:AL28) -> 5703.4 | BN28: =SUM(AM28:AQ28) -> 4168.6 | BO28: =SUM(AR28:AU28) -> 0 | BP28: =SUM(AV28:AY28) -> 0 | BQ28: =SUM(AZ28:BD28) -> 0 | BR28: =SUM(BF28:BQ28) -> 52585.02 | BS28: =SUM(BF28:BH28) -> 18540.29 | BT28: =SUM(BI28:BK28) -> 18280.37 | BU28: =SUM(BL28:BN28) -> 15764.36 | BV28: =SUM(BO28:BQ28) -> 0 | BW28: =SUM(BF28:BK28) -> 36820.66 | BX28: =SUM(BL28:BQ28) -> 15764.36 | BY28: =IF(Info!$O$3="Q1",$BS28,IF(Info!$O$3="Q2",$BS28+$BT28,IF(Info!$O$3="Q3",$BS28+$BT28+$BU28,$BR28))) -> 18540.29 | BZ28: =IF(Info!$O$3="Q1",$BS28,IF(Info!$O$3="Q2",$BT28,IF(Info!$O$3="Q3",$BU28,$BV28))) -> 18540.29
B29: Pcs sold | D29: =SUM(E29:BD29) -> 67086.19 | E29: =SUM(Paniglgasse:Lerchenfelder!E29) -> 1596.81 | F29: =SUM(Paniglgasse:Lerchenfelder!F29) -> 1303.52 | G29: =SUM(Paniglgasse:Lerchenfelder!G29) -> 2431.37 | H29: =SUM(Paniglgasse:Lerchenfelder!H29) -> 2153.16 | I29: =SUM(Paniglgasse:Lerchenfelder!I29) -> 1222.36 | J29: =SUM(Paniglgasse:Lerchenfelder!J29) -> 1355.75 | K29: =SUM(Paniglgasse:Lerchenfelder!K29) -> 1439.58 | L29: =SUM(Paniglgasse:Lerchenfelder!L29) -> 3043.73 | ... BD29: =SUM(Paniglgasse:Lerchenfelder!BD29) -> 0 | BF29: =SUM(E29:H29) -> 7484.86 | BG29: =SUM(I29:L29) -> 7061.42 | BH29: =SUM(M29:Q29) -> 8498.21 | BI29: =SUM(R29:U29) -> 6411.73 | BJ29: =SUM(V29:Y29) -> 7805.26 | BK29: =SUM(Z29:AD29) -> 9972.85 | BL29: =SUM(AE29:AH29) -> 7850.24 | BM29: =SUM(AI29:AL29) -> 6356.78 | BN29: =SUM(AM29:AQ29) -> 5644.84 | BO29: =SUM(AR29:AU29) -> 0 | BP29: =SUM(AV29:AY29) -> 0 | BQ29: =SUM(AZ29:BD29) -> 0 | BR29: =SUM(BF29:BQ29) -> 67086.19 | BS29: =SUM(BF29:BH29) -> 23044.49 | BT29: =SUM(BI29:BK29) -> 24189.84 | BU29: =SUM(BL29:BN29) -> 19851.86 | BV29: =SUM(BO29:BQ29) -> 0 | BW29: =SUM(BF29:BK29) -> 47234.33 | BX29: =SUM(BL29:BQ29) -> 19851.86 | BY29: =IF(Info!$O$3="Q1",$BS29,IF(Info!$O$3="Q2",$BS29+$BT29,IF(Info!$O$3="Q3",$BS29+$BT29+$BU29,$BR29))) -> 23044.49 | BZ29: =IF(Info!$O$3="Q1",$BS29,IF(Info!$O$3="Q2",$BT29,IF(Info!$O$3="Q3",$BU29,$BV29))) -> 23044.49
B30: Pcs taken down | D30: =SUM(E30:BD30) -> 12233.05 | E30: =SUM(Paniglgasse:Lerchenfelder!E30) -> 0 | F30: =SUM(Paniglgasse:Lerchenfelder!F30) -> 0 | G30: =SUM(Paniglgasse:Lerchenfelder!G30) -> 0 | H30: =SUM(Paniglgasse:Lerchenfelder!H30) -> 1625.45 | I30: =SUM(Paniglgasse:Lerchenfelder!I30) -> 1 | J30: =SUM(Paniglgasse:Lerchenfelder!J30) -> 3 | K30: =SUM(Paniglgasse:Lerchenfelder!K30) -> 0 | L30: =SUM(Paniglgasse:Lerchenfelder!L30) -> 5 | ... BD30: =SUM(Paniglgasse:Lerchenfelder!BD30) -> 0 | BF30: =SUM(E30:H30) -> 1625.45 | BG30: =SUM(I30:L30) -> 9 | BH30: =SUM(M30:Q30) -> 1452.88 | BI30: =SUM(R30:U30) -> 1490.68 | BJ30: =SUM(V30:Y30) -> 1737.39 | BK30: =SUM(Z30:AD30) -> 1983.56 | BL30: =SUM(AE30:AH30) -> 1711.54 | BM30: =SUM(AI30:AL30) -> 14.04 | BN30: =SUM(AM30:AQ30) -> 2208.51 | BO30: =SUM(AR30:AU30) -> 0 | BP30: =SUM(AV30:AY30) -> 0 | BQ30: =SUM(AZ30:BD30) -> 0 | BR30: =SUM(BF30:BQ30) -> 12233.05 | BS30: =SUM(BF30:BH30) -> 3087.33 | BT30: =SUM(BI30:BK30) -> 5211.63 | BU30: =SUM(BL30:BN30) -> 3934.09 | BV30: =SUM(BO30:BQ30) -> 0 | BW30: =SUM(BF30:BK30) -> 8298.96 | BX30: =SUM(BL30:BQ30) -> 3934.09 | BY30: =IF(Info!$O$3="Q1",$BS30,IF(Info!$O$3="Q2",$BS30+$BT30,IF(Info!$O$3="Q3",$BS30+$BT30+$BU30,$BR30))) -> 3087.33 | BZ30: =IF(Info!$O$3="Q1",$BS30,IF(Info!$O$3="Q2",$BT30,IF(Info!$O$3="Q3",$BU30,$BV30))) -> 3087.33
B31: Old extra | D31: =SUM(E31:BD31) -> 211.76 | E31: =SUM(Paniglgasse:Lerchenfelder!E31) -> 0 | F31: =SUM(Paniglgasse:Lerchenfelder!F31) -> 0 | G31: =SUM(Paniglgasse:Lerchenfelder!G31) -> 0 | H31: =SUM(Paniglgasse:Lerchenfelder!H31) -> 0 | I31: =SUM(Paniglgasse:Lerchenfelder!I31) -> 0 | J31: =SUM(Paniglgasse:Lerchenfelder!J31) -> 0 | K31: =SUM(Paniglgasse:Lerchenfelder!K31) -> 0 | L31: =SUM(Paniglgasse:Lerchenfelder!L31) -> 3.56 | ... BD31: =SUM(Paniglgasse:Lerchenfelder!BD31) -> 0 | BF31: =SUM(E31:H31) -> 0 | BG31: =SUM(I31:L31) -> 3.56 | BH31: =SUM(M31:Q31) -> 3.79 | BI31: =SUM(R31:U31) -> 0 | BJ31: =SUM(V31:Y31) -> 2.27 | BK31: =SUM(Z31:AD31) -> 71.85 | BL31: =SUM(AE31:AH31) -> 17.11 | BM31: =SUM(AI31:AL31) -> 3 | BN31: =SUM(AM31:AQ31) -> 110.18 | BO31: =SUM(AR31:AU31) -> 0 | BP31: =SUM(AV31:AY31) -> 0 | BQ31: =SUM(AZ31:BD31) -> 0 | BR31: =SUM(BF31:BQ31) -> 211.76 | BS31: =SUM(BF31:BH31) -> 7.35 | BT31: =SUM(BI31:BK31) -> 74.12 | BU31: =SUM(BL31:BN31) -> 130.29 | BV31: =SUM(BO31:BQ31) -> 0 | BW31: =SUM(BF31:BK31) -> 81.47 | BX31: =SUM(BL31:BQ31) -> 130.29 | BY31: =IF(Info!$O$3="Q1",$BS31,IF(Info!$O$3="Q2",$BS31+$BT31,IF(Info!$O$3="Q3",$BS31+$BT31+$BU31,$BR31))) -> 7.35 | BZ31: =IF(Info!$O$3="Q1",$BS31,IF(Info!$O$3="Q2",$BT31,IF(Info!$O$3="Q3",$BU31,$BV31))) -> 7.35
B32: Pcs in the shop, end of week | D32: =SUM(E32:BD32) -> 122373.89 | E32: =IF(E15=0,E6+E27-E29-E30-E31-E5,E27-E29-E30-E31-E5) -> 2477.79 | F32: =IF(F15=0,F6+F27-F29-F30-F31-F5,E32+F15+F28-F29-F30-F31-F5) -> 2360.66 | G32: =IF(G15=0,G6+G27-G29-G30-G31-G5,F32+G15+G28-G29-G30-G31-G5) -> 2240.25 | H32: =IF(H15=0,H6+H27-H29-H30-H31-H5,G32+H15+H28-H29-H30-H31-H5) -> 2754.08 | I32: =IF(I15=0,I6+I27-I29-I30-I31-I5,H32+I15+I28-I29-I30-I31-I5) -> 2746.6 | J32: =IF(J15=0,J6+J27-J29-J30-J31-J5,I32+J15+J28-J29-J30-J31-J5) -> 2811.36 | K32: =IF(K15=0,K6+K27-K29-K30-K31-K5,J32+K15+K28-K29-K30-K31-K5) -> 2588.68 | L32: =IF(L15=0,L6+L27-L29-L30-L31-L5,K32+L15+L28-L29-L30-L31-L5) -> 1721.83 | M32: =IF(M15=0,M6+M27-M29-M30-M31-M5,L32+M15+M28-M29-M30-M31-M5) -> 2891.31 | ... BD32: =IF(BD15=0,BD6+BD27-BD29-BD30-BD31-BD5,BC32+BD15+BD28-BD29-BD30-BD31-BD5) -> 1703.2 | BF32: =SUM(E32:H32) -> 9832.78 | BG32: =SUM(I32:L32) -> 9868.47 | BH32: =SUM(M32:Q32) -> 14916.57 | BI32: =SUM(R32:U32) -> 12703.57 | BJ32: =SUM(V32:Y32) -> 11529.33 | BK32: =SUM(Z32:AD32) -> 13305.95 | BL32: =SUM(AE32:AH32) -> 9695.15 | BM32: =SUM(AI32:AL32) -> 9908.91 | BN32: =SUM(AM32:AQ32) -> 8471.56 | BO32: =SUM(AR32:AU32) -> 6812.8 | BP32: =SUM(AV32:AY32) -> 6812.8 | BQ32: =SUM(AZ32:BD32) -> 8516 | BR32: =SUM(BF32:BQ32) -> 122373.89 | BS32: =SUM(BF32:BH32) -> 34617.82 | BT32: =SUM(BI32:BK32) -> 37538.85 | BU32: =SUM(BL32:BN32) -> 28075.62 | BV32: =SUM(BO32:BQ32) -> 22141.6 | BW32: =SUM(BF32:BK32) -> 72156.67 | BX32: =SUM(BL32:BQ32) -> 50217.22 | BY32: =IF(Info!$O$3="Q1",$BS32,IF(Info!$O$3="Q2",$BS32+$BT32,IF(Info!$O$3="Q3",$BS32+$BT32+$BU32,$BR32))) -> 34617.82 | BZ32: =IF(Info!$O$3="Q1",$BS32,IF(Info!$O$3="Q2",$BT32,IF(Info!$O$3="Q3",$BU32,$BV32))) -> 34617.82
B33: Pcs prepared for next new opening | D33: =SUM(E33:BD33) -> 31837.19 | E33: =SUM(Paniglgasse:Lerchenfelder!E33) -> 0 | F33: =SUM(Paniglgasse:Lerchenfelder!F33) -> 506.88 | G33: =SUM(Paniglgasse:Lerchenfelder!G33) -> 3017.96 | H33: =SUM(Paniglgasse:Lerchenfelder!H33) -> 1932.46 | I33: =SUM(Paniglgasse:Lerchenfelder!I33) -> 700.94 | J33: =SUM(Paniglgasse:Lerchenfelder!J33) -> 438.74 | K33: =SUM(Paniglgasse:Lerchenfelder!K33) -> 813.74 | L33: =SUM(Paniglgasse:Lerchenfelder!L33) -> 2374.48 | ... BD33: =SUM(Paniglgasse:Lerchenfelder!BD33) -> 0 | BF33: =SUM(E33:H33) -> 5457.3 | BG33: =SUM(I33:L33) -> 4327.9 | BH33: =SUM(M33:Q33) -> 1471.15 | BI33: =SUM(R33:U33) -> 0 | BJ33: =SUM(V33:Y33) -> 1281.47 | BK33: =SUM(Z33:AD33) -> 5082.91 | BL33: =SUM(AE33:AH33) -> 6034.84 | BM33: =SUM(AI33:AL33) -> 3385.99 | BN33: =SUM(AM33:AQ33) -> 4795.63 | BO33: =SUM(AR33:AU33) -> 0 | BP33: =SUM(AV33:AY33) -> 0 | BQ33: =SUM(AZ33:BD33) -> 0 | BR33: =SUM(BF33:BQ33) -> 31837.19 | BS33: =SUM(BF33:BH33) -> 11256.35 | BT33: =SUM(BI33:BK33) -> 6364.38 | BU33: =SUM(BL33:BN33) -> 14216.46 | BV33: =SUM(BO33:BQ33) -> 0 | BW33: =SUM(BF33:BK33) -> 17620.73 | BX33: =SUM(BL33:BQ33) -> 14216.46 | BY33: =IF(Info!$O$3="Q1",$BS33,IF(Info!$O$3="Q2",$BS33+$BT33,IF(Info!$O$3="Q3",$BS33+$BT33+$BU33,$BR33))) -> 11256.35 | BZ33: =IF(Info!$O$3="Q1",$BS33,IF(Info!$O$3="Q2",$BT33,IF(Info!$O$3="Q3",$BU33,$BV33))) -> 11256.35
B34: Kgs used for Pcs prepared for next new opening | D34: =SUM(E34:BD34) -> 11878.11 | E34: =SUM(Paniglgasse:Lerchenfelder!E34) -> 0 | F34: =SUM(Paniglgasse:Lerchenfelder!F34) -> 273.11 | G34: =SUM(Paniglgasse:Lerchenfelder!G34) -> 1437.14 | H34: =SUM(Paniglgasse:Lerchenfelder!H34) -> 864.69 | I34: =SUM(Paniglgasse:Lerchenfelder!I34) -> 197.15 | J34: =SUM(Paniglgasse:Lerchenfelder!J34) -> 191.78 | K34: =SUM(Paniglgasse:Lerchenfelder!K34) -> 372.47 | L34: =SUM(Paniglgasse:Lerchenfelder!L34) -> 892.38 | ... BD34: =SUM(Paniglgasse:Lerchenfelder!BD34) -> 0 | BF34: =SUM(E34:H34) -> 2574.94 | BG34: =SUM(I34:L34) -> 1653.78 | BH34: =SUM(M34:Q34) -> 467.07 | BI34: =SUM(R34:U34) -> 0 | BJ34: =SUM(V34:Y34) -> 327.93 | BK34: =SUM(Z34:AD34) -> 1832 | BL34: =SUM(AE34:AH34) -> 2085.58 | BM34: =SUM(AI34:AL34) -> 1042.94 | BN34: =SUM(AM34:AQ34) -> 1893.87 | BO34: =SUM(AR34:AU34) -> 0 | BP34: =SUM(AV34:AY34) -> 0 | BQ34: =SUM(AZ34:BD34) -> 0 | BR34: =SUM(BF34:BQ34) -> 11878.11 | BS34: =SUM(BF34:BH34) -> 4695.79 | BT34: =SUM(BI34:BK34) -> 2159.93 | BU34: =SUM(BL34:BN34) -> 5022.39 | BV34: =SUM(BO34:BQ34) -> 0 | BW34: =SUM(BF34:BK34) -> 6855.72 | BX34: =SUM(BL34:BQ34) -> 5022.39 | BY34: =IF(Info!$O$3="Q1",$BS34,IF(Info!$O$3="Q2",$BS34+$BT34,IF(Info!$O$3="Q3",$BS34+$BT34+$BU34,$BR34))) -> 4695.79 | BZ34: =IF(Info!$O$3="Q1",$BS34,IF(Info!$O$3="Q2",$BT34,IF(Info!$O$3="Q3",$BU34,$BV34))) -> 4695.79
B36: Kgs received clothes | D36: =SUM(E36:BD36) -> 27488.3 | E36: =SUM(Paniglgasse:Lerchenfelder!E36) -> 0 | F36: =SUM(Paniglgasse:Lerchenfelder!F36) -> 1994.14 | G36: =SUM(Paniglgasse:Lerchenfelder!G36) -> 371.72 | H36: =SUM(Paniglgasse:Lerchenfelder!H36) -> 860.93 | I36: =SUM(Paniglgasse:Lerchenfelder!I36) -> 865.82 | J36: =SUM(Paniglgasse:Lerchenfelder!J36) -> 1060.53 | K36: =SUM(Paniglgasse:Lerchenfelder!K36) -> 1316.42 | L36: =SUM(Paniglgasse:Lerchenfelder!L36) -> 1395.6 | ... BD36: =SUM(Paniglgasse:Lerchenfelder!BD36) -> 0 | BF36: =SUM(E36:H36) -> 3226.79 | BG36: =SUM(I36:L36) -> 4638.37 | BH36: =SUM(M36:Q36) -> 3067.43 | BI36: =SUM(R36:U36) -> 2778.43 | BJ36: =SUM(V36:Y36) -> 1746.79 | BK36: =SUM(Z36:AD36) -> 4556.13 | BL36: =SUM(AE36:AH36) -> 2003.61 | BM36: =SUM(AI36:AL36) -> 2736.35 | BN36: =SUM(AM36:AQ36) -> 2734.4 | BO36: =SUM(AR36:AU36) -> 0 | BP36: =SUM(AV36:AY36) -> 0 | BQ36: =SUM(AZ36:BD36) -> 0 | BR36: =SUM(BF36:BQ36) -> 27488.3 | BS36: =SUM(BF36:BH36) -> 10932.59 | BT36: =SUM(BI36:BK36) -> 9081.35 | BU36: =SUM(BL36:BN36) -> 7474.36 | BV36: =SUM(BO36:BQ36) -> 0 | BW36: =SUM(BF36:BK36) -> 20013.94 | BX36: =SUM(BL36:BQ36) -> 7474.36 | BY36: =IF(Info!$O$3="Q1",$BS36,IF(Info!$O$3="Q2",$BS36+$BT36,IF(Info!$O$3="Q3",$BS36+$BT36+$BU36,$BR36))) -> 10932.59 | BZ36: =IF(Info!$O$3="Q1",$BS36,IF(Info!$O$3="Q2",$BT36,IF(Info!$O$3="Q3",$BU36,$BV36))) -> 10932.59
B37: Kgs put into the shop, shop A | D37: =SUM(E37:BD37) -> 13250.27 | E37: =SUM(Paniglgasse:Lerchenfelder!E37) -> 234.93 | F37: =SUM(Paniglgasse:Lerchenfelder!F37) -> 0 | G37: =SUM(Paniglgasse:Lerchenfelder!G37) -> 0 | H37: =SUM(Paniglgasse:Lerchenfelder!H37) -> 1676.32 | I37: =SUM(Paniglgasse:Lerchenfelder!I37) -> 607 | J37: =SUM(Paniglgasse:Lerchenfelder!J37) -> 93 | K37: =SUM(Paniglgasse:Lerchenfelder!K37) -> 0 | L37: =SUM(Paniglgasse:Lerchenfelder!L37) -> 0 | ... BD37: =SUM(Paniglgasse:Lerchenfelder!BD37) -> 0 | BF37: =SUM(E37:H37) -> 1911.25 | BG37: =SUM(I37:L37) -> 700 | BH37: =SUM(M37:Q37) -> 1844.92 | BI37: =SUM(R37:U37) -> 1536.96 | BJ37: =SUM(V37:Y37) -> 1720.46 | BK37: =SUM(Z37:AD37) -> 1507.61 | BL37: =SUM(AE37:AH37) -> 1390.41 | BM37: =SUM(AI37:AL37) -> 519.76 | BN37: =SUM(AM37:AQ37) -> 2118.9 | BO37: =SUM(AR37:AU37) -> 0 | BP37: =SUM(AV37:AY37) -> 0 | BQ37: =SUM(AZ37:BD37) -> 0 | BR37: =SUM(BF37:BQ37) -> 13250.27 | BS37: =SUM(BF37:BH37) -> 4456.17 | BT37: =SUM(BI37:BK37) -> 4765.03 | BU37: =SUM(BL37:BN37) -> 4029.07 | BV37: =SUM(BO37:BQ37) -> 0 | BW37: =SUM(BF37:BK37) -> 9221.2 | BX37: =SUM(BL37:BQ37) -> 4029.07 | BY37: =IF(Info!$O$3="Q1",$BS37,IF(Info!$O$3="Q2",$BS37+$BT37,IF(Info!$O$3="Q3",$BS37+$BT37+$BU37,$BR37))) -> 4456.17 | BZ37: =IF(Info!$O$3="Q1",$BS37,IF(Info!$O$3="Q2",$BT37,IF(Info!$O$3="Q3",$BU37,$BV37))) -> 4456.17
B38: Kgs put into the shop, shop B | D38: =SUM(E38:BD38) -> 11329.59 | E38: =SUM(Paniglgasse:Lerchenfelder!E38) -> 350.07 | F38: =SUM(Paniglgasse:Lerchenfelder!F38) -> 584.3 | G38: =SUM(Paniglgasse:Lerchenfelder!G38) -> 990.32 | H38: =SUM(Paniglgasse:Lerchenfelder!H38) -> 0 | I38: =SUM(Paniglgasse:Lerchenfelder!I38) -> 0 | J38: =SUM(Paniglgasse:Lerchenfelder!J38) -> 451.7 | K38: =SUM(Paniglgasse:Lerchenfelder!K38) -> 538.74 | L38: =SUM(Paniglgasse:Lerchenfelder!L38) -> 978.54 | ... BD38: =SUM(Paniglgasse:Lerchenfelder!BD38) -> 0 | BF38: =SUM(E38:H38) -> 1924.69 | BG38: =SUM(I38:L38) -> 1968.98 | BH38: =SUM(M38:Q38) -> 1805.65 | BI38: =SUM(R38:U38) -> 774.89 | BJ38: =SUM(V38:Y38) -> 912.93 | BK38: =SUM(Z38:AD38) -> 1570.88 | BL38: =SUM(AE38:AH38) -> 936.72 | BM38: =SUM(AI38:AL38) -> 1043 | BN38: =SUM(AM38:AQ38) -> 391.85 | BO38: =SUM(AR38:AU38) -> 0 | BP38: =SUM(AV38:AY38) -> 0 | BQ38: =SUM(AZ38:BD38) -> 0 | BR38: =SUM(BF38:BQ38) -> 11329.59 | BS38: =SUM(BF38:BH38) -> 5699.32 | BT38: =SUM(BI38:BK38) -> 3258.7 | BU38: =SUM(BL38:BN38) -> 2371.57 | BV38: =SUM(BO38:BQ38) -> 0 | BW38: =SUM(BF38:BK38) -> 8958.02 | BX38: =SUM(BL38:BQ38) -> 2371.57 | BY38: =IF(Info!$O$3="Q1",$BS38,IF(Info!$O$3="Q2",$BS38+$BT38,IF(Info!$O$3="Q3",$BS38+$BT38+$BU38,$BR38))) -> 5699.32 | BZ38: =IF(Info!$O$3="Q1",$BS38,IF(Info!$O$3="Q2",$BT38,IF(Info!$O$3="Q3",$BU38,$BV38))) -> 5699.32
B39: Kgs put into the shop, HHR | D39: =SUM(E39:BD39) -> 0 | E39: =SUM(Paniglgasse:Lerchenfelder!E39) -> 0 | F39: =SUM(Paniglgasse:Lerchenfelder!F39) -> 0 | G39: =SUM(Paniglgasse:Lerchenfelder!G39) -> 0 | H39: =SUM(Paniglgasse:Lerchenfelder!H39) -> 0 | I39: =SUM(Paniglgasse:Lerchenfelder!I39) -> 0 | J39: =SUM(Paniglgasse:Lerchenfelder!J39) -> 0 | K39: =SUM(Paniglgasse:Lerchenfelder!K39) -> 0 | L39: =SUM(Paniglgasse:Lerchenfelder!L39) -> 0 | ... BD39: =SUM(Paniglgasse:Lerchenfelder!BD39) -> 0 | BF39: =SUM(E39:H39) -> 0 | BG39: =SUM(I39:L39) -> 0 | BH39: =SUM(M39:Q39) -> 0 | BI39: =SUM(R39:U39) -> 0 | BJ39: =SUM(V39:Y39) -> 0 | BK39: =SUM(Z39:AD39) -> 0 | BL39: =SUM(AE39:AH39) -> 0 | BM39: =SUM(AI39:AL39) -> 0 | BN39: =SUM(AM39:AQ39) -> 0 | BO39: =SUM(AR39:AU39) -> 0 | BP39: =SUM(AV39:AY39) -> 0 | BQ39: =SUM(AZ39:BD39) -> 0 | BR39: =SUM(BF39:BQ39) -> 0 | BS39: =SUM(BF39:BH39) -> 0 | BT39: =SUM(BI39:BK39) -> 0 | BU39: =SUM(BL39:BN39) -> 0 | BV39: =SUM(BO39:BQ39) -> 0 | BW39: =SUM(BF39:BK39) -> 0 | BX39: =SUM(BL39:BQ39) -> 0 | BY39: =IF(Info!$O$3="Q1",$BS39,IF(Info!$O$3="Q2",$BS39+$BT39,IF(Info!$O$3="Q3",$BS39+$BT39+$BU39,$BR39))) -> 0 | BZ39: =IF(Info!$O$3="Q1",$BS39,IF(Info!$O$3="Q2",$BT39,IF(Info!$O$3="Q3",$BU39,$BV39))) -> 0
B40: Kgs put into the shop, shoes A | D40: =SUM(E40:BD40) -> 868.74 | E40: =SUM(Paniglgasse:Lerchenfelder!E40) -> 0 | F40: =SUM(Paniglgasse:Lerchenfelder!F40) -> 0 | G40: =SUM(Paniglgasse:Lerchenfelder!G40) -> 0 | H40: =SUM(Paniglgasse:Lerchenfelder!H40) -> 65.32 | I40: =SUM(Paniglgasse:Lerchenfelder!I40) -> 29.01 | J40: =SUM(Paniglgasse:Lerchenfelder!J40) -> 0 | K40: =SUM(Paniglgasse:Lerchenfelder!K40) -> 23 | L40: =SUM(Paniglgasse:Lerchenfelder!L40) -> 23 | ... BD40: =SUM(Paniglgasse:Lerchenfelder!BD40) -> 0 | BF40: =SUM(E40:H40) -> 65.32 | BG40: =SUM(I40:L40) -> 75.01 | BH40: =SUM(M40:Q40) -> 114.19 | BI40: =SUM(R40:U40) -> 66.83 | BJ40: =SUM(V40:Y40) -> 130.85 | BK40: =SUM(Z40:AD40) -> 114.38 | BL40: =SUM(AE40:AH40) -> 130.28 | BM40: =SUM(AI40:AL40) -> 20 | BN40: =SUM(AM40:AQ40) -> 151.88 | BO40: =SUM(AR40:AU40) -> 0 | BP40: =SUM(AV40:AY40) -> 0 | BQ40: =SUM(AZ40:BD40) -> 0 | BR40: =SUM(BF40:BQ40) -> 868.74 | BS40: =SUM(BF40:BH40) -> 254.52 | BT40: =SUM(BI40:BK40) -> 312.06 | BU40: =SUM(BL40:BN40) -> 302.16 | BV40: =SUM(BO40:BQ40) -> 0 | BW40: =SUM(BF40:BK40) -> 566.58 | BX40: =SUM(BL40:BQ40) -> 302.16 | BY40: =IF(Info!$O$3="Q1",$BS40,IF(Info!$O$3="Q2",$BS40+$BT40,IF(Info!$O$3="Q3",$BS40+$BT40+$BU40,$BR40))) -> 254.52 | BZ40: =IF(Info!$O$3="Q1",$BS40,IF(Info!$O$3="Q2",$BT40,IF(Info!$O$3="Q3",$BU40,$BV40))) -> 254.52
B41: Kgs put into the shop, shoes B | D41: =SUM(E41:BD41) -> 0 | E41: =SUM(Paniglgasse:Lerchenfelder!E41) -> 0 | F41: =SUM(Paniglgasse:Lerchenfelder!F41) -> 0 | G41: =SUM(Paniglgasse:Lerchenfelder!G41) -> 0 | H41: =SUM(Paniglgasse:Lerchenfelder!H41) -> 0 | I41: =SUM(Paniglgasse:Lerchenfelder!I41) -> 0 | J41: =SUM(Paniglgasse:Lerchenfelder!J41) -> 0 | K41: =SUM(Paniglgasse:Lerchenfelder!K41) -> 0 | L41: =SUM(Paniglgasse:Lerchenfelder!L41) -> 0 | ... BD41: =SUM(Paniglgasse:Lerchenfelder!BD41) -> 0 | BF41: =SUM(E41:H41) -> 0 | BG41: =SUM(I41:L41) -> 0 | BH41: =SUM(M41:Q41) -> 0 | BI41: =SUM(R41:U41) -> 0 | BJ41: =SUM(V41:Y41) -> 0 | BK41: =SUM(Z41:AD41) -> 0 | BL41: =SUM(AE41:AH41) -> 0 | BM41: =SUM(AI41:AL41) -> 0 | BN41: =SUM(AM41:AQ41) -> 0 | BO41: =SUM(AR41:AU41) -> 0 | BP41: =SUM(AV41:AY41) -> 0 | BQ41: =SUM(AZ41:BD41) -> 0 | BR41: =SUM(BF41:BQ41) -> 0 | BS41: =SUM(BF41:BH41) -> 0 | BT41: =SUM(BI41:BK41) -> 0 | BU41: =SUM(BL41:BN41) -> 0 | BV41: =SUM(BO41:BQ41) -> 0 | BW41: =SUM(BF41:BK41) -> 0 | BX41: =SUM(BL41:BQ41) -> 0 | BY41: =IF(Info!$O$3="Q1",$BS41,IF(Info!$O$3="Q2",$BS41+$BT41,IF(Info!$O$3="Q3",$BS41+$BT41+$BU41,$BR41))) -> 0 | BZ41: =IF(Info!$O$3="Q1",$BS41,IF(Info!$O$3="Q2",$BT41,IF(Info!$O$3="Q3",$BU41,$BV41))) -> 0
B42: Kgs put into the shop, Mix Summer | D42: =SUM(E42:BD42) -> 0 | E42: =SUM(Paniglgasse:Lerchenfelder!E42) -> 0 | F42: =SUM(Paniglgasse:Lerchenfelder!F42) -> 0 | G42: =SUM(Paniglgasse:Lerchenfelder!G42) -> 0 | H42: =SUM(Paniglgasse:Lerchenfelder!H42) -> 0 | I42: =SUM(Paniglgasse:Lerchenfelder!I42) -> 0 | J42: =SUM(Paniglgasse:Lerchenfelder!J42) -> 0 | K42: =SUM(Paniglgasse:Lerchenfelder!K42) -> 0 | L42: =SUM(Paniglgasse:Lerchenfelder!L42) -> 0 | ... BD42: =SUM(Paniglgasse:Lerchenfelder!BD42) -> 0 | BF42: =SUM(E42:H42) -> 0 | BG42: =SUM(I42:L42) -> 0 | BH42: =SUM(M42:Q42) -> 0 | BI42: =SUM(R42:U42) -> 0 | BJ42: =SUM(V42:Y42) -> 0 | BK42: =SUM(Z42:AD42) -> 0 | BL42: =SUM(AE42:AH42) -> 0 | BM42: =SUM(AI42:AL42) -> 0 | BN42: =SUM(AM42:AQ42) -> 0 | BO42: =SUM(AR42:AU42) -> 0 | BP42: =SUM(AV42:AY42) -> 0 | BQ42: =SUM(AZ42:BD42) -> 0 | BR42: =SUM(BF42:BQ42) -> 0 | BS42: =SUM(BF42:BH42) -> 0 | BT42: =SUM(BI42:BK42) -> 0 | BU42: =SUM(BL42:BN42) -> 0 | BV42: =SUM(BO42:BQ42) -> 0 | BW42: =SUM(BF42:BK42) -> 0 | BX42: =SUM(BL42:BQ42) -> 0 | BY42: =IF(Info!$O$3="Q1",$BS42,IF(Info!$O$3="Q2",$BS42+$BT42,IF(Info!$O$3="Q3",$BS42+$BT42+$BU42,$BR42))) -> 0 | BZ42: =IF(Info!$O$3="Q1",$BS42,IF(Info!$O$3="Q2",$BT42,IF(Info!$O$3="Q3",$BU42,$BV42))) -> 0
B43: Kgs put into the shop, Mix Winter | D43: =SUM(E43:BD43) -> 0 | E43: =SUM(Paniglgasse:Lerchenfelder!E43) -> 0 | F43: =SUM(Paniglgasse:Lerchenfelder!F43) -> 0 | G43: =SUM(Paniglgasse:Lerchenfelder!G43) -> 0 | H43: =SUM(Paniglgasse:Lerchenfelder!H43) -> 0 | I43: =SUM(Paniglgasse:Lerchenfelder!I43) -> 0 | J43: =SUM(Paniglgasse:Lerchenfelder!J43) -> 0 | K43: =SUM(Paniglgasse:Lerchenfelder!K43) -> 0 | L43: =SUM(Paniglgasse:Lerchenfelder!L43) -> 0 | ... BD43: =SUM(Paniglgasse:Lerchenfelder!BD43) -> 0 | BF43: =SUM(E43:H43) -> 0 | BG43: =SUM(I43:L43) -> 0 | BH43: =SUM(M43:Q43) -> 0 | BI43: =SUM(R43:U43) -> 0 | BJ43: =SUM(V43:Y43) -> 0 | BK43: =SUM(Z43:AD43) -> 0 | BL43: =SUM(AE43:AH43) -> 0 | BM43: =SUM(AI43:AL43) -> 0 | BN43: =SUM(AM43:AQ43) -> 0 | BO43: =SUM(AR43:AU43) -> 0 | BP43: =SUM(AV43:AY43) -> 0 | BQ43: =SUM(AZ43:BD43) -> 0 | BR43: =SUM(BF43:BQ43) -> 0 | BS43: =SUM(BF43:BH43) -> 0 | BT43: =SUM(BI43:BK43) -> 0 | BU43: =SUM(BL43:BN43) -> 0 | BV43: =SUM(BO43:BQ43) -> 0 | BW43: =SUM(BF43:BK43) -> 0 | BX43: =SUM(BL43:BQ43) -> 0 | BY43: =IF(Info!$O$3="Q1",$BS43,IF(Info!$O$3="Q2",$BS43+$BT43,IF(Info!$O$3="Q3",$BS43+$BT43+$BU43,$BR43))) -> 0 | BZ43: =IF(Info!$O$3="Q1",$BS43,IF(Info!$O$3="Q2",$BT43,IF(Info!$O$3="Q3",$BU43,$BV43))) -> 0
B44: Kgs put into the shop, Handbag A | D44: =SUM(E44:BD44) -> 873 | E44: =SUM(Paniglgasse:Lerchenfelder!E44) -> 0 | F44: =SUM(Paniglgasse:Lerchenfelder!F44) -> 0 | G44: =SUM(Paniglgasse:Lerchenfelder!G44) -> 0 | H44: =SUM(Paniglgasse:Lerchenfelder!H44) -> 77.08 | I44: =SUM(Paniglgasse:Lerchenfelder!I44) -> 0 | J44: =SUM(Paniglgasse:Lerchenfelder!J44) -> 28.21 | K44: =SUM(Paniglgasse:Lerchenfelder!K44) -> 0 | L44: =SUM(Paniglgasse:Lerchenfelder!L44) -> 0 | ... BD44: =SUM(Paniglgasse:Lerchenfelder!BD44) -> 0 | BF44: =SUM(E44:H44) -> 77.08 | BG44: =SUM(I44:L44) -> 28.21 | BH44: =SUM(M44:Q44) -> 106.29 | BI44: =SUM(R44:U44) -> 76.51 | BJ44: =SUM(V44:Y44) -> 128.62 | BK44: =SUM(Z44:AD44) -> 138.55 | BL44: =SUM(AE44:AH44) -> 133.53 | BM44: =SUM(AI44:AL44) -> 30 | BN44: =SUM(AM44:AQ44) -> 154.21 | BO44: =SUM(AR44:AU44) -> 0 | BP44: =SUM(AV44:AY44) -> 0 | BQ44: =SUM(AZ44:BD44) -> 0 | BR44: =SUM(BF44:BQ44) -> 873 | BS44: =SUM(BF44:BH44) -> 211.58 | BT44: =SUM(BI44:BK44) -> 343.68 | BU44: =SUM(BL44:BN44) -> 317.74 | BV44: =SUM(BO44:BQ44) -> 0 | BW44: =SUM(BF44:BK44) -> 555.26 | BX44: =SUM(BL44:BQ44) -> 317.74 | BY44: =IF(Info!$O$3="Q1",$BS44,IF(Info!$O$3="Q2",$BS44+$BT44,IF(Info!$O$3="Q3",$BS44+$BT44+$BU44,$BR44))) -> 211.58 | BZ44: =IF(Info!$O$3="Q1",$BS44,IF(Info!$O$3="Q2",$BT44,IF(Info!$O$3="Q3",$BU44,$BV44))) -> 211.58
B45: Kgs put into the shop, Handbag B | D45: =SUM(E45:BD45) -> 0 | E45: =SUM(Paniglgasse:Lerchenfelder!E45) -> 0 | F45: =SUM(Paniglgasse:Lerchenfelder!F45) -> 0 | G45: =SUM(Paniglgasse:Lerchenfelder!G45) -> 0 | H45: =SUM(Paniglgasse:Lerchenfelder!H45) -> 0 | I45: =SUM(Paniglgasse:Lerchenfelder!I45) -> 0 | J45: =SUM(Paniglgasse:Lerchenfelder!J45) -> 0 | K45: =SUM(Paniglgasse:Lerchenfelder!K45) -> 0 | L45: =SUM(Paniglgasse:Lerchenfelder!L45) -> 0 | ... BD45: =SUM(Paniglgasse:Lerchenfelder!BD45) -> 0 | BF45: =SUM(E45:H45) -> 0 | BG45: =SUM(I45:L45) -> 0 | BH45: =SUM(M45:Q45) -> 0 | BI45: =SUM(R45:U45) -> 0 | BJ45: =SUM(V45:Y45) -> 0 | BK45: =SUM(Z45:AD45) -> 0 | BL45: =SUM(AE45:AH45) -> 0 | BM45: =SUM(AI45:AL45) -> 0 | BN45: =SUM(AM45:AQ45) -> 0 | BO45: =SUM(AR45:AU45) -> 0 | BP45: =SUM(AV45:AY45) -> 0 | BQ45: =SUM(AZ45:BD45) -> 0 | BR45: =SUM(BF45:BQ45) -> 0 | BS45: =SUM(BF45:BH45) -> 0 | BT45: =SUM(BI45:BK45) -> 0 | BU45: =SUM(BL45:BN45) -> 0 | BV45: =SUM(BO45:BQ45) -> 0 | BW45: =SUM(BF45:BK45) -> 0 | BX45: =SUM(BL45:BQ45) -> 0 | BY45: =IF(Info!$O$3="Q1",$BS45,IF(Info!$O$3="Q2",$BS45+$BT45,IF(Info!$O$3="Q3",$BS45+$BT45+$BU45,$BR45))) -> 0 | BZ45: =IF(Info!$O$3="Q1",$BS45,IF(Info!$O$3="Q2",$BT45,IF(Info!$O$3="Q3",$BU45,$BV45))) -> 0
B46: Kgs put into the shop, things | D46: =SUM(E46:BD46) -> 54.09 | E46: =SUM(Paniglgasse:Lerchenfelder!E46) -> 0 | F46: =SUM(Paniglgasse:Lerchenfelder!F46) -> 0 | G46: =SUM(Paniglgasse:Lerchenfelder!G46) -> 0 | H46: =SUM(Paniglgasse:Lerchenfelder!H46) -> 9.44 | I46: =SUM(Paniglgasse:Lerchenfelder!I46) -> 0 | J46: =SUM(Paniglgasse:Lerchenfelder!J46) -> 0 | K46: =SUM(Paniglgasse:Lerchenfelder!K46) -> 3.53 | L46: =SUM(Paniglgasse:Lerchenfelder!L46) -> 0 | ... BD46: =SUM(Paniglgasse:Lerchenfelder!BD46) -> 0 | BF46: =SUM(E46:H46) -> 9.44 | BG46: =SUM(I46:L46) -> 3.53 | BH46: =SUM(M46:Q46) -> 14.6 | BI46: =SUM(R46:U46) -> 4.16 | BJ46: =SUM(V46:Y46) -> 3.8 | BK46: =SUM(Z46:AD46) -> 8.68 | BL46: =SUM(AE46:AH46) -> 6.21 | BM46: =SUM(AI46:AL46) -> 0 | BN46: =SUM(AM46:AQ46) -> 3.67 | BO46: =SUM(AR46:AU46) -> 0 | BP46: =SUM(AV46:AY46) -> 0 | BQ46: =SUM(AZ46:BD46) -> 0 | BR46: =SUM(BF46:BQ46) -> 54.09 | BS46: =SUM(BF46:BH46) -> 27.57 | BT46: =SUM(BI46:BK46) -> 16.64 | BU46: =SUM(BL46:BN46) -> 9.88 | BV46: =SUM(BO46:BQ46) -> 0 | BW46: =SUM(BF46:BK46) -> 44.21 | BX46: =SUM(BL46:BQ46) -> 9.88 | BY46: =IF(Info!$O$3="Q1",$BS46,IF(Info!$O$3="Q2",$BS46+$BT46,IF(Info!$O$3="Q3",$BS46+$BT46+$BU46,$BR46))) -> 27.57 | BZ46: =IF(Info!$O$3="Q1",$BS46,IF(Info!$O$3="Q2",$BT46,IF(Info!$O$3="Q3",$BU46,$BV46))) -> 27.57
B47: Kgs put into the shop, total | D47: =SUM(E47:BD47) -> 26375.69 | E47: =SUM(E37:E46) -> 585 | F47: =SUM(F37:F46) -> 584.3 | G47: =SUM(G37:G46) -> 990.32 | H47: =SUM(H37:H46) -> 1828.16 | I47: =SUM(I37:I46) -> 636.01 | J47: =SUM(J37:J46) -> 572.91 | K47: =SUM(K37:K46) -> 565.27 | L47: =SUM(L37:L46) -> 1001.54 | ... BD47: =SUM(BD37:BD46) -> 0 | BF47: =SUM(E47:H47) -> 3987.78 | BG47: =SUM(I47:L47) -> 2775.73 | BH47: =SUM(M47:Q47) -> 3885.65 | BI47: =SUM(R47:U47) -> 2459.35 | BJ47: =SUM(V47:Y47) -> 2896.66 | BK47: =SUM(Z47:AD47) -> 3340.1 | BL47: =SUM(AE47:AH47) -> 2597.15 | BM47: =SUM(AI47:AL47) -> 1612.76 | BN47: =SUM(AM47:AQ47) -> 2820.51 | BO47: =SUM(AR47:AU47) -> 0 | BP47: =SUM(AV47:AY47) -> 0 | BQ47: =SUM(AZ47:BD47) -> 0 | BR47: =SUM(BF47:BQ47) -> 26375.69 | BS47: =SUM(BF47:BH47) -> 10649.16 | BT47: =SUM(BI47:BK47) -> 8696.11 | BU47: =SUM(BL47:BN47) -> 7030.42 | BV47: =SUM(BO47:BQ47) -> 0 | BW47: =SUM(BF47:BK47) -> 19345.27 | BX47: =SUM(BL47:BQ47) -> 7030.42 | BY47: =IF(Info!$O$3="Q1",$BS47,IF(Info!$O$3="Q2",$BS47+$BT47,IF(Info!$O$3="Q3",$BS47+$BT47+$BU47,$BR47))) -> 10649.16 | BZ47: =IF(Info!$O$3="Q1",$BS47,IF(Info!$O$3="Q2",$BT47,IF(Info!$O$3="Q3",$BU47,$BV47))) -> 10649.16
B48: Kgs of clothes left | D48: =SUM(E48:BD48) -> 107474.03 | E48: =SUM(Paniglgasse:Lerchenfelder!E48) -> 2717.69 | F48: =SUM(Paniglgasse:Lerchenfelder!F48) -> 3645.22 | G48: =SUM(Paniglgasse:Lerchenfelder!G48) -> 3119.69 | H48: =SUM(Paniglgasse:Lerchenfelder!H48) -> 2314.51 | I48: =SUM(Paniglgasse:Lerchenfelder!I48) -> 2872.41 | J48: =SUM(Paniglgasse:Lerchenfelder!J48) -> 2782.97 | K48: =SUM(Paniglgasse:Lerchenfelder!K48) -> 3703.95 | L48: =SUM(Paniglgasse:Lerchenfelder!L48) -> 4174.82 | ... BD48: =SUM(Paniglgasse:Lerchenfelder!BD48) -> 0 | BF48: =SUM(E48:H48) -> 11797.11 | BG48: =SUM(I48:L48) -> 13534.15 | BH48: =SUM(M48:Q48) -> 16165.49 | BI48: =SUM(R48:U48) -> 8842.68 | BJ48: =SUM(V48:Y48) -> 9960 | BK48: =SUM(Z48:AD48) -> 12085.33 | BL48: =SUM(AE48:AH48) -> 13129.43 | BM48: =SUM(AI48:AL48) -> 11406.2 | BN48: =SUM(AM48:AQ48) -> 10553.64 | BO48: =SUM(AR48:AU48) -> 0 | BP48: =SUM(AV48:AY48) -> 0 | BQ48: =SUM(AZ48:BD48) -> 0 | BR48: =SUM(BF48:BQ48) -> 107474.03 | BS48: =SUM(BF48:BH48) -> 41496.75 | BT48: =SUM(BI48:BK48) -> 30888.01 | BU48: =SUM(BL48:BN48) -> 35089.27 | BV48: =SUM(BO48:BQ48) -> 0 | BW48: =SUM(BF48:BK48) -> 72384.76 | BX48: =SUM(BL48:BQ48) -> 35089.27 | BY48: =IF(Info!$O$3="Q1",$BS48,IF(Info!$O$3="Q2",$BS48+$BT48,IF(Info!$O$3="Q3",$BS48+$BT48+$BU48,$BR48))) -> 41496.75 | BZ48: =IF(Info!$O$3="Q1",$BS48,IF(Info!$O$3="Q2",$BT48,IF(Info!$O$3="Q3",$BU48,$BV48))) -> 41496.75
B49: Kgs of shoes left | D49: =SUM(E49:BD49) -> 2251.71 | E49: =SUM(Paniglgasse:Lerchenfelder!E49) -> 0 | F49: =SUM(Paniglgasse:Lerchenfelder!F49) -> 0 | G49: =SUM(Paniglgasse:Lerchenfelder!G49) -> 42.35 | H49: =SUM(Paniglgasse:Lerchenfelder!H49) -> 59.79 | I49: =SUM(Paniglgasse:Lerchenfelder!I49) -> 79.09 | J49: =SUM(Paniglgasse:Lerchenfelder!J49) -> 88.22 | K49: =SUM(Paniglgasse:Lerchenfelder!K49) -> 68.22 | L49: =SUM(Paniglgasse:Lerchenfelder!L49) -> 87.59 | ... BD49: =SUM(Paniglgasse:Lerchenfelder!BD49) -> 0 | BF49: =SUM(E49:H49) -> 102.14 | BG49: =SUM(I49:L49) -> 323.12 | BH49: =SUM(M49:Q49) -> 111.26 | BI49: =SUM(R49:U49) -> 56.93 | BJ49: =SUM(V49:Y49) -> 384.08 | BK49: =SUM(Z49:AD49) -> 231.99 | BL49: =SUM(AE49:AH49) -> 324.5 | BM49: =SUM(AI49:AL49) -> 455.49 | BN49: =SUM(AM49:AQ49) -> 262.2 | BO49: =SUM(AR49:AU49) -> 0 | BP49: =SUM(AV49:AY49) -> 0 | BQ49: =SUM(AZ49:BD49) -> 0 | BR49: =SUM(BF49:BQ49) -> 2251.71 | BS49: =SUM(BF49:BH49) -> 536.52 | BT49: =SUM(BI49:BK49) -> 673 | BU49: =SUM(BL49:BN49) -> 1042.19 | BV49: =SUM(BO49:BQ49) -> 0 | BW49: =SUM(BF49:BK49) -> 1209.52 | BX49: =SUM(BL49:BQ49) -> 1042.19 | BY49: =IF(Info!$O$3="Q1",$BS49,IF(Info!$O$3="Q2",$BS49+$BT49,IF(Info!$O$3="Q3",$BS49+$BT49+$BU49,$BR49))) -> 536.52 | BZ49: =IF(Info!$O$3="Q1",$BS49,IF(Info!$O$3="Q2",$BT49,IF(Info!$O$3="Q3",$BU49,$BV49))) -> 536.52
B50: Kgs of HHR left | D50: =SUM(E50:BD50) -> 0 | E50: =SUM(Paniglgasse:Lerchenfelder!E50) -> 0 | F50: =SUM(Paniglgasse:Lerchenfelder!F50) -> 0 | G50: =SUM(Paniglgasse:Lerchenfelder!G50) -> 0 | H50: =SUM(Paniglgasse:Lerchenfelder!H50) -> 0 | I50: =SUM(Paniglgasse:Lerchenfelder!I50) -> 0 | J50: =SUM(Paniglgasse:Lerchenfelder!J50) -> 0 | K50: =SUM(Paniglgasse:Lerchenfelder!K50) -> 0 | L50: =SUM(Paniglgasse:Lerchenfelder!L50) -> 0 | ... BD50: =SUM(Paniglgasse:Lerchenfelder!BD50) -> 0 | BF50: =SUM(E50:H50) -> 0 | BG50: =SUM(I50:L50) -> 0 | BH50: =SUM(M50:Q50) -> 0 | BI50: =SUM(R50:U50) -> 0 | BJ50: =SUM(V50:Y50) -> 0 | BK50: =SUM(Z50:AD50) -> 0 | BL50: =SUM(AE50:AH50) -> 0 | BM50: =SUM(AI50:AL50) -> 0 | BN50: =SUM(AM50:AQ50) -> 0 | BO50: =SUM(AR50:AU50) -> 0 | BP50: =SUM(AV50:AY50) -> 0 | BQ50: =SUM(AZ50:BD50) -> 0 | BR50: =SUM(BF50:BQ50) -> 0 | BS50: =SUM(BF50:BH50) -> 0 | BT50: =SUM(BI50:BK50) -> 0 | BU50: =SUM(BL50:BN50) -> 0 | BV50: =SUM(BO50:BQ50) -> 0 | BW50: =SUM(BF50:BK50) -> 0 | BX50: =SUM(BL50:BQ50) -> 0 | BY50: =IF(Info!$O$3="Q1",$BS50,IF(Info!$O$3="Q2",$BS50+$BT50,IF(Info!$O$3="Q3",$BS50+$BT50+$BU50,$BR50))) -> 0 | BZ50: =IF(Info!$O$3="Q1",$BS50,IF(Info!$O$3="Q2",$BT50,IF(Info!$O$3="Q3",$BU50,$BV50))) -> 0
B51: Kgs of things left | D51: =SUM(E51:BD51) -> 844.9 | E51: =SUM(Paniglgasse:Lerchenfelder!E51) -> 0 | F51: =SUM(Paniglgasse:Lerchenfelder!F51) -> 0 | G51: =SUM(Paniglgasse:Lerchenfelder!G51) -> 37.1 | H51: =SUM(Paniglgasse:Lerchenfelder!H51) -> 0 | I51: =SUM(Paniglgasse:Lerchenfelder!I51) -> 15 | J51: =SUM(Paniglgasse:Lerchenfelder!J51) -> 0 | K51: =SUM(Paniglgasse:Lerchenfelder!K51) -> 15 | L51: =SUM(Paniglgasse:Lerchenfelder!L51) -> 62 | ... BD51: =SUM(Paniglgasse:Lerchenfelder!BD51) -> 0 | BF51: =SUM(E51:H51) -> 37.1 | BG51: =SUM(I51:L51) -> 92 | BH51: =SUM(M51:Q51) -> 113.63 | BI51: =SUM(R51:U51) -> 11.41 | BJ51: =SUM(V51:Y51) -> 11.82 | BK51: =SUM(Z51:AD51) -> 95.91 | BL51: =SUM(AE51:AH51) -> 202.87 | BM51: =SUM(AI51:AL51) -> 255.19 | BN51: =SUM(AM51:AQ51) -> 24.97 | BO51: =SUM(AR51:AU51) -> 0 | BP51: =SUM(AV51:AY51) -> 0 | BQ51: =SUM(AZ51:BD51) -> 0 | BR51: =SUM(BF51:BQ51) -> 844.9 | BS51: =SUM(BF51:BH51) -> 242.73 | BT51: =SUM(BI51:BK51) -> 119.14 | BU51: =SUM(BL51:BN51) -> 483.03 | BV51: =SUM(BO51:BQ51) -> 0 | BW51: =SUM(BF51:BK51) -> 361.87 | BX51: =SUM(BL51:BQ51) -> 483.03 | BY51: =IF(Info!$O$3="Q1",$BS51,IF(Info!$O$3="Q2",$BS51+$BT51,IF(Info!$O$3="Q3",$BS51+$BT51+$BU51,$BR51))) -> 242.73 | BZ51: =IF(Info!$O$3="Q1",$BS51,IF(Info!$O$3="Q2",$BT51,IF(Info!$O$3="Q3",$BU51,$BV51))) -> 242.73
B52: Kgs in the shop, end of the week | D52: =SUM(E52:BD52) -> 110570.64 | E52: =SUM(E48:E51) -> 2717.69 | F52: =SUM(F48:F51) -> 3645.22 | G52: =SUM(G48:G51) -> 3199.14 | H52: =SUM(H48:H51) -> 2374.3 | I52: =SUM(I48:I51) -> 2966.5 | J52: =SUM(J48:J51) -> 2871.19 | K52: =SUM(K48:K51) -> 3787.17 | L52: =SUM(L48:L51) -> 4324.41 | ... BD52: =SUM(BD48:BD51) -> 0
B53: No. of pieces / Kg | D53: =IF(D73=0,0,(D27-D26)/D47) -> 3.0150131 | E53: =IF(E73=0,0,(E27-E26)/E47) -> 2.2076581 | F53: =IF(F73=0,0,(F27-F26)/F47) -> 1.9873524 | G53: =IF(G73=0,0,(G27-G26)/G47) -> 2.2561697 | H53: =IF(H73=0,0,(H27-H26)/H47) -> 2.3537984 | I53: =IF(I73=0,0,(I27-I26)/I47) -> 1.8504112 | J53: =IF(J73=0,0,(J27-J26)/J47) -> 2.5572428 | K53: =IF(K73=0,0,(K27-K26)/K47) -> 2.1704672 | ... BD53: =IF(BD73=0,0,(BD27-BD26)/BD47) -> 0 | BF53: =IF(BF73=0,0,(BF27-BF26)/BF47) -> 2.2544223 | BG53: =IF(BG73=0,0,(BG27-BG26)/BG47) -> 2.1952567 | BH53: =IF(BH73=0,0,(BH27-BH26)/BH47) -> 2.8515178 | BI53: =IF(BI73=0,0,(BI27-BI26)/BI47) -> 3.5002216 | BJ53: =IF(BJ73=0,0,(BJ27-BJ26)/BJ47) -> 3.3685037 | BK53: =IF(BK73=0,0,(BK27-BK26)/BK47) -> 3.5505015 | BL53: =IF(BL73=0,0,(BL27-BL26)/BL47) -> 3.696321 | BM53: =IF(BM73=0,0,(BM27-BM26)/BM47) -> 3.536422 | ... BZ53: =IF(BZ73=0,0,(BZ27-BZ26)/BZ47) -> 2.456868
B54: No of sales (customers) | D54: =SUM(E54:BD54) -> 30525 | E54: =SUM(Paniglgasse:Lerchenfelder!E54) -> 784 | F54: =SUM(Paniglgasse:Lerchenfelder!F54) -> 613.2 | G54: =SUM(Paniglgasse:Lerchenfelder!G54) -> 1113.06 | H54: =SUM(Paniglgasse:Lerchenfelder!H54) -> 759.18 | I54: =SUM(Paniglgasse:Lerchenfelder!I54) -> 605.55 | J54: =SUM(Paniglgasse:Lerchenfelder!J54) -> 757.77 | K54: =SUM(Paniglgasse:Lerchenfelder!K54) -> 714.67 | L54: =SUM(Paniglgasse:Lerchenfelder!L54) -> 1049.29 | ... BD54: =SUM(Paniglgasse:Lerchenfelder!BD54) -> 0 | BF54: =SUM(E54:H54) -> 3269.44 | BG54: =SUM(I54:L54) -> 3127.28 | BH54: =SUM(M54:Q54) -> 4185.67 | BI54: =SUM(R54:U54) -> 3019.88 | BJ54: =SUM(V54:Y54) -> 3298.55 | BK54: =SUM(Z54:AD54) -> 4413.86 | BL54: =SUM(AE54:AH54) -> 3180.93 | BM54: =SUM(AI54:AL54) -> 3168.71 | BN54: =SUM(AM54:AQ54) -> 2860.68 | BO54: =SUM(AR54:AU54) -> 0 | BP54: =SUM(AV54:AY54) -> 0 | BQ54: =SUM(AZ54:BD54) -> 0 | BR54: =SUM(BF54:BQ54) -> 30525 | BS54: =SUM(BF54:BH54) -> 10582.39 | BT54: =SUM(BI54:BK54) -> 10732.29 | BU54: =SUM(BL54:BN54) -> 9210.32 | BV54: =SUM(BO54:BQ54) -> 0 | BW54: =SUM(BF54:BK54) -> 21314.68 | BX54: =SUM(BL54:BQ54) -> 9210.32 | BY54: =IF(Info!$O$3="Q1",$BS54,IF(Info!$O$3="Q2",$BS54+$BT54,IF(Info!$O$3="Q3",$BS54+$BT54+$BU54,$BR54))) -> 10582.39 | BZ54: =IF(Info!$O$3="Q1",$BS54,IF(Info!$O$3="Q2",$BT54,IF(Info!$O$3="Q3",$BU54,$BV54))) -> 10582.39
B55: Workhours normal time | D55: =SUM(E55:BD55) -> 7288.07 | E55: =SUM(Paniglgasse:Lerchenfelder!E55) -> 123.37 | F55: =SUM(Paniglgasse:Lerchenfelder!F55) -> 168.19 | G55: =SUM(Paniglgasse:Lerchenfelder!G55) -> 190.18 | H55: =SUM(Paniglgasse:Lerchenfelder!H55) -> 263.13 | I55: =SUM(Paniglgasse:Lerchenfelder!I55) -> 204.86 | J55: =SUM(Paniglgasse:Lerchenfelder!J55) -> 188.59 | K55: =SUM(Paniglgasse:Lerchenfelder!K55) -> 221.09 | L55: =SUM(Paniglgasse:Lerchenfelder!L55) -> 225.77 | ... BD55: =SUM(Paniglgasse:Lerchenfelder!BD55) -> 0 | BF55: =SUM(E55:H55) -> 744.87 | BG55: =SUM(I55:L55) -> 840.31 | BH55: =SUM(M55:Q55) -> 1028.5 | BI55: =SUM(R55:U55) -> 679.03 | BJ55: =SUM(V55:Y55) -> 818.8 | BK55: =SUM(Z55:AD55) -> 896.2 | BL55: =SUM(AE55:AH55) -> 758.91 | BM55: =SUM(AI55:AL55) -> 702.8 | BN55: =SUM(AM55:AQ55) -> 818.65 | BO55: =SUM(AR55:AU55) -> 0 | BP55: =SUM(AV55:AY55) -> 0 | BQ55: =SUM(AZ55:BD55) -> 0 | BR55: =SUM(BF55:BQ55) -> 7288.07 | BS55: =SUM(BF55:BH55) -> 2613.68 | BT55: =SUM(BI55:BK55) -> 2394.03 | BU55: =SUM(BL55:BN55) -> 2280.36 | BV55: =SUM(BO55:BQ55) -> 0 | BW55: =SUM(BF55:BK55) -> 5007.71 | BX55: =SUM(BL55:BQ55) -> 2280.36 | BY55: =IF(Info!$O$3="Q1",$BS55,IF(Info!$O$3="Q2",$BS55+$BT55,IF(Info!$O$3="Q3",$BS55+$BT55+$BU55,$BR55))) -> 2613.68 | BZ55: =IF(Info!$O$3="Q1",$BS55,IF(Info!$O$3="Q2",$BT55,IF(Info!$O$3="Q3",$BU55,$BV55))) -> 2613.68
B56: Workhours overtime | D56: =SUM(E56:BD56) -> 0 | E56: =SUM(Paniglgasse:Lerchenfelder!E56) -> 0 | F56: =SUM(Paniglgasse:Lerchenfelder!F56) -> 0 | G56: =SUM(Paniglgasse:Lerchenfelder!G56) -> 0 | H56: =SUM(Paniglgasse:Lerchenfelder!H56) -> 0 | I56: =SUM(Paniglgasse:Lerchenfelder!I56) -> 0 | J56: =SUM(Paniglgasse:Lerchenfelder!J56) -> 0 | K56: =SUM(Paniglgasse:Lerchenfelder!K56) -> 0 | L56: =SUM(Paniglgasse:Lerchenfelder!L56) -> 0 | ... BD56: =SUM(Paniglgasse:Lerchenfelder!BD56) -> 0 | BF56: =SUM(E56:H56) -> 0 | BG56: =SUM(I56:L56) -> 0 | BH56: =SUM(M56:Q56) -> 0 | BI56: =SUM(R56:U56) -> 0 | BJ56: =SUM(V56:Y56) -> 0 | BK56: =SUM(Z56:AD56) -> 0 | BL56: =SUM(AE56:AH56) -> 0 | BM56: =SUM(AI56:AL56) -> 0 | BN56: =SUM(AM56:AQ56) -> 0 | BO56: =SUM(AR56:AU56) -> 0 | BP56: =SUM(AV56:AY56) -> 0 | BQ56: =SUM(AZ56:BD56) -> 0 | BR56: =SUM(BF56:BQ56) -> 0 | BS56: =SUM(BF56:BH56) -> 0 | BT56: =SUM(BI56:BK56) -> 0 | BU56: =SUM(BL56:BN56) -> 0 | BV56: =SUM(BO56:BQ56) -> 0 | BW56: =SUM(BF56:BK56) -> 0 | BX56: =SUM(BL56:BQ56) -> 0 | BY56: =IF(Info!$O$3="Q1",$BS56,IF(Info!$O$3="Q2",$BS56+$BT56,IF(Info!$O$3="Q3",$BS56+$BT56+$BU56,$BR56))) -> 0 | BZ56: =IF(Info!$O$3="Q1",$BS56,IF(Info!$O$3="Q2",$BT56,IF(Info!$O$3="Q3",$BU56,$BV56))) -> 0
B58: Income (excl.VAT)
B59: Income / Pcs put in | D59: =IF(D$73=0,0,D74/D27) -> 5.8617843 | E59: =IF(E$73=0,0,E74/E27) -> 9.9397913 | F59: =IF(F$73=0,0,F74/F27) -> 6.2165758 | G59: =IF(G$73=0,0,G74/G27) -> 4.9294382 | H59: =IF(H$73=0,0,H74/H27) -> 3.5539252 | I59: =IF(I$73=0,0,I74/I27) -> 14.619177 | J59: =IF(J$73=0,0,J74/J27) -> 10.134294 | K59: =IF(K$73=0,0,K74/K27) -> 7.7007566 | ... BD59: =IF(BD$73=0,0,BD74/BD27) -> 0 | BF59: =IF(BF$73=0,0,BF74/BF27) -> 5.1570665 | BG59: =IF(BG$73=0,0,BG74/BG27) -> 8.5849947 | BH59: =IF(BH$73=0,0,BH74/BH27) -> 6.3100782 | BI59: =IF(BI$73=0,0,BI74/BI27) -> 6.1498991 | BJ59: =IF(BJ$73=0,0,BJ74/BJ27) -> 5.3820157 | BK59: =IF(BK$73=0,0,BK74/BK27) -> 5.0350795 | BL59: =IF(BL$73=0,0,BL74/BL27) -> 4.5967562 | BM59: =IF(BM$73=0,0,BM74/BM27) -> 6.9550444 | ... BZ59: =IF(BZ$73=0,0,BZ74/BZ27) -> 6.4437117
B60: Income / Customer | D60: =IF(D$73=0,0,D74/D54) -> 15.27099 | E60: =IF(E$73=0,0,E74/E54) -> 16.373778 | F60: =IF(F$73=0,0,F74/F54) -> 11.77226 | G60: =IF(G$73=0,0,G74/G54) -> 9.8952363 | H60: =IF(H$73=0,0,H74/H54) -> 20.144059 | I60: =IF(I$73=0,0,I74/I54) -> 28.412215 | J60: =IF(J$73=0,0,J74/J54) -> 19.59361 | K60: =IF(K$73=0,0,K74/K54) -> 13.220169 | ... BD60: =IF(BD$73=0,0,BD74/BD54) -> 0 | BF60: =IF(BF$73=0,0,BF74/BF54) -> 14.180639 | BG60: =IF(BG$73=0,0,BG74/BG54) -> 16.727683 | BH60: =IF(BH$73=0,0,BH74/BH54) -> 16.703578 | BI60: =IF(BI$73=0,0,BI74/BI54) -> 17.530495 | BJ60: =IF(BJ$73=0,0,BJ74/BJ54) -> 15.92049 | BK60: =IF(BK$73=0,0,BK74/BK54) -> 13.528104 | BL60: =IF(BL$73=0,0,BL74/BL54) -> 13.872798 | BM60: =IF(BM$73=0,0,BM74/BM54) -> 12.51847 | ... BZ60: =IF(BZ$73=0,0,BZ74/BZ54) -> 15.931237
B61: Income / 40 hour week | D61: =IF(D$73=0,0,D74/(D55+D56)*40) -> 2558.411 | E61: =IF(E$73=0,0,E74/(E55+E56)*40) -> 4162.1275 | F61: =IF(F$73=0,0,F74/(F55+F56)*40) -> 1716.8084 | G61: =IF(G$73=0,0,G74/(G55+G56)*40) -> 2316.5405 | H61: =IF(H$73=0,0,H74/(H55+H56)*40) -> 2324.7774 | I61: =IF(I$73=0,0,I74/(I55+I56)*40) -> 3359.3706 | J61: =IF(J$73=0,0,J74/(J55+J56)*40) -> 3149.1489 | K61: =IF(K$73=0,0,K74/(K55+K56)*40) -> 1709.3597 | ... BD61: =IF(BD$73=0,0,BD74/(BD55+BD56)*40) -> 0 | BF61: =IF(BF$73=0,0,BF74/(BF55+BF56)*40) -> 2489.7096 | BG61: =IF(BG$73=0,0,BG74/(BG55+BG56)*40) -> 2490.1358 | BH61: =IF(BH$73=0,0,BH74/(BH55+BH56)*40) -> 2719.1314 | BI61: =IF(BI$73=0,0,BI74/(BI55+BI56)*40) -> 3118.5657 | BJ61: =IF(BJ$73=0,0,BJ74/(BJ55+BJ56)*40) -> 2565.4389 | BK61: =IF(BK$73=0,0,BK74/(BK55+BK56)*40) -> 2665.0818 | BL61: =IF(BL$73=0,0,BL74/(BL55+BL56)*40) -> 2325.8832 | BM61: =IF(BM$73=0,0,BM74/(BM55+BM56)*40) -> 2257.6779 | ... BZ61: =IF(BZ$73=0,0,BZ74/(BZ55+BZ56)*40) -> 2580.1256
B62: Income / work-hour | D62: =IF(D$73=0,0,D74/(D55+D56)) -> 63.960276 | E62: =IF(E$73=0,0,E74/(E55+E56)) -> 104.05319 | F62: =IF(F$73=0,0,F74/(F55+F56)) -> 42.920209 | G62: =IF(G$73=0,0,G74/(G55+G56)) -> 57.913512 | H62: =IF(H$73=0,0,H74/(H55+H56)) -> 58.119434 | I62: =IF(I$73=0,0,I74/(I55+I56)) -> 83.984266 | J62: =IF(J$73=0,0,J74/(J55+J56)) -> 78.728724 | K62: =IF(K$73=0,0,K74/(K55+K56)) -> 42.733992 | ... BD62: =IF(BD$73=0,0,BD74/(BD55+BD56)) -> 0 | BF62: =IF(BF$73=0,0,BF74/(BF55+BF56)) -> 62.24274 | BG62: =IF(BG$73=0,0,BG74/(BG55+BG56)) -> 62.253395 | BH62: =IF(BH$73=0,0,BH74/(BH55+BH56)) -> 67.978286 | BI62: =IF(BI$73=0,0,BI74/(BI55+BI56)) -> 77.964142 | BJ62: =IF(BJ$73=0,0,BJ74/(BJ55+BJ56)) -> 64.135971 | BK62: =IF(BK$73=0,0,BK74/(BK55+BK56)) -> 66.627046 | BL62: =IF(BL$73=0,0,BL74/(BL55+BL56)) -> 58.147079 | BM62: =IF(BM$73=0,0,BM74/(BM55+BM56)) -> 56.441946 | ... BZ62: =IF(BZ$73=0,0,BZ74/(BZ55+BZ56)) -> 64.50314
B63: Result / work-hour | D63: =IF(D$73=0,0,D136/(D55+D56)) -> 1.4445481 | E63: =IF(E$73=0,0,E136/(E55+E56)) -> 10.061291 | F63: =IF(F$73=0,0,F136/(F55+F56)) -> -28.600592 | G63: =IF(G$73=0,0,G136/(G55+G56)) -> -7.7522448 | H63: =IF(H$73=0,0,H136/(H55+H56)) -> -20.07725 | I63: =IF(I$73=0,0,I136/(I55+I56)) -> 18.371496 | J63: =IF(J$73=0,0,J136/(J55+J56)) -> 12.795233 | K63: =IF(K$73=0,0,K136/(K55+K56)) -> -12.632315 | ... BD63: =IF(BD$73=0,0,BD136/(BD55+BD56)) -> 0 | BF63: =IF(BF$73=0,0,BF136/(BF55+BF56)) -> -13.863253 | BG63: =IF(BG$73=0,0,BG136/(BG55+BG56)) -> 1.3030921 | BH63: =IF(BH$73=0,0,BH136/(BH55+BH56)) -> 13.90571 | BI63: =IF(BI$73=0,0,BI136/(BI55+BI56)) -> 6.7720521 | BJ63: =IF(BJ$73=0,0,BJ136/(BJ55+BJ56)) -> 12.761067 | BK63: =IF(BK$73=0,0,BK136/(BK55+BK56)) -> -12.313262 | BL63: =IF(BL$73=0,0,BL136/(BL55+BL56)) -> -0.47104366 | BM63: =IF(BM$73=0,0,BM136/(BM55+BM56)) -> -5.4115452 | ... BZ63: =IF(BZ$73=0,0,BZ136/(BZ55+BZ56)) -> 1.9400627
B64: Per piece sold
B65: Income / Pcs sold | D65: =IF(D$74=0,0,D74/D29) -> 6.9484788 | E65: =IF(E$73=0,0,E74/E29) -> 8.0391792 | F65: =IF(F$73=0,0,F74/F29) -> 5.5378897 | G65: =IF(G$73=0,0,G74/G29) -> 4.5299529 | H65: =IF(H$73=0,0,H74/H29) -> 7.1025686 | I65: =IF(I$73=0,0,I74/I29) -> 14.075245 | J65: =IF(J$73=0,0,J74/J29) -> 10.951466 | K65: =IF(K$73=0,0,K74/K29) -> 6.5630658 | L65: =IF(L$73=0,0,L74/L29) -> 3.5520973 | ... BD65: =IF(BD$73=0,0,BD74/BD29) -> 0 | BF65: =IF(BF$73=0,0,BF74/BF29) -> 6.194204 | BG65: =IF(BG$73=0,0,BG74/BG29) -> 7.4081629 | BH65: =IF(BH$73=0,0,BH74/BH29) -> 8.2271051 | BI65: =IF(BI$73=0,0,BI74/BI29) -> 8.2567406 | BJ65: =IF(BJ$73=0,0,BJ74/BJ29) -> 6.7280953 | BK65: =IF(BK$73=0,0,BK74/BK29) -> 5.9873715 | BL65: =IF(BL$73=0,0,BL74/BL29) -> 5.6212804 | BM65: =IF(BM$73=0,0,BM74/BM29) -> 6.2401719 | ... BZ65: =IF(BZ$73=0,0,BZ74/BZ29) -> 7.3158732
B66: Result / Pcs sold | D66: =IF(D$73=0,0,D136/D29) -> 0.15693197 | E66: =IF(E$73=0,0,E136/E29) -> 0.7773382 | F66: =IF(F$73=0,0,F136/F29) -> -3.6902645 | G66: =IF(G$73=0,0,G136/G29) -> -0.60637498 | H66: =IF(H$73=0,0,H136/H29) -> -2.4535691 | I66: =IF(I$73=0,0,I136/I29) -> 3.0789495 | J66: =IF(J$73=0,0,J136/J29) -> 1.7798658 | K66: =IF(K$73=0,0,K136/K29) -> -1.9400649 | ... BD66: =IF(BD$73=0,0,BD136/BD29) -> 0 | BF66: =IF(BF$73=0,0,BF136/BF29) -> -1.3796278 | BG66: =IF(BG$73=0,0,BG136/BG29) -> 0.15506815 | BH66: =IF(BH$73=0,0,BH136/BH29) -> 1.6829453 | BI66: =IF(BI$73=0,0,BI136/BI29) -> 0.71718967 | BJ66: =IF(BJ$73=0,0,BJ136/BJ29) -> 1.3386821 | BK66: =IF(BK$73=0,0,BK136/BK29) -> -1.1065187 | BL66: =IF(BL$73=0,0,BL136/BL29) -> -0.045537429 | BM66: =IF(BM$73=0,0,BM136/BM29) -> -0.59829567 | ... BZ66: =IF(BZ$73=0,0,BZ136/BZ29) -> 0.22003971
B67: Per customer
B68: Income / Customer | D68: =IF(D$73=0,0,D74/D54) -> 15.27099 | E68: =IF(E$73=0,0,E74/E54) -> 16.373778 | F68: =IF(F$73=0,0,F74/F54) -> 11.77226 | G68: =IF(G$73=0,0,G74/G54) -> 9.8952363 | H68: =IF(H$73=0,0,H74/H54) -> 20.144059 | I68: =IF(I$73=0,0,I74/I54) -> 28.412215 | J68: =IF(J$73=0,0,J74/J54) -> 19.59361 | K68: =IF(K$73=0,0,K74/K54) -> 13.220169 | ... BD68: =IF(BD$73=0,0,BD74/BD54) -> 0 | BF68: =IF(BF$73=0,0,BF74/BF54) -> 14.180639 | BG68: =IF(BG$73=0,0,BG74/BG54) -> 16.727683 | BH68: =IF(BH$73=0,0,BH74/BH54) -> 16.703578 | BI68: =IF(BI$73=0,0,BI74/BI54) -> 17.530495 | BJ68: =IF(BJ$73=0,0,BJ74/BJ54) -> 15.92049 | BK68: =IF(BK$73=0,0,BK74/BK54) -> 13.528104 | BL68: =IF(BL$73=0,0,BL74/BL54) -> 13.872798 | BM68: =IF(BM$73=0,0,BM74/BM54) -> 12.51847 | ... BZ68: =IF(BZ$73=0,0,BZ74/BZ54) -> 15.931237
B69: Result / Customer | D69: =IF(D$73=0,0,D136/D54) -> 0.34489658 | E69: =IF(E$73=0,0,E136/E54) -> 1.5832416 | F69: =IF(F$73=0,0,F136/F54) -> -7.8446406 | G69: =IF(G$73=0,0,G136/G54) -> -1.3245664 | H69: =IF(H$73=0,0,H136/H54) -> -6.9587277 | I69: =IF(I$73=0,0,I136/I54) -> 6.2151511 | J69: =IF(J$73=0,0,J136/J54) -> 3.1844136 | K69: =IF(K$73=0,0,K136/K54) -> -3.9079276 | ... BD69: =IF(BD$73=0,0,BD136/BD54) -> 0 | BF69: =IF(BF$73=0,0,BF136/BF54) -> -3.1584372 | BG69: =IF(BG$73=0,0,BG136/BG54) -> 0.35014495 | BH69: =IF(BH$73=0,0,BH136/BH54) -> 3.4169016 | BI69: =IF(BI$73=0,0,BI136/BI54) -> 1.5227183 | BJ69: =IF(BJ$73=0,0,BJ136/BJ54) -> 3.1676832 | BK69: =IF(BK$73=0,0,BK136/BK54) -> -2.5001122 | BL69: =IF(BL$73=0,0,BL136/BL54) -> -0.11238215 | BM69: =IF(BM$73=0,0,BM136/BM54) -> -1.2002468 | ... BZ69: =IF(BZ$73=0,0,BZ136/BZ54) -> 0.47916425
B70: Income per kg | D70: =IFERROR(D74/D47,0) -> 17.673356 | E70: =IFERROR(E74/E47,0) -> 21.943661 | F70: =IFERROR(F74/F47,0) -> 12.354527 | G70: =IFERROR(G74/G47,0) -> 11.121649 | H70: =IFERROR(H74/H47,0) -> 8.3652233 | I70: =IFERROR(I74/I47,0) -> 27.051488 | J70: =IFERROR(J74/J47,0) -> 25.915851 | K70: =IFERROR(K74/K47,0) -> 16.71424 | ... BD70: =IFERROR(BD74/BD47,0) -> 0 | BF70: =IFERROR(BF74/BF47,0) -> 11.626206 | BG70: =IFERROR(BG74/BG47,0) -> 18.846267 | BH70: =IFERROR(BH74/BH47,0) -> 17.9933 | BI70: =IFERROR(BI74/BI47,0) -> 21.52601 | BJ70: =IFERROR(BJ74/BJ47,0) -> 18.12934 | BK70: =IFERROR(BK74/BK47,0) -> 17.877057 | BL70: =IFERROR(BL74/BL47,0) -> 16.991086 | BM70: =IFERROR(BM74/BM47,0) -> 24.595972 | ... BZ70: =IFERROR(BZ74/BZ47,0) -> 15.831349
B72: Economy
B73: Sales turnover (incl. VAT) | D73: =SUM(E73:BD73) -> 559376.36 | E73: =SUM(Paniglgasse:Lerchenfelder!E73) -> 15404.45 | F73: =SUM(Paniglgasse:Lerchenfelder!F73) -> 8662.5 | G73: =SUM(Paniglgasse:Lerchenfelder!G73) -> 13216.79 | H73: =SUM(Paniglgasse:Lerchenfelder!H73) -> 18351.56 | I73: =SUM(Paniglgasse:Lerchenfelder!I73) -> 20646.02 | J73: =SUM(Paniglgasse:Lerchenfelder!J73) -> 17816.94 | K73: =SUM(Paniglgasse:Lerchenfelder!K73) -> 11337.67 | L73: =SUM(Paniglgasse:Lerchenfelder!L73) -> 12973.95 | ... BD73: =SUM(Paniglgasse:Lerchenfelder!BD73) -> 0 | BF73: =SUM(E73:H73) -> 55635.3 | BG73: =SUM(I73:L73) -> 62774.58 | BH73: =SUM(M73:Q73) -> 83898.8 | BI73: =SUM(R73:U73) -> 63527.99 | BJ73: =SUM(V73:Y73) -> 63017.44 | BK73: =SUM(Z73:AD73) -> 71653.39 | BL73: =SUM(AE73:AH73) -> 52954.08 | BM73: =SUM(AI73:AL73) -> 47600.88 | BN73: =SUM(AM73:AQ73) -> 58313.9 | BO73: =SUM(AR73:AU73) -> 0 | BP73: =SUM(AV73:AY73) -> 0 | BQ73: =SUM(AZ73:BD73) -> 0 | BR73: =SUM(BF73:BQ73) -> 559376.36 | BS73: =SUM(BF73:BH73) -> 202308.68 | BT73: =SUM(BI73:BK73) -> 198198.82 | BU73: =SUM(BL73:BN73) -> 158868.86 | BV73: =SUM(BO73:BQ73) -> 0 | BW73: =SUM(BF73:BK73) -> 400507.5 | BX73: =SUM(BL73:BQ73) -> 158868.86 | BY73: =IF(Info!$O$3="Q1",$BS73,IF(Info!$O$3="Q2",$BS73+$BT73,IF(Info!$O$3="Q3",$BS73+$BT73+$BU73,$BR73))) -> 202308.68 | BZ73: =IF(Info!$O$3="Q1",$BS73,IF(Info!$O$3="Q2",$BT73,IF(Info!$O$3="Q3",$BU73,$BV73))) -> 202308.68
B74: Sales income (excl. VAT) | D74: =SUM(E74:BD74) -> 466146.97 | E74: =E73/(1+$C$77) -> 12837.042 | F74: =F73/(1+$C$77) -> 7218.75 | G74: =G73/(1+$C$77) -> 11013.992 | H74: =H73/(1+$C$77) -> 15292.967 | I74: =I73/(1+$C$77) -> 17205.017 | J74: =J73/(1+$C$77) -> 14847.45 | K74: =K73/(1+$C$77) -> 9448.0583 | L74: =L73/(1+$C$77) -> 10811.625 | ... BD74: =BD73/(1+$C$77) -> 0 | BF74: =SUM(E74:H74) -> 46362.75 | BG74: =SUM(I74:L74) -> 52312.15 | BH74: =SUM(M74:Q74) -> 69915.667 | BI74: =SUM(R74:U74) -> 52939.992 | BJ74: =SUM(V74:Y74) -> 52514.533 | BK74: =SUM(Z74:AD74) -> 59711.158 | BL74: =SUM(AE74:AH74) -> 44128.4 | BM74: =SUM(AI74:AL74) -> 39667.4 | BN74: =SUM(AM74:AQ74) -> 48594.917 | BO74: =SUM(AR74:AU74) -> 0 | BP74: =SUM(AV74:AY74) -> 0 | BQ74: =SUM(AZ74:BD74) -> 0 | BR74: =SUM(BF74:BQ74) -> 466146.97 | BS74: =SUM(BF74:BH74) -> 168590.57 | BT74: =SUM(BI74:BK74) -> 165165.68 | BU74: =SUM(BL74:BN74) -> 132390.72 | BV74: =SUM(BO74:BQ74) -> 0 | BW74: =SUM(BF74:BK74) -> 333756.25 | BX74: =SUM(BL74:BQ74) -> 132390.72 | BY74: =IF(Info!$O$3="Q1",$BS74,IF(Info!$O$3="Q2",$BS74+$BT74,IF(Info!$O$3="Q3",$BS74+$BT74+$BU74,$BR74))) -> 168590.57 | BZ74: =IF(Info!$O$3="Q1",$BS74,IF(Info!$O$3="Q2",$BT74,IF(Info!$O$3="Q3",$BU74,$BV74))) -> 168590.57
B75: Sales of upcycle (excl.VAT) | D75: =SUM(E75:BD75) -> 0 | E75: =SUM(Paniglgasse:Lerchenfelder!E75) -> 0 | F75: =SUM(Paniglgasse:Lerchenfelder!F75) -> 0 | G75: =SUM(Paniglgasse:Lerchenfelder!G75) -> 0 | H75: =SUM(Paniglgasse:Lerchenfelder!H75) -> 0 | I75: =SUM(Paniglgasse:Lerchenfelder!I75) -> 0 | J75: =SUM(Paniglgasse:Lerchenfelder!J75) -> 0 | K75: =SUM(Paniglgasse:Lerchenfelder!K75) -> 0 | L75: =SUM(Paniglgasse:Lerchenfelder!L75) -> 0 | ... BD75: =SUM(Paniglgasse:Lerchenfelder!BD75) -> 0 | BF75: =SUM(E75:H75) -> 0 | BG75: =SUM(I75:L75) -> 0 | BH75: =SUM(M75:Q75) -> 0 | BI75: =SUM(R75:U75) -> 0 | BJ75: =SUM(V75:Y75) -> 0 | BK75: =SUM(Z75:AD75) -> 0 | BL75: =SUM(AE75:AH75) -> 0 | BM75: =SUM(AI75:AL75) -> 0 | BN75: =SUM(AM75:AQ75) -> 0 | BO75: =SUM(AR75:AU75) -> 0 | BP75: =SUM(AV75:AY75) -> 0 | BQ75: =SUM(AZ75:BD75) -> 0 | BR75: =SUM(BF75:BQ75) -> 0 | BS75: =SUM(BF75:BH75) -> 0 | BT75: =SUM(BI75:BK75) -> 0 | BU75: =SUM(BL75:BN75) -> 0 | BV75: =SUM(BO75:BQ75) -> 0 | BW75: =SUM(BF75:BK75) -> 0 | BX75: =SUM(BL75:BQ75) -> 0 | BY75: =IF(Info!$O$3="Q1",$BS75,IF(Info!$O$3="Q2",$BS75+$BT75,IF(Info!$O$3="Q3",$BS75+$BT75+$BU75,$BR75))) -> 0 | BZ75: =IF(Info!$O$3="Q1",$BS75,IF(Info!$O$3="Q2",$BT75,IF(Info!$O$3="Q3",$BU75,$BV75))) -> 0
B76: Sales of paper bags (excl.VAT) | D76: =SUM(E76:BD76) -> 0 | E76: =SUM(Paniglgasse:Lerchenfelder!E76) -> 0 | F76: =SUM(Paniglgasse:Lerchenfelder!F76) -> 0 | G76: =SUM(Paniglgasse:Lerchenfelder!G76) -> 0 | H76: =SUM(Paniglgasse:Lerchenfelder!H76) -> 0 | I76: =SUM(Paniglgasse:Lerchenfelder!I76) -> 0 | J76: =SUM(Paniglgasse:Lerchenfelder!J76) -> 0 | K76: =SUM(Paniglgasse:Lerchenfelder!K76) -> 0 | L76: =SUM(Paniglgasse:Lerchenfelder!L76) -> 0 | ... BD76: =SUM(Paniglgasse:Lerchenfelder!BD76) -> 0 | BF76: =SUM(E76:H76) -> 0 | BG76: =SUM(I76:L76) -> 0 | BH76: =SUM(M76:Q76) -> 0 | BI76: =SUM(R76:U76) -> 0 | BJ76: =SUM(V76:Y76) -> 0 | BK76: =SUM(Z76:AD76) -> 0 | BL76: =SUM(AE76:AH76) -> 0 | BM76: =SUM(AI76:AL76) -> 0 | BN76: =SUM(AM76:AQ76) -> 0 | BO76: =SUM(AR76:AU76) -> 0 | BP76: =SUM(AV76:AY76) -> 0 | BQ76: =SUM(AZ76:BD76) -> 0 | BR76: =SUM(BF76:BQ76) -> 0 | BS76: =SUM(BF76:BH76) -> 0 | BT76: =SUM(BI76:BK76) -> 0 | BU76: =SUM(BL76:BN76) -> 0 | BV76: =SUM(BO76:BQ76) -> 0 | BW76: =SUM(BF76:BK76) -> 0 | BX76: =SUM(BL76:BQ76) -> 0 | BY76: =IF(Info!$O$3="Q1",$BS76,IF(Info!$O$3="Q2",$BS76+$BT76,IF(Info!$O$3="Q3",$BS76+$BT76+$BU76,$BR76))) -> 0 | BZ76: =IF(Info!$O$3="Q1",$BS76,IF(Info!$O$3="Q2",$BT76,IF(Info!$O$3="Q3",$BU76,$BV76))) -> 0
B77: Total income (excl. VAT) | C77: =Info!$R$3 -> 0.2 | D77: =SUM(E77:BD77) -> 466146.97 | E77: =SUM(E74:E76) -> 12837.042 | F77: =SUM(F74:F76) -> 7218.75 | G77: =SUM(G74:G76) -> 11013.992 | H77: =SUM(H74:H76) -> 15292.967 | I77: =SUM(I74:I76) -> 17205.017 | J77: =SUM(J74:J76) -> 14847.45 | K77: =SUM(K74:K76) -> 9448.0583 | L77: =SUM(L74:L76) -> 10811.625 | ... BD77: =SUM(BD74:BD76) -> 0 | BF77: =SUM(E77:H77) -> 46362.75 | BG77: =SUM(I77:L77) -> 52312.15 | BH77: =SUM(M77:Q77) -> 69915.667 | BI77: =SUM(R77:U77) -> 52939.992 | BJ77: =SUM(V77:Y77) -> 52514.533 | BK77: =SUM(Z77:AD77) -> 59711.158 | BL77: =SUM(AE77:AH77) -> 44128.4 | BM77: =SUM(AI77:AL77) -> 39667.4 | BN77: =SUM(AM77:AQ77) -> 48594.917 | BO77: =SUM(AR77:AU77) -> 0 | BP77: =SUM(AV77:AY77) -> 0 | BQ77: =SUM(AZ77:BD77) -> 0 | BR77: =SUM(BF77:BQ77) -> 466146.97 | BS77: =SUM(BF77:BH77) -> 168590.57 | BT77: =SUM(BI77:BK77) -> 165165.68 | BU77: =SUM(BL77:BN77) -> 132390.72 | BV77: =SUM(BO77:BQ77) -> 0 | BW77: =SUM(BF77:BK77) -> 333756.25 | BX77: =SUM(BL77:BQ77) -> 132390.72 | BY77: =IF(Info!$O$3="Q1",$BS77,IF(Info!$O$3="Q2",$BS77+$BT77,IF(Info!$O$3="Q3",$BS77+$BT77+$BU77,$BR77))) -> 168590.57 | BZ77: =IF(Info!$O$3="Q1",$BS77,IF(Info!$O$3="Q2",$BT77,IF(Info!$O$3="Q3",$BU77,$BV77))) -> 168590.57
B78: Accumulated income from ordinary sales (excl. VAT) | E78: =E74 -> 12837.042 | F78: =E78+F74 -> 20055.792 | G78: =F78+G74 -> 31069.783 | H78: =G78+H74 -> 46362.75 | I78: =H78+I74 -> 63567.767 | J78: =I78+J74 -> 78415.217 | K78: =J78+K74 -> 87863.275 | L78: =K78+L74 -> 98674.9 | M78: =L78+M74 -> 116484.28 | ... CA78: =BZ78+CA74 -> 2667916
B79: Contribution margin | D79: =SUM(E79:BD79) -> 357029.31 | E79: =E74-E86 -> 10777.742 | F79: =F74-F86 -> 5325.77 | G79: =G74-G86 -> 8405.9417 | H79: =H74-H86 -> 4592.7767 | I79: =I74-I86 -> 14263.597 | J79: =J74-J86 -> 12983.85 | K79: =K74-K86 -> 7723.5283 | L79: =L74-L86 -> 8068.529 | ... CA79: =CA74-CA86 -> 0
B80: Expenses excl. VAT
A81: 1 | B81: Clothes | D81: =SUM(E81:BD81) -> 105430.74 | E81: =((E37+E40)*Info!$AJ$3)+(E38*Info!$AJ$5)+(E41*Info!$AJ$6)+(E39*Info!$AJ$7)+(E42*Info!$AJ$9)+(E43*Info!$AJ$10)+(E44*Info!$AJ$11)+(E45*Info!$AJ$12)+(E46*Info!$AJ$13) -> 2061.804 | F81: =((F37+F40)*Info!$AJ$3)+(F38*Info!$AJ$5)+(F41*Info!$AJ$6)+(F39*Info!$AJ$7)+(F42*Info!$AJ$9)+(F43*Info!$AJ$10)+(F44*Info!$AJ$11)+(F45*Info!$AJ$12)+(F46*Info!$AJ$13) -> 1402.32 | G81: =((G37+G40)*Info!$AJ$3)+(G38*Info!$AJ$5)+(G41*Info!$AJ$6)+(G39*Info!$AJ$7)+(G42*Info!$AJ$9)+(G43*Info!$AJ$10)+(G44*Info!$AJ$11)+(G45*Info!$AJ$12)+(G46*Info!$AJ$13) -> 2376.768 | H81: =((H37+H40)*Info!$AJ$3)+(H38*Info!$AJ$5)+(H41*Info!$AJ$6)+(H39*Info!$AJ$7)+(H42*Info!$AJ$9)+(H43*Info!$AJ$10)+(H44*Info!$AJ$11)+(H45*Info!$AJ$12)+(H46*Info!$AJ$13) -> 9506.432 | I81: =((I37+I40)*Info!$AJ$3)+(I38*Info!$AJ$5)+(I41*Info!$AJ$6)+(I39*Info!$AJ$7)+(I42*Info!$AJ$9)+(I43*Info!$AJ$10)+(I44*Info!$AJ$11)+(I45*Info!$AJ$12)+(I46*Info!$AJ$13) -> 3307.252 | J81: =((J37+J40)*Info!$AJ$3)+(J38*Info!$AJ$5)+(J41*Info!$AJ$6)+(J39*Info!$AJ$7)+(J42*Info!$AJ$9)+(J43*Info!$AJ$10)+(J44*Info!$AJ$11)+(J45*Info!$AJ$12)+(J46*Info!$AJ$13) -> 1714.372 | K81: =((K37+K40)*Info!$AJ$3)+(K38*Info!$AJ$5)+(K41*Info!$AJ$6)+(K39*Info!$AJ$7)+(K42*Info!$AJ$9)+(K43*Info!$AJ$10)+(K44*Info!$AJ$11)+(K45*Info!$AJ$12)+(K46*Info!$AJ$13) -> 1430.932 | L81: =((L37+L40)*Info!$AJ$3)+(L38*Info!$AJ$5)+(L41*Info!$AJ$6)+(L39*Info!$AJ$7)+(L42*Info!$AJ$9)+(L43*Info!$AJ$10)+(L44*Info!$AJ$11)+(L45*Info!$AJ$12)+(L46*Info!$AJ$13) -> 2468.096 | ... BD81: =((BD37+BD40)*Info!$AJ$3)+(BD38*Info!$AJ$5)+(BD41*Info!$AJ$6)+(BD39*Info!$AJ$7)+(BD42*Info!$AJ$9)+(BD43*Info!$AJ$10)+(BD44*Info!$AJ$11)+(BD45*Info!$AJ$12)+(BD46*Info!$AJ$13) -> 0
B82: Cost of clothes put in the shop | D82: =SUM(E82:BD82) -> 105303.09 | E82: =SUM(Paniglgasse:Lerchenfelder!E82) -> 2059.3 | F82: =SUM(Paniglgasse:Lerchenfelder!F82) -> 1552.98 | G82: =SUM(Paniglgasse:Lerchenfelder!G82) -> 2608.05 | H82: =SUM(Paniglgasse:Lerchenfelder!H82) -> 10555.19 | I82: =SUM(Paniglgasse:Lerchenfelder!I82) -> 2731.42 | J82: =SUM(Paniglgasse:Lerchenfelder!J82) -> 1653.6 | K82: =SUM(Paniglgasse:Lerchenfelder!K82) -> 1419.65 | L82: =SUM(Paniglgasse:Lerchenfelder!L82) -> 2468.096 | ... BD82: =SUM(Paniglgasse:Lerchenfelder!BD82) -> 0 | BF82: =SUM(E82:H82) -> 16775.52 | BG82: =SUM(I82:L82) -> 8272.766 | BH82: =SUM(M82:Q82) -> 15306.476 | BI82: =SUM(R82:U82) -> 11354.94 | BJ82: =SUM(V82:Y82) -> 10944.23 | BK82: =SUM(Z82:AD82) -> 13075.64 | BL82: =SUM(AE82:AH82) -> 11504.68 | BM82: =SUM(AI82:AL82) -> 4987.82 | BN82: =SUM(AM82:AQ82) -> 13081.02 | BO82: =SUM(AR82:AU82) -> 0 | BP82: =SUM(AV82:AY82) -> 0 | BQ82: =SUM(AZ82:BD82) -> 0 | BR82: =SUM(BF82:BQ82) -> 105303.09 | BS82: =SUM(BF82:BH82) -> 40354.762 | BT82: =SUM(BI82:BK82) -> 35374.81 | BU82: =SUM(BL82:BN82) -> 29573.52 | BV82: =SUM(BO82:BQ82) -> 0 | BW82: =SUM(BF82:BK82) -> 75729.572 | BX82: =SUM(BL82:BQ82) -> 29573.52 | BY82: =IF(Info!$O$3="Q1",$BS82,IF(Info!$O$3="Q2",$BS82+$BT82,IF(Info!$O$3="Q3",$BS82+$BT82+$BU82,$BR82))) -> 40354.762 | BZ82: =IF(Info!$O$3="Q1",$BS82,IF(Info!$O$3="Q2",$BT82,IF(Info!$O$3="Q3",$BU82,$BV82))) -> 40354.762
B83: Transport of clothes (international) | D83: =SUM(E83:BD83) -> 3814.56 | E83: =SUM(Paniglgasse:Lerchenfelder!E83) -> 0 | F83: =SUM(Paniglgasse:Lerchenfelder!F83) -> 340 | G83: =SUM(Paniglgasse:Lerchenfelder!G83) -> 0 | H83: =SUM(Paniglgasse:Lerchenfelder!H83) -> 145 | I83: =SUM(Paniglgasse:Lerchenfelder!I83) -> 210 | J83: =SUM(Paniglgasse:Lerchenfelder!J83) -> 210 | K83: =SUM(Paniglgasse:Lerchenfelder!K83) -> 304.88 | L83: =SUM(Paniglgasse:Lerchenfelder!L83) -> 275 | ... BD83: =SUM(Paniglgasse:Lerchenfelder!BD83) -> 0 | BF83: =SUM(E83:H83) -> 485 | BG83: =SUM(I83:L83) -> 999.88 | BH83: =SUM(M83:Q83) -> 286.82 | BI83: =SUM(R83:U83) -> 324.43 | BJ83: =SUM(V83:Y83) -> 233.5 | BK83: =SUM(Z83:AD83) -> 466.81 | BL83: =SUM(AE83:AH83) -> 327.94 | BM83: =SUM(AI83:AL83) -> 439.57 | BN83: =SUM(AM83:AQ83) -> 250.61 | BO83: =SUM(AR83:AU83) -> 0 | BP83: =SUM(AV83:AY83) -> 0 | BQ83: =SUM(AZ83:BD83) -> 0 | BR83: =SUM(BF83:BQ83) -> 3814.56 | BS83: =SUM(BF83:BH83) -> 1771.7 | BT83: =SUM(BI83:BK83) -> 1024.74 | BU83: =SUM(BL83:BN83) -> 1018.12 | BV83: =SUM(BO83:BQ83) -> 0 | BW83: =SUM(BF83:BK83) -> 2796.44 | BX83: =SUM(BL83:BQ83) -> 1018.12 | BY83: =IF(Info!$O$3="Q1",$BS83,IF(Info!$O$3="Q2",$BS83+$BT83,IF(Info!$O$3="Q3",$BS83+$BT83+$BU83,$BR83))) -> 1771.7 | BZ83: =IF(Info!$O$3="Q1",$BS83,IF(Info!$O$3="Q2",$BT83,IF(Info!$O$3="Q3",$BU83,$BV83))) -> 1771.7
B84: Transport of clothes (local) | D84: =SUM(E84:BD84) -> 0 | E84: =SUM(Paniglgasse:Lerchenfelder!E84) -> 0 | F84: =SUM(Paniglgasse:Lerchenfelder!F84) -> 0 | G84: =SUM(Paniglgasse:Lerchenfelder!G84) -> 0 | H84: =SUM(Paniglgasse:Lerchenfelder!H84) -> 0 | I84: =SUM(Paniglgasse:Lerchenfelder!I84) -> 0 | J84: =SUM(Paniglgasse:Lerchenfelder!J84) -> 0 | K84: =SUM(Paniglgasse:Lerchenfelder!K84) -> 0 | L84: =SUM(Paniglgasse:Lerchenfelder!L84) -> 0 | ... BD84: =SUM(Paniglgasse:Lerchenfelder!BD84) -> 0 | BF84: =SUM(E84:H84) -> 0 | BG84: =SUM(I84:L84) -> 0 | BH84: =SUM(M84:Q84) -> 0 | BI84: =SUM(R84:U84) -> 0 | BJ84: =SUM(V84:Y84) -> 0 | BK84: =SUM(Z84:AD84) -> 0 | BL84: =SUM(AE84:AH84) -> 0 | BM84: =SUM(AI84:AL84) -> 0 | BN84: =SUM(AM84:AQ84) -> 0 | BO84: =SUM(AR84:AU84) -> 0 | BP84: =SUM(AV84:AY84) -> 0 | BQ84: =SUM(AZ84:BD84) -> 0 | BR84: =SUM(BF84:BQ84) -> 0 | BS84: =SUM(BF84:BH84) -> 0 | BT84: =SUM(BI84:BK84) -> 0 | BU84: =SUM(BL84:BN84) -> 0 | BV84: =SUM(BO84:BQ84) -> 0 | BW84: =SUM(BF84:BK84) -> 0 | BX84: =SUM(BL84:BQ84) -> 0 | BY84: =IF(Info!$O$3="Q1",$BS84,IF(Info!$O$3="Q2",$BS84+$BT84,IF(Info!$O$3="Q3",$BS84+$BT84+$BU84,$BR84))) -> 0 | BZ84: =IF(Info!$O$3="Q1",$BS84,IF(Info!$O$3="Q2",$BT84,IF(Info!$O$3="Q3",$BU84,$BV84))) -> 0
B85: Customs brokers fees/Upcycle product | D85: =SUM(E85:BD85) -> 0 | E85: =SUM(Paniglgasse:Lerchenfelder!E85) -> 0 | F85: =SUM(Paniglgasse:Lerchenfelder!F85) -> 0 | G85: =SUM(Paniglgasse:Lerchenfelder!G85) -> 0 | H85: =SUM(Paniglgasse:Lerchenfelder!H85) -> 0 | I85: =SUM(Paniglgasse:Lerchenfelder!I85) -> 0 | J85: =SUM(Paniglgasse:Lerchenfelder!J85) -> 0 | K85: =SUM(Paniglgasse:Lerchenfelder!K85) -> 0 | L85: =SUM(Paniglgasse:Lerchenfelder!L85) -> 0 | ... BD85: =SUM(Paniglgasse:Lerchenfelder!BD85) -> 0 | BF85: =SUM(E85:H85) -> 0 | BG85: =SUM(I85:L85) -> 0 | BH85: =SUM(M85:Q85) -> 0 | BI85: =SUM(R85:U85) -> 0 | BJ85: =SUM(V85:Y85) -> 0 | BK85: =SUM(Z85:AD85) -> 0 | BL85: =SUM(AE85:AH85) -> 0 | BM85: =SUM(AI85:AL85) -> 0 | BN85: =SUM(AM85:AQ85) -> 0 | BO85: =SUM(AR85:AU85) -> 0 | BP85: =SUM(AV85:AY85) -> 0 | BQ85: =SUM(AZ85:BD85) -> 0 | BR85: =SUM(BF85:BQ85) -> 0 | BS85: =SUM(BF85:BH85) -> 0 | BT85: =SUM(BI85:BK85) -> 0 | BU85: =SUM(BL85:BN85) -> 0 | BV85: =SUM(BO85:BQ85) -> 0 | BW85: =SUM(BF85:BK85) -> 0 | BX85: =SUM(BL85:BQ85) -> 0 | BY85: =IF(Info!$O$3="Q1",$BS85,IF(Info!$O$3="Q2",$BS85+$BT85,IF(Info!$O$3="Q3",$BS85+$BT85+$BU85,$BR85))) -> 0 | BZ85: =IF(Info!$O$3="Q1",$BS85,IF(Info!$O$3="Q2",$BT85,IF(Info!$O$3="Q3",$BU85,$BV85))) -> 0
B86: Total clothes | D86: =SUM(E86:BD86) -> 109117.65 | E86: =SUM(E82:E85) -> 2059.3 | F86: =SUM(F82:F85) -> 1892.98 | G86: =SUM(G82:G85) -> 2608.05 | H86: =SUM(H82:H85) -> 10700.19 | I86: =SUM(I82:I85) -> 2941.42 | J86: =SUM(J82:J85) -> 1863.6 | K86: =SUM(K82:K85) -> 1724.53 | L86: =SUM(L82:L85) -> 2743.096 | ... BD86: =SUM(BD82:BD85) -> 0 | BF86: =SUM(E86:H86) -> 17260.52 | BG86: =SUM(I86:L86) -> 9272.646 | BH86: =SUM(M86:Q86) -> 15593.296 | BI86: =SUM(R86:U86) -> 11679.37 | BJ86: =SUM(V86:Y86) -> 11177.73 | BK86: =SUM(Z86:AD86) -> 13542.45 | BL86: =SUM(AE86:AH86) -> 11832.62 | BM86: =SUM(AI86:AL86) -> 5427.39 | BN86: =SUM(AM86:AQ86) -> 13331.63 | BO86: =SUM(AR86:AU86) -> 0 | BP86: =SUM(AV86:AY86) -> 0 | BQ86: =SUM(AZ86:BD86) -> 0 | BR86: =SUM(BF86:BQ86) -> 109117.65 | BS86: =SUM(BF86:BH86) -> 42126.462 | BT86: =SUM(BI86:BK86) -> 36399.55 | BU86: =SUM(BL86:BN86) -> 30591.64 | BV86: =SUM(BO86:BQ86) -> 0 | BW86: =SUM(BF86:BK86) -> 78526.012 | BX86: =SUM(BL86:BQ86) -> 30591.64 | BY86: =IF(Info!$O$3="Q1",$BS86,IF(Info!$O$3="Q2",$BS86+$BT86,IF(Info!$O$3="Q3",$BS86+$BT86+$BU86,$BR86))) -> 42126.462 | BZ86: =IF(Info!$O$3="Q1",$BS86,IF(Info!$O$3="Q2",$BT86,IF(Info!$O$3="Q3",$BU86,$BV86))) -> 42126.462
A87: 2 | B87: Buildings | D87: =SUM(E82:BD85)-D86 -> 0
B88: Rent | D88: =SUM(E88:BD88) -> 71415.4 | E88: =SUM(Paniglgasse:Lerchenfelder!E88) -> 1992.0825 | F88: =SUM(Paniglgasse:Lerchenfelder!F88) -> 1992.0825 | G88: =SUM(Paniglgasse:Lerchenfelder!G88) -> 1992.0825 | H88: =SUM(Paniglgasse:Lerchenfelder!H88) -> 1992.0825 | I88: =SUM(Paniglgasse:Lerchenfelder!I88) -> 1992.0825 | J88: =SUM(Paniglgasse:Lerchenfelder!J88) -> 1992.0825 | K88: =SUM(Paniglgasse:Lerchenfelder!K88) -> 1992.0825 | L88: =SUM(Paniglgasse:Lerchenfelder!L88) -> 1992.0825 | ... BD88: =SUM(Paniglgasse:Lerchenfelder!BD88) -> 0 | BF88: =SUM(E88:H88) -> 7968.33 | BG88: =SUM(I88:L88) -> 7968.33 | BH88: =SUM(M88:Q88) -> 7968.33 | BI88: =SUM(R88:U88) -> 8204.65 | BJ88: =SUM(V88:Y88) -> 8188.7 | BK88: =SUM(Z88:AD88) -> 8188.7 | BL88: =SUM(AE88:AH88) -> 8188.7 | BM88: =SUM(AI88:AL88) -> 8188.7 | BN88: =SUM(AM88:AQ88) -> 6550.96 | BO88: =SUM(AR88:AU88) -> 0 | BP88: =SUM(AV88:AY88) -> 0 | BQ88: =SUM(AZ88:BD88) -> 0 | BR88: =SUM(BF88:BQ88) -> 71415.4 | BS88: =SUM(BF88:BH88) -> 23904.99 | BT88: =SUM(BI88:BK88) -> 24582.05 | BU88: =SUM(BL88:BN88) -> 22928.36 | BV88: =SUM(BO88:BQ88) -> 0 | BW88: =SUM(BF88:BK88) -> 48487.04 | BX88: =SUM(BL88:BQ88) -> 22928.36 | BY88: =IF(Info!$O$3="Q1",$BS88,IF(Info!$O$3="Q2",$BS88+$BT88,IF(Info!$O$3="Q3",$BS88+$BT88+$BU88,$BR88))) -> 23904.99 | BZ88: =IF(Info!$O$3="Q1",$BS88,IF(Info!$O$3="Q2",$BT88,IF(Info!$O$3="Q3",$BU88,$BV88))) -> 23904.99
B89: Electricity / heating / water | D89: =SUM(E89:BD89) -> 2916.9054 | E89: =SUM(Paniglgasse:Lerchenfelder!E89) -> 442.24712 | F89: =SUM(Paniglgasse:Lerchenfelder!F89) -> 442.24712 | G89: =SUM(Paniglgasse:Lerchenfelder!G89) -> 442.24712 | H89: =SUM(Paniglgasse:Lerchenfelder!H89) -> 442.24712 | I89: =SUM(Paniglgasse:Lerchenfelder!I89) -> 442.24712 | J89: =SUM(Paniglgasse:Lerchenfelder!J89) -> 442.24712 | K89: =SUM(Paniglgasse:Lerchenfelder!K89) -> 442.24712 | L89: =SUM(Paniglgasse:Lerchenfelder!L89) -> 442.24712 | ... BD89: =SUM(Paniglgasse:Lerchenfelder!BD89) -> 0 | BF89: =SUM(E89:H89) -> 1768.9885 | BG89: =SUM(I89:L89) -> 1768.9885 | BH89: =SUM(M89:Q89) -> 2034.3731 | BI89: =SUM(R89:U89) -> 1768.9885 | BJ89: =SUM(V89:Y89) -> -7963.3415 | BK89: =SUM(Z89:AD89) -> 2034.3731 | BL89: =SUM(AE89:AH89) -> -1891.9515 | BM89: =SUM(AI89:AL89) -> 1768.9885 | BN89: =SUM(AM89:AQ89) -> 1627.4985 | BO89: =SUM(AR89:AU89) -> 0 | BP89: =SUM(AV89:AY89) -> 0 | BQ89: =SUM(AZ89:BD89) -> 0 | BR89: =SUM(BF89:BQ89) -> 2916.9054 | BS89: =SUM(BF89:BH89) -> 5572.35 | BT89: =SUM(BI89:BK89) -> -4159.98 | BU89: =SUM(BL89:BN89) -> 1504.5354 | BV89: =SUM(BO89:BQ89) -> 0 | BW89: =SUM(BF89:BK89) -> 1412.37 | BX89: =SUM(BL89:BQ89) -> 1504.5354 | BY89: =IF(Info!$O$3="Q1",$BS89,IF(Info!$O$3="Q2",$BS89+$BT89,IF(Info!$O$3="Q3",$BS89+$BT89+$BU89,$BR89))) -> 5572.35 | BZ89: =IF(Info!$O$3="Q1",$BS89,IF(Info!$O$3="Q2",$BT89,IF(Info!$O$3="Q3",$BU89,$BV89))) -> 5572.35
B90: Maintenance / renovation | D90: =SUM(E90:BD90) -> 931.465 | E90: =SUM(Paniglgasse:Lerchenfelder!E90) -> 0 | F90: =SUM(Paniglgasse:Lerchenfelder!F90) -> 0 | G90: =SUM(Paniglgasse:Lerchenfelder!G90) -> 77.59 | H90: =SUM(Paniglgasse:Lerchenfelder!H90) -> 21.45 | I90: =SUM(Paniglgasse:Lerchenfelder!I90) -> 37.95 | J90: =SUM(Paniglgasse:Lerchenfelder!J90) -> 10.94 | K90: =SUM(Paniglgasse:Lerchenfelder!K90) -> 70.35 | L90: =SUM(Paniglgasse:Lerchenfelder!L90) -> 0 | ... BD90: =SUM(Paniglgasse:Lerchenfelder!BD90) -> 0 | BF90: =SUM(E90:H90) -> 99.04 | BG90: =SUM(I90:L90) -> 119.24 | BH90: =SUM(M90:Q90) -> 0 | BI90: =SUM(R90:U90) -> 0 | BJ90: =SUM(V90:Y90) -> 0 | BK90: =SUM(Z90:AD90) -> 0 | BL90: =SUM(AE90:AH90) -> 0 | BM90: =SUM(AI90:AL90) -> 374.58 | BN90: =SUM(AM90:AQ90) -> 338.605 | BO90: =SUM(AR90:AU90) -> 0 | BP90: =SUM(AV90:AY90) -> 0 | BQ90: =SUM(AZ90:BD90) -> 0 | BR90: =SUM(BF90:BQ90) -> 931.465 | BS90: =SUM(BF90:BH90) -> 218.28 | BT90: =SUM(BI90:BK90) -> 0 | BU90: =SUM(BL90:BN90) -> 713.185 | BV90: =SUM(BO90:BQ90) -> 0 | BW90: =SUM(BF90:BK90) -> 218.28 | BX90: =SUM(BL90:BQ90) -> 713.185 | BY90: =IF(Info!$O$3="Q1",$BS90,IF(Info!$O$3="Q2",$BS90+$BT90,IF(Info!$O$3="Q3",$BS90+$BT90+$BU90,$BR90))) -> 218.28 | BZ90: =IF(Info!$O$3="Q1",$BS90,IF(Info!$O$3="Q2",$BT90,IF(Info!$O$3="Q3",$BU90,$BV90))) -> 218.28
B91: Insurance | D91: =SUM(E91:BD91) -> 703.07333 | E91: =SUM(Paniglgasse:Lerchenfelder!E91) -> 0 | F91: =SUM(Paniglgasse:Lerchenfelder!F91) -> 0 | G91: =SUM(Paniglgasse:Lerchenfelder!G91) -> 0 | H91: =SUM(Paniglgasse:Lerchenfelder!H91) -> 0 | I91: =SUM(Paniglgasse:Lerchenfelder!I91) -> 0 | J91: =SUM(Paniglgasse:Lerchenfelder!J91) -> 0 | K91: =SUM(Paniglgasse:Lerchenfelder!K91) -> 0 | L91: =SUM(Paniglgasse:Lerchenfelder!L91) -> 0 | ... BD91: =SUM(Paniglgasse:Lerchenfelder!BD91) -> 0 | BF91: =SUM(E91:H91) -> 0 | BG91: =SUM(I91:L91) -> 0 | BH91: =SUM(M91:Q91) -> 0 | BI91: =SUM(R91:U91) -> 0 | BJ91: =SUM(V91:Y91) -> 0 | BK91: =SUM(Z91:AD91) -> 0 | BL91: =SUM(AE91:AH91) -> 0 | BM91: =SUM(AI91:AL91) -> 703.07333 | BN91: =SUM(AM91:AQ91) -> 0 | BO91: =SUM(AR91:AU91) -> 0 | BP91: =SUM(AV91:AY91) -> 0 | BQ91: =SUM(AZ91:BD91) -> 0 | BR91: =SUM(BF91:BQ91) -> 703.07333 | BS91: =SUM(BF91:BH91) -> 0 | BT91: =SUM(BI91:BK91) -> 0 | BU91: =SUM(BL91:BN91) -> 703.07333 | BV91: =SUM(BO91:BQ91) -> 0 | BW91: =SUM(BF91:BK91) -> 0 | BX91: =SUM(BL91:BQ91) -> 703.07333 | BY91: =IF(Info!$O$3="Q1",$BS91,IF(Info!$O$3="Q2",$BS91+$BT91,IF(Info!$O$3="Q3",$BS91+$BT91+$BU91,$BR91))) -> 0 | BZ91: =IF(Info!$O$3="Q1",$BS91,IF(Info!$O$3="Q2",$BT91,IF(Info!$O$3="Q3",$BU91,$BV91))) -> 0
B92: Acquisition of assets for buildings | D92: =SUM(E92:BD92) -> 0 | E92: =SUM(Paniglgasse:Lerchenfelder!E92) -> 0 | F92: =SUM(Paniglgasse:Lerchenfelder!F92) -> 0 | G92: =SUM(Paniglgasse:Lerchenfelder!G92) -> 0 | H92: =SUM(Paniglgasse:Lerchenfelder!H92) -> 0 | I92: =SUM(Paniglgasse:Lerchenfelder!I92) -> 0 | J92: =SUM(Paniglgasse:Lerchenfelder!J92) -> 0 | K92: =SUM(Paniglgasse:Lerchenfelder!K92) -> 0 | L92: =SUM(Paniglgasse:Lerchenfelder!L92) -> 0 | ... BD92: =SUM(Paniglgasse:Lerchenfelder!BD92) -> 0 | BF92: =SUM(E92:H92) -> 0 | BG92: =SUM(I92:L92) -> 0 | BH92: =SUM(M92:Q92) -> 0 | BI92: =SUM(R92:U92) -> 0 | BJ92: =SUM(V92:Y92) -> 0 | BK92: =SUM(Z92:AD92) -> 0 | BL92: =SUM(AE92:AH92) -> 0 | BM92: =SUM(AI92:AL92) -> 0 | BN92: =SUM(AM92:AQ92) -> 0 | BO92: =SUM(AR92:AU92) -> 0 | BP92: =SUM(AV92:AY92) -> 0 | BQ92: =SUM(AZ92:BD92) -> 0 | BR92: =SUM(BF92:BQ92) -> 0 | BS92: =SUM(BF92:BH92) -> 0 | BT92: =SUM(BI92:BK92) -> 0 | BU92: =SUM(BL92:BN92) -> 0 | BV92: =SUM(BO92:BQ92) -> 0 | BW92: =SUM(BF92:BK92) -> 0 | BX92: =SUM(BL92:BQ92) -> 0 | BY92: =IF(Info!$O$3="Q1",$BS92,IF(Info!$O$3="Q2",$BS92+$BT92,IF(Info!$O$3="Q3",$BS92+$BT92+$BU92,$BR92))) -> 0 | BZ92: =IF(Info!$O$3="Q1",$BS92,IF(Info!$O$3="Q2",$BT92,IF(Info!$O$3="Q3",$BU92,$BV92))) -> 0
B93: Other buildings expenses | D93: =SUM(E93:BD93) -> 0 | E93: =SUM(Paniglgasse:Lerchenfelder!E93) -> 0 | F93: =SUM(Paniglgasse:Lerchenfelder!F93) -> 0 | G93: =SUM(Paniglgasse:Lerchenfelder!G93) -> 0 | H93: =SUM(Paniglgasse:Lerchenfelder!H93) -> 0 | I93: =SUM(Paniglgasse:Lerchenfelder!I93) -> 0 | J93: =SUM(Paniglgasse:Lerchenfelder!J93) -> 0 | K93: =SUM(Paniglgasse:Lerchenfelder!K93) -> 0 | L93: =SUM(Paniglgasse:Lerchenfelder!L93) -> 0 | ... BD93: =SUM(Paniglgasse:Lerchenfelder!BD93) -> 0 | BF93: =SUM(E93:H93) -> 0 | BG93: =SUM(I93:L93) -> 0 | BH93: =SUM(M93:Q93) -> 0 | BI93: =SUM(R93:U93) -> 0 | BJ93: =SUM(V93:Y93) -> 0 | BK93: =SUM(Z93:AD93) -> 0 | BL93: =SUM(AE93:AH93) -> 0 | BM93: =SUM(AI93:AL93) -> 0 | BN93: =SUM(AM93:AQ93) -> 0 | BO93: =SUM(AR93:AU93) -> 0 | BP93: =SUM(AV93:AY93) -> 0 | BQ93: =SUM(AZ93:BD93) -> 0 | BR93: =SUM(BF93:BQ93) -> 0 | BS93: =SUM(BF93:BH93) -> 0 | BT93: =SUM(BI93:BK93) -> 0 | BU93: =SUM(BL93:BN93) -> 0 | BV93: =SUM(BO93:BQ93) -> 0 | BW93: =SUM(BF93:BK93) -> 0 | BX93: =SUM(BL93:BQ93) -> 0 | BY93: =IF(Info!$O$3="Q1",$BS93,IF(Info!$O$3="Q2",$BS93+$BT93,IF(Info!$O$3="Q3",$BS93+$BT93+$BU93,$BR93))) -> 0 | BZ93: =IF(Info!$O$3="Q1",$BS93,IF(Info!$O$3="Q2",$BT93,IF(Info!$O$3="Q3",$BU93,$BV93))) -> 0
B94: Total buildings | D94: =SUM(E94:BD94) -> 75966.844 | E94: =SUM(E88:E93) -> 2434.3296 | F94: =SUM(F88:F93) -> 2434.3296 | G94: =SUM(G88:G93) -> 2511.9196 | H94: =SUM(H88:H93) -> 2455.7796 | I94: =SUM(I88:I93) -> 2472.2796 | J94: =SUM(J88:J93) -> 2445.2696 | K94: =SUM(K88:K93) -> 2504.6796 | L94: =SUM(L88:L93) -> 2434.3296 | ... BD94: =SUM(BD88:BD93) -> 0 | BF94: =SUM(E94:H94) -> 9836.3585 | BG94: =SUM(I94:L94) -> 9856.5585 | BH94: =SUM(M94:Q94) -> 10002.703 | BI94: =SUM(R94:U94) -> 9973.6385 | BJ94: =SUM(V94:Y94) -> 225.35846 | BK94: =SUM(Z94:AD94) -> 10223.073 | BL94: =SUM(AE94:AH94) -> 6296.7485 | BM94: =SUM(AI94:AL94) -> 11035.342 | BN94: =SUM(AM94:AQ94) -> 8517.0635 | BO94: =SUM(AR94:AU94) -> 0 | BP94: =SUM(AV94:AY94) -> 0 | BQ94: =SUM(AZ94:BD94) -> 0 | BR94: =SUM(BF94:BQ94) -> 75966.844 | BS94: =SUM(BF94:BH94) -> 29695.62 | BT94: =SUM(BI94:BK94) -> 20422.07 | BU94: =SUM(BL94:BN94) -> 25849.154 | BV94: =SUM(BO94:BQ94) -> 0 | BW94: =SUM(BF94:BK94) -> 50117.69 | BX94: =SUM(BL94:BQ94) -> 25849.154 | BY94: =IF(Info!$O$3="Q1",$BS94,IF(Info!$O$3="Q2",$BS94+$BT94,IF(Info!$O$3="Q3",$BS94+$BT94+$BU94,$BR94))) -> 29695.62 | BZ94: =IF(Info!$O$3="Q1",$BS94,IF(Info!$O$3="Q2",$BT94,IF(Info!$O$3="Q3",$BU94,$BV94))) -> 29695.62
A95: 3 | B95: Sales expenses | D95: =SUM(E88:BD93)-D94 -> 0
B96: Sales expenses | D96: =SUM(E96:BD96) -> 1259.67 | E96: =SUM(Paniglgasse:Lerchenfelder!E96) -> 0 | F96: =SUM(Paniglgasse:Lerchenfelder!F96) -> 215.66 | G96: =SUM(Paniglgasse:Lerchenfelder!G96) -> 0 | H96: =SUM(Paniglgasse:Lerchenfelder!H96) -> 323.8 | I96: =SUM(Paniglgasse:Lerchenfelder!I96) -> 206.38 | J96: =SUM(Paniglgasse:Lerchenfelder!J96) -> 217.44 | K96: =SUM(Paniglgasse:Lerchenfelder!K96) -> 50 | L96: =SUM(Paniglgasse:Lerchenfelder!L96) -> 0 | ... BD96: =SUM(Paniglgasse:Lerchenfelder!BD96) -> 0 | BF96: =SUM(E96:H96) -> 539.46 | BG96: =SUM(I96:L96) -> 473.82 | BH96: =SUM(M96:Q96) -> 50 | BI96: =SUM(R96:U96) -> 0 | BJ96: =SUM(V96:Y96) -> 0 | BK96: =SUM(Z96:AD96) -> 0 | BL96: =SUM(AE96:AH96) -> 196.39 | BM96: =SUM(AI96:AL96) -> 0 | BN96: =SUM(AM96:AQ96) -> 0 | BO96: =SUM(AR96:AU96) -> 0 | BP96: =SUM(AV96:AY96) -> 0 | BQ96: =SUM(AZ96:BD96) -> 0 | BR96: =SUM(BF96:BQ96) -> 1259.67 | BS96: =SUM(BF96:BH96) -> 1063.28 | BT96: =SUM(BI96:BK96) -> 0 | BU96: =SUM(BL96:BN96) -> 196.39 | BV96: =SUM(BO96:BQ96) -> 0 | BW96: =SUM(BF96:BK96) -> 1063.28 | BX96: =SUM(BL96:BQ96) -> 196.39 | BY96: =IF(Info!$O$3="Q1",$BS96,IF(Info!$O$3="Q2",$BS96+$BT96,IF(Info!$O$3="Q3",$BS96+$BT96+$BU96,$BR96))) -> 1063.28 | BZ96: =IF(Info!$O$3="Q1",$BS96,IF(Info!$O$3="Q2",$BT96,IF(Info!$O$3="Q3",$BU96,$BV96))) -> 1063.28
B97: Shops equipment | D97: =SUM(E97:BD97) -> 0 | E97: =SUM(Paniglgasse:Lerchenfelder!E97) -> 0 | F97: =SUM(Paniglgasse:Lerchenfelder!F97) -> 0 | G97: =SUM(Paniglgasse:Lerchenfelder!G97) -> 0 | H97: =SUM(Paniglgasse:Lerchenfelder!H97) -> 0 | I97: =SUM(Paniglgasse:Lerchenfelder!I97) -> 0 | J97: =SUM(Paniglgasse:Lerchenfelder!J97) -> 0 | K97: =SUM(Paniglgasse:Lerchenfelder!K97) -> 0 | L97: =SUM(Paniglgasse:Lerchenfelder!L97) -> 0 | ... BD97: =SUM(Paniglgasse:Lerchenfelder!BD97) -> 0 | BF97: =SUM(E97:H97) -> 0 | BG97: =SUM(I97:L97) -> 0 | BH97: =SUM(M97:Q97) -> 0 | BI97: =SUM(R97:U97) -> 0 | BJ97: =SUM(V97:Y97) -> 0 | BK97: =SUM(Z97:AD97) -> 0 | BL97: =SUM(AE97:AH97) -> 0 | BM97: =SUM(AI97:AL97) -> 0 | BN97: =SUM(AM97:AQ97) -> 0 | BO97: =SUM(AR97:AU97) -> 0 | BP97: =SUM(AV97:AY97) -> 0 | BQ97: =SUM(AZ97:BD97) -> 0 | BR97: =SUM(BF97:BQ97) -> 0 | BS97: =SUM(BF97:BH97) -> 0 | BT97: =SUM(BI97:BK97) -> 0 | BU97: =SUM(BL97:BN97) -> 0 | BV97: =SUM(BO97:BQ97) -> 0 | BW97: =SUM(BF97:BK97) -> 0 | BX97: =SUM(BL97:BQ97) -> 0 | BY97: =IF(Info!$O$3="Q1",$BS97,IF(Info!$O$3="Q2",$BS97+$BT97,IF(Info!$O$3="Q3",$BS97+$BT97+$BU97,$BR97))) -> 0 | BZ97: =IF(Info!$O$3="Q1",$BS97,IF(Info!$O$3="Q2",$BT97,IF(Info!$O$3="Q3",$BU97,$BV97))) -> 0
B98: Total sales expenses | D98: =SUM(E98:BD98) -> 1259.67 | E98: =SUM(E96:E97) -> 0 | F98: =SUM(F96:F97) -> 215.66 | G98: =SUM(G96:G97) -> 0 | H98: =SUM(H96:H97) -> 323.8 | I98: =SUM(I96:I97) -> 206.38 | J98: =SUM(J96:J97) -> 217.44 | K98: =SUM(K96:K97) -> 50 | L98: =SUM(L96:L97) -> 0 | ... BD98: =SUM(BD96:BD97) -> 0 | BF98: =SUM(E98:H98) -> 539.46 | BG98: =SUM(I98:L98) -> 473.82 | BH98: =SUM(M98:Q98) -> 50 | BI98: =SUM(R98:U98) -> 0 | BJ98: =SUM(V98:Y98) -> 0 | BK98: =SUM(Z98:AD98) -> 0 | BL98: =SUM(AE98:AH98) -> 196.39 | BM98: =SUM(AI98:AL98) -> 0 | BN98: =SUM(AM98:AQ98) -> 0 | BO98: =SUM(AR98:AU98) -> 0 | BP98: =SUM(AV98:AY98) -> 0 | BQ98: =SUM(AZ98:BD98) -> 0 | BR98: =SUM(BF98:BQ98) -> 1259.67 | BS98: =SUM(BF98:BH98) -> 1063.28 | BT98: =SUM(BI98:BK98) -> 0 | BU98: =SUM(BL98:BN98) -> 196.39 | BV98: =SUM(BO98:BQ98) -> 0 | BW98: =SUM(BF98:BK98) -> 1063.28 | BX98: =SUM(BL98:BQ98) -> 196.39 | BY98: =IF(Info!$O$3="Q1",$BS98,IF(Info!$O$3="Q2",$BS98+$BT98,IF(Info!$O$3="Q3",$BS98+$BT98+$BU98,$BR98))) -> 1063.28 | BZ98: =IF(Info!$O$3="Q1",$BS98,IF(Info!$O$3="Q2",$BT98,IF(Info!$O$3="Q3",$BU98,$BV98))) -> 1063.28
A99: 4 | B99: Running Expenses | D99: =SUM(E96:BD97)-D98 -> 0
B100: Running expenses | D100: =SUM(E100:BD100) -> 1407.44 | E100: =SUM(Paniglgasse:Lerchenfelder!E100) -> 0 | F100: =SUM(Paniglgasse:Lerchenfelder!F100) -> 0 | G100: =SUM(Paniglgasse:Lerchenfelder!G100) -> 10.71 | H100: =SUM(Paniglgasse:Lerchenfelder!H100) -> 0 | I100: =SUM(Paniglgasse:Lerchenfelder!I100) -> 0 | J100: =SUM(Paniglgasse:Lerchenfelder!J100) -> 31.78 | K100: =SUM(Paniglgasse:Lerchenfelder!K100) -> 112.73333 | L100: =SUM(Paniglgasse:Lerchenfelder!L100) -> 72.81 | ... BD100: =SUM(Paniglgasse:Lerchenfelder!BD100) -> 0 | BF100: =SUM(E100:H100) -> 10.71 | BG100: =SUM(I100:L100) -> 217.32333 | BH100: =SUM(M100:Q100) -> 128.55667 | BI100: =SUM(R100:U100) -> 133.15 | BJ100: =SUM(V100:Y100) -> 166.48333 | BK100: =SUM(Z100:AD100) -> 121.79167 | BL100: =SUM(AE100:AH100) -> 91.533333 | BM100: =SUM(AI100:AL100) -> 278.74167 | BN100: =SUM(AM100:AQ100) -> 259.15 | BO100: =SUM(AR100:AU100) -> 0 | BP100: =SUM(AV100:AY100) -> 0 | BQ100: =SUM(AZ100:BD100) -> 0 | BR100: =SUM(BF100:BQ100) -> 1407.44 | BS100: =SUM(BF100:BH100) -> 356.59 | BT100: =SUM(BI100:BK100) -> 421.425 | BU100: =SUM(BL100:BN100) -> 629.425 | BV100: =SUM(BO100:BQ100) -> 0 | BW100: =SUM(BF100:BK100) -> 778.015 | BX100: =SUM(BL100:BQ100) -> 629.425 | BY100: =IF(Info!$O$3="Q1",$BS100,IF(Info!$O$3="Q2",$BS100+$BT100,IF(Info!$O$3="Q3",$BS100+$BT100+$BU100,$BR100))) -> 356.59 | BZ100: =IF(Info!$O$3="Q1",$BS100,IF(Info!$O$3="Q2",$BT100,IF(Info!$O$3="Q3",$BU100,$BV100))) -> 356.59
B101: Fixed running expenses | D101: =SUM(E101:BD101) -> 731.34333 | E101: =SUM(Paniglgasse:Lerchenfelder!E101) -> 0 | F101: =SUM(Paniglgasse:Lerchenfelder!F101) -> 331.99 | G101: =SUM(Paniglgasse:Lerchenfelder!G101) -> 0 | H101: =SUM(Paniglgasse:Lerchenfelder!H101) -> 0 | I101: =SUM(Paniglgasse:Lerchenfelder!I101) -> 0 | J101: =SUM(Paniglgasse:Lerchenfelder!J101) -> 0 | K101: =SUM(Paniglgasse:Lerchenfelder!K101) -> 0 | L101: =SUM(Paniglgasse:Lerchenfelder!L101) -> 0 | ... BD101: =SUM(Paniglgasse:Lerchenfelder!BD101) -> 0 | BF101: =SUM(E101:H101) -> 331.99 | BG101: =SUM(I101:L101) -> 0 | BH101: =SUM(M101:Q101) -> 0 | BI101: =SUM(R101:U101) -> 0 | BJ101: =SUM(V101:Y101) -> 0 | BK101: =SUM(Z101:AD101) -> 0 | BL101: =SUM(AE101:AH101) -> 62.733333 | BM101: =SUM(AI101:AL101) -> 336.62 | BN101: =SUM(AM101:AQ101) -> 0 | BO101: =SUM(AR101:AU101) -> 0 | BP101: =SUM(AV101:AY101) -> 0 | BQ101: =SUM(AZ101:BD101) -> 0 | BR101: =SUM(BF101:BQ101) -> 731.34333 | BS101: =SUM(BF101:BH101) -> 331.99 | BT101: =SUM(BI101:BK101) -> 0 | BU101: =SUM(BL101:BN101) -> 399.35333 | BV101: =SUM(BO101:BQ101) -> 0 | BW101: =SUM(BF101:BK101) -> 331.99 | BX101: =SUM(BL101:BQ101) -> 399.35333 | BY101: =IF(Info!$O$3="Q1",$BS101,IF(Info!$O$3="Q2",$BS101+$BT101,IF(Info!$O$3="Q3",$BS101+$BT101+$BU101,$BR101))) -> 331.99 | BZ101: =IF(Info!$O$3="Q1",$BS101,IF(Info!$O$3="Q2",$BT101,IF(Info!$O$3="Q3",$BU101,$BV101))) -> 331.99
B102: Tel / fax / internet | D102: =SUM(E102:BD102) -> 1668.02 | E102: =SUM(Paniglgasse:Lerchenfelder!E102) -> 0 | F102: =SUM(Paniglgasse:Lerchenfelder!F102) -> 145.79 | G102: =SUM(Paniglgasse:Lerchenfelder!G102) -> 61.86 | H102: =SUM(Paniglgasse:Lerchenfelder!H102) -> 0 | I102: =SUM(Paniglgasse:Lerchenfelder!I102) -> 123.09 | J102: =SUM(Paniglgasse:Lerchenfelder!J102) -> 55.27 | K102: =SUM(Paniglgasse:Lerchenfelder!K102) -> 0 | L102: =SUM(Paniglgasse:Lerchenfelder!L102) -> 0 | ... BD102: =SUM(Paniglgasse:Lerchenfelder!BD102) -> 0 | BF102: =SUM(E102:H102) -> 207.65 | BG102: =SUM(I102:L102) -> 178.36 | BH102: =SUM(M102:Q102) -> 207.08 | BI102: =SUM(R102:U102) -> 201.13 | BJ102: =SUM(V102:Y102) -> 203.22 | BK102: =SUM(Z102:AD102) -> 178.01 | BL102: =SUM(AE102:AH102) -> 116.94 | BM102: =SUM(AI102:AL102) -> 181.97 | BN102: =SUM(AM102:AQ102) -> 193.66 | BO102: =SUM(AR102:AU102) -> 0 | BP102: =SUM(AV102:AY102) -> 0 | BQ102: =SUM(AZ102:BD102) -> 0 | BR102: =SUM(BF102:BQ102) -> 1668.02 | BS102: =SUM(BF102:BH102) -> 593.09 | BT102: =SUM(BI102:BK102) -> 582.36 | BU102: =SUM(BL102:BN102) -> 492.57 | BV102: =SUM(BO102:BQ102) -> 0 | BW102: =SUM(BF102:BK102) -> 1175.45 | BX102: =SUM(BL102:BQ102) -> 492.57 | BY102: =IF(Info!$O$3="Q1",$BS102,IF(Info!$O$3="Q2",$BS102+$BT102,IF(Info!$O$3="Q3",$BS102+$BT102+$BU102,$BR102))) -> 593.09 | BZ102: =IF(Info!$O$3="Q1",$BS102,IF(Info!$O$3="Q2",$BT102,IF(Info!$O$3="Q3",$BU102,$BV102))) -> 593.09
B103: Other running expenses | D103: =SUM(E103:BD103) -> 2693.2233 | E103: =SUM(Paniglgasse:Lerchenfelder!E103) -> 0 | F103: =SUM(Paniglgasse:Lerchenfelder!F103) -> 0 | G103: =SUM(Paniglgasse:Lerchenfelder!G103) -> 0 | H103: =SUM(Paniglgasse:Lerchenfelder!H103) -> 25.5 | I103: =SUM(Paniglgasse:Lerchenfelder!I103) -> 0 | J103: =SUM(Paniglgasse:Lerchenfelder!J103) -> 100.67 | K103: =SUM(Paniglgasse:Lerchenfelder!K103) -> 25.5 | L103: =SUM(Paniglgasse:Lerchenfelder!L103) -> 195 | ... BD103: =SUM(Paniglgasse:Lerchenfelder!BD103) -> 0 | BF103: =SUM(E103:H103) -> 25.5 | BG103: =SUM(I103:L103) -> 321.17 | BH103: =SUM(M103:Q103) -> 25.5 | BI103: =SUM(R103:U103) -> 0 | BJ103: =SUM(V103:Y103) -> 0 | BK103: =SUM(Z103:AD103) -> 1522.2333 | BL103: =SUM(AE103:AH103) -> 290.37 | BM103: =SUM(AI103:AL103) -> 301.58 | BN103: =SUM(AM103:AQ103) -> 206.87 | BO103: =SUM(AR103:AU103) -> 0 | BP103: =SUM(AV103:AY103) -> 0 | BQ103: =SUM(AZ103:BD103) -> 0 | BR103: =SUM(BF103:BQ103) -> 2693.2233 | BS103: =SUM(BF103:BH103) -> 372.17 | BT103: =SUM(BI103:BK103) -> 1522.2333 | BU103: =SUM(BL103:BN103) -> 798.82 | BV103: =SUM(BO103:BQ103) -> 0 | BW103: =SUM(BF103:BK103) -> 1894.4033 | BX103: =SUM(BL103:BQ103) -> 798.82 | BY103: =IF(Info!$O$3="Q1",$BS103,IF(Info!$O$3="Q2",$BS103+$BT103,IF(Info!$O$3="Q3",$BS103+$BT103+$BU103,$BR103))) -> 372.17 | BZ103: =IF(Info!$O$3="Q1",$BS103,IF(Info!$O$3="Q2",$BT103,IF(Info!$O$3="Q3",$BU103,$BV103))) -> 372.17
...

Sheet WK2
D1: =Info!$N$3 -> 2025 | E1: 1st Quarter | R1: 2nd Quarter | AE1: 3rd Quarter | AR1: 4th Quarter | BF1: Q1 | BI1: Q2 | BL1: Q3 | BO1: Q4
B2: =Info!$D$1 -> Textile House Austria | E2: January | I2: February | M2: March | R2: April | V2: May | Z2: June | AE2: July | AI2: August | AM2: September | AR2: October | AV2: November | AZ2: December | BF2: January | BG2: February | BH2: March | BI2: April | BJ2: May | BK2: June | BL2: July | BM2: August | BN2: September | BO2: October | BP2: November | BQ2: December | BR2: Year | BS2: Q1 | BT2: Q2 | BU2: Q3 | BV2: Q4 | BW2: H1 | BX2: H2 | BY2: Selection | BZ2: Selection
B3: 2 week | E3: Week | F3: Week | G3: Week | H3: Week | I3: Week | J3: Week | K3: Week | L3: Week | M3: Week | N3: Week | O3: Week | P3: Week | Q3: Week | R3: Week | S3: Week | T3: Week | U3: Week | V3: Week | W3: Week | X3: Week | Y3: Week | Z3: Week | AA3: Week | AB3: Week | AC3: Week | AD3: Week | AE3: Week | AF3: Week | AG3: Week | AH3: Week | AI3: Week | AJ3: Week | AK3: Week | AL3: Week | AM3: Week | AN3: Week | AO3: Week | AP3: Week | AQ3: Week | AR3: Week | AS3: Week | AT3: Week | AU3: Week | AV3: Week | AW3: Week | AX3: Week | AY3: Week | AZ3: Week | BA3: Week | BB3: Week | BC3: Week | BD3: Week | BF3: 1-4 | BG3: 5-8 | BH3: 9-13 | BI3: 14-17 | BJ3: 18-21 | BK3: 22-26 | BL3: 27-30 | BM3: 31-34 | BN3: 35-39 | BO3: 40-43 | BP3: 44-47 | BQ3: 48-52 | BR3: =$D$1 -> 2025 | BS3: 1-13 | BT3: 14-26 | BU3: 27-39 | BV3: 40-52 | BW3: 1-26 | BX3: 27-52 | BY3: YTD | BZ3: Quarter
D4: Total | E4: 1 | F4: 2 | G4: 3 | H4: 4 | I4: 5 | J4: 6 | K4: 7 | L4: 8 | M4: 9 | N4: 10 | O4: 11 | P4: 12 | Q4: 13 | R4: 14 | S4: 15 | T4: 16 | U4: 17 | V4: 18 | W4: 19 | X4: 20 | Y4: 21 | Z4: 22 | AA4: 23 | AB4: 24 | AC4: 25 | AD4: 26 | AE4: 27 | AF4: 28 | AG4: 29 | AH4: 30 | AI4: 31 | AJ4: 32 | AK4: 33 | AL4: 34 | AM4: 35 | AN4: 36 | AO4: 37 | AP4: 38 | AQ4: 39 | AR4: 40 | AS4: 41 | AT4: 42 | AU4: 43 | AV4: 44 | AW4: 45 | AX4: 46 | AY4: 47 | AZ4: 48 | BA4: 49 | BB4: 50 | BC4: 51 | BD4: 52 | BF4: 4 | BG4: 4 | BH4: 5 | BI4: 4 | BJ4: 4 | BK4: 5 | BL4: 4 | BM4: 4 | BN4: 5 | BO4: 4 | BP4: 4 | BQ4: 5
B5: Pieces stolen | D5: =SUM(E5:BD5) -> 0 | BF5: =SUM(E5:H5) -> 0 | BG5: =SUM(I5:L5) -> 0 | BH5: =SUM(M5:Q5) -> 0 | BI5: =SUM(R5:U5) -> 0 | BJ5: =SUM(V5:Y5) -> 0 | BK5: =SUM(Z5:AD5) -> 0 | BL5: =SUM(AE5:AH5) -> 0 | BM5: =SUM(AI5:AL5) -> 0 | BN5: =SUM(AM5:AQ5) -> 0 | BO5: =SUM(AR5:AU5) -> 0 | BP5: =SUM(AV5:AY5) -> 0 | BQ5: =SUM(AZ5:BD5) -> 0 | BR5: =SUM(BF5:BQ5) -> 0 | BS5: =SUM(BF5:BH5) -> 0 | BT5: =SUM(BI5:BK5) -> 0 | BU5: =SUM(BL5:BN5) -> 0 | BV5: =SUM(BO5:BQ5) -> 0 | BW5: =SUM(BF5:BK5) -> 0 | BX5: =SUM(BL5:BQ5) -> 0 | BY5: =IF(Info!$O$3="Q1",$BS5,IF(Info!$O$3="Q2",$BS5+$BT5,IF(Info!$O$3="Q3",$BS5+$BT5+$BU5,$BR5))) -> 0 | BZ5: =IF(Info!$O$3="Q1",$BS5,IF(Info!$O$3="Q2",$BT5,IF(Info!$O$3="Q3",$BU5,$BV5))) -> 0
B6: Pcs in the shop, week begin | D6: =SUM(E6:BD6) -> 299787.8 | E6: =SUM(Paniglgasse:Newshop2!E6) -> 5765.15 | F6: =IF(F15=0,E32,F15) -> 5765.15 | G6: =IF(G15=0,F32,G15) -> 5765.15 | H6: =IF(H15=0,G32,H15) -> 5765.15 | I6: =IF(I15=0,H32,I15) -> 5765.15 | J6: =IF(J15=0,I32,J15) -> 5765.15 | K6: =IF(K15=0,J32,K15) -> 5765.15 | L6: =IF(L15=0,K32,L15) -> 5765.15 | M6: =IF(M15=0,L32,M15) -> 5765.15 | ... BD6: =IF(BD15=0,BC32,BD15) -> 5765.15 | BF6: =SUM(E6:H6) -> 23060.6 | BG6: =SUM(I6:L6) -> 23060.6 | BH6: =SUM(M6:Q6) -> 28825.75 | BI6: =SUM(R6:U6) -> 23060.6 | BJ6: =SUM(V6:Y6) -> 23060.6 | BK6: =SUM(Z6:AD6) -> 28825.75 | BL6: =SUM(AE6:AH6) -> 23060.6 | BM6: =SUM(AI6:AL6) -> 23060.6 | BN6: =SUM(AM6:AQ6) -> 28825.75 | BO6: =SUM(AR6:AU6) -> 23060.6 | BP6: =SUM(AV6:AY6) -> 23060.6 | BQ6: =SUM(AZ6:BD6) -> 28825.75 | BR6: =SUM(BF6:BQ6) -> 299787.8 | BS6: =SUM(BF6:BH6) -> 74946.95 | BT6: =SUM(BI6:BK6) -> 74946.95 | BU6: =SUM(BL6:BN6) -> 74946.95 | BV6: =SUM(BO6:BQ6) -> 74946.95 | BW6: =SUM(BF6:BK6) -> 149893.9 | BX6: =SUM(BL6:BQ6) -> 149893.9 | BY6: =IF(Info!$O$3="Q1",$BS6,IF(Info!$O$3="Q2",$BS6+$BT6,IF(Info!$O$3="Q3",$BS6+$BT6+$BU6,$BR6))) -> 74946.95 | BZ6: =IF(Info!$O$3="Q1",$BS6,IF(Info!$O$3="Q2",$BT6,IF(Info!$O$3="Q3",$BU6,$BV6))) -> 74946.95
B7: Pcs put into the shop, A new opening | D7: =SUM(E7:BD7) -> 0 | BF7: =SUM(E7:H7) -> 0 | BG7: =SUM(I7:L7) -> 0 | BH7: =SUM(M7:Q7) -> 0 | BI7: =SUM(R7:U7) -> 0 | BJ7: =SUM(V7:Y7) -> 0 | BK7: =SUM(Z7:AD7) -> 0 | BL7: =SUM(AE7:AH7) -> 0 | BM7: =SUM(AI7:AL7) -> 0 | BN7: =SUM(AM7:AQ7) -> 0 | BO7: =SUM(AR7:AU7) -> 0 | BP7: =SUM(AV7:AY7) -> 0 | BQ7: =SUM(AZ7:BD7) -> 0 | BR7: =SUM(BF7:BQ7) -> 0 | BS7: =SUM(BF7:BH7) -> 0 | BT7: =SUM(BI7:BK7) -> 0 | BU7: =SUM(BL7:BN7) -> 0 | BV7: =SUM(BO7:BQ7) -> 0 | BW7: =SUM(BF7:BK7) -> 0 | BX7: =SUM(BL7:BQ7) -> 0 | BY7: =IF(Info!$O$3="Q1",$BS7,IF(Info!$O$3="Q2",$BS7+$BT7,IF(Info!$O$3="Q3",$BS7+$BT7+$BU7,$BR7))) -> 0 | BZ7: =IF(Info!$O$3="Q1",$BS7,IF(Info!$O$3="Q2",$BT7,IF(Info!$O$3="Q3",$BU7,$BV7))) -> 0
B8: Pcs put into the shop, B new opening | D8: =SUM(E8:BD8) -> 0 | BF8: =SUM(E8:H8) -> 0 | BG8: =SUM(I8:L8) -> 0 | BH8: =SUM(M8:Q8) -> 0 | BI8: =SUM(R8:U8) -> 0 | BJ8: =SUM(V8:Y8) -> 0 | BK8: =SUM(Z8:AD8) -> 0 | BL8: =SUM(AE8:AH8) -> 0 | BM8: =SUM(AI8:AL8) -> 0 | BN8: =SUM(AM8:AQ8) -> 0 | BO8: =SUM(AR8:AU8) -> 0 | BP8: =SUM(AV8:AY8) -> 0 | BQ8: =SUM(AZ8:BD8) -> 0 | BR8: =SUM(BF8:BQ8) -> 0 | BS8: =SUM(BF8:BH8) -> 0 | BT8: =SUM(BI8:BK8) -> 0 | BU8: =SUM(BL8:BN8) -> 0 | BV8: =SUM(BO8:BQ8) -> 0 | BW8: =SUM(BF8:BK8) -> 0 | BX8: =SUM(BL8:BQ8) -> 0 | BY8: =IF(Info!$O$3="Q1",$BS8,IF(Info!$O$3="Q2",$BS8+$BT8,IF(Info!$O$3="Q3",$BS8+$BT8+$BU8,$BR8))) -> 0 | BZ8: =IF(Info!$O$3="Q1",$BS8,IF(Info!$O$3="Q2",$BT8,IF(Info!$O$3="Q3",$BU8,$BV8))) -> 0
B9: Pcs put into the shop, shoes A new opening | D9: =SUM(E9:BD9) -> 0 | BF9: =SUM(E9:H9) -> 0 | BG9: =SUM(I9:L9) -> 0 | BH9: =SUM(M9:Q9) -> 0 | BI9: =SUM(R9:U9) -> 0 | BJ9: =SUM(V9:Y9) -> 0 | BK9: =SUM(Z9:AD9) -> 0 | BL9: =SUM(AE9:AH9) -> 0 | BM9: =SUM(AI9:AL9) -> 0 | BN9: =SUM(AM9:AQ9) -> 0 | BO9: =SUM(AR9:AU9) -> 0 | BP9: =SUM(AV9:AY9) -> 0 | BQ9: =SUM(AZ9:BD9) -> 0 | BR9: =SUM(BF9:BQ9) -> 0 | BS9: =SUM(BF9:BH9) -> 0 | BT9: =SUM(BI9:BK9) -> 0 | BU9: =SUM(BL9:BN9) -> 0 | BV9: =SUM(BO9:BQ9) -> 0 | BW9: =SUM(BF9:BK9) -> 0 | BX9: =SUM(BL9:BQ9) -> 0 | BY9: =IF(Info!$O$3="Q1",$BS9,IF(Info!$O$3="Q2",$BS9+$BT9,IF(Info!$O$3="Q3",$BS9+$BT9+$BU9,$BR9))) -> 0 | BZ9: =IF(Info!$O$3="Q1",$BS9,IF(Info!$O$3="Q2",$BT9,IF(Info!$O$3="Q3",$BU9,$BV9))) -> 0
B10: Pcs put into the shop, shoes B new opening | D10: =SUM(E10:BD10) -> 0 | BF10: =SUM(E10:H10) -> 0 | BG10: =SUM(I10:L10) -> 0 | BH10: =SUM(M10:Q10) -> 0 | BI10: =SUM(R10:U10) -> 0 | BJ10: =SUM(V10:Y10) -> 0 | BK10: =SUM(Z10:AD10) -> 0 | BL10: =SUM(AE10:AH10) -> 0 | BM10: =SUM(AI10:AL10) -> 0 | BN10: =SUM(AM10:AQ10) -> 0 | BO10: =SUM(AR10:AU10) -> 0 | BP10: =SUM(AV10:AY10) -> 0 | BQ10: =SUM(AZ10:BD10) -> 0 | BR10: =SUM(BF10:BQ10) -> 0 | BS10: =SUM(BF10:BH10) -> 0 | BT10: =SUM(BI10:BK10) -> 0 | BU10: =SUM(BL10:BN10) -> 0 | BV10: =SUM(BO10:BQ10) -> 0 | BW10: =SUM(BF10:BK10) -> 0 | BX10: =SUM(BL10:BQ10) -> 0 | BY10: =IF(Info!$O$3="Q1",$BS10,IF(Info!$O$3="Q2",$BS10+$BT10,IF(Info!$O$3="Q3",$BS10+$BT10+$BU10,$BR10))) -> 0 | BZ10: =IF(Info!$O$3="Q1",$BS10,IF(Info!$O$3="Q2",$BT10,IF(Info!$O$3="Q3",$BU10,$BV10))) -> 0
B11: Pcs put into the shop, HHR new opening | D11: =SUM(E11:BD11) -> 0 | BF11: =SUM(E11:H11) -> 0 | BG11: =SUM(I11:L11) -> 0 | BH11: =SUM(M11:Q11) -> 0 | BI11: =SUM(R11:U11) -> 0 | BJ11: =SUM(V11:Y11) -> 0 | BK11: =SUM(Z11:AD11) -> 0 | BL11: =SUM(AE11:AH11) -> 0 | BM11: =SUM(AI11:AL11) -> 0 | BN11: =SUM(AM11:AQ11) -> 0 | BO11: =SUM(AR11:AU11) -> 0 | BP11: =SUM(AV11:AY11) -> 0 | BQ11: =SUM(AZ11:BD11) -> 0 | BR11: =SUM(BF11:BQ11) -> 0 | BS11: =SUM(BF11:BH11) -> 0 | BT11: =SUM(BI11:BK11) -> 0 | BU11: =SUM(BL11:BN11) -> 0 | BV11: =SUM(BO11:BQ11) -> 0 | BW11: =SUM(BF11:BK11) -> 0 | BX11: =SUM(BL11:BQ11) -> 0 | BY11: =IF(Info!$O$3="Q1",$BS11,IF(Info!$O$3="Q2",$BS11+$BT11,IF(Info!$O$3="Q3",$BS11+$BT11+$BU11,$BR11))) -> 0 | BZ11: =IF(Info!$O$3="Q1",$BS11,IF(Info!$O$3="Q2",$BT11,IF(Info!$O$3="Q3",$BU11,$BV11))) -> 0
B12: Pcs put into the shop, Handbag A new opening | D12: =SUM(E12:BD12) -> 0 | BF12: =SUM(E12:H12) -> 0 | BG12: =SUM(I12:L12) -> 0 | BH12: =SUM(M12:Q12) -> 0 | BI12: =SUM(R12:U12) -> 0 | BJ12: =SUM(V12:Y12) -> 0 | BK12: =SUM(Z12:AD12) -> 0 | BL12: =SUM(AE12:AH12) -> 0 | BM12: =SUM(AI12:AL12) -> 0 | BN12: =SUM(AM12:AQ12) -> 0 | BO12: =SUM(AR12:AU12) -> 0 | BP12: =SUM(AV12:AY12) -> 0 | BQ12: =SUM(AZ12:BD12) -> 0 | BR12: =SUM(BF12:BQ12) -> 0 | BS12: =SUM(BF12:BH12) -> 0 | BT12: =SUM(BI12:BK12) -> 0 | BU12: =SUM(BL12:BN12) -> 0 | BV12: =SUM(BO12:BQ12) -> 0 | BW12: =SUM(BF12:BK12) -> 0 | BX12: =SUM(BL12:BQ12) -> 0 | BY12: =IF(Info!$O$3="Q1",$BS12,IF(Info!$O$3="Q2",$BS12+$BT12,IF(Info!$O$3="Q3",$BS12+$BT12+$BU12,$BR12))) -> 0 | BZ12: =IF(Info!$O$3="Q1",$BS12,IF(Info!$O$3="Q2",$BT12,IF(Info!$O$3="Q3",$BU12,$BV12))) -> 0
B13: Pcs put into the shop, Handbag B new opening | D13: =SUM(E13:BD13) -> 0 | BF13: =SUM(E13:H13) -> 0 | BG13: =SUM(I13:L13) -> 0 | BH13: =SUM(M13:Q13) -> 0 | BI13: =SUM(R13:U13) -> 0 | BJ13: =SUM(V13:Y13) -> 0 | BK13: =SUM(Z13:AD13) -> 0 | BL13: =SUM(AE13:AH13) -> 0 | BM13: =SUM(AI13:AL13) -> 0 | BN13: =SUM(AM13:AQ13) -> 0 | BO13: =SUM(AR13:AU13) -> 0 | BP13: =SUM(AV13:AY13) -> 0 | BQ13: =SUM(AZ13:BD13) -> 0 | BR13: =SUM(BF13:BQ13) -> 0 | BS13: =SUM(BF13:BH13) -> 0 | BT13: =SUM(BI13:BK13) -> 0 | BU13: =SUM(BL13:BN13) -> 0 | BV13: =SUM(BO13:BQ13) -> 0 | BW13: =SUM(BF13:BK13) -> 0 | BX13: =SUM(BL13:BQ13) -> 0 | BY13: =IF(Info!$O$3="Q1",$BS13,IF(Info!$O$3="Q2",$BS13+$BT13,IF(Info!$O$3="Q3",$BS13+$BT13+$BU13,$BR13))) -> 0 | BZ13: =IF(Info!$O$3="Q1",$BS13,IF(Info!$O$3="Q2",$BT13,IF(Info!$O$3="Q3",$BU13,$BV13))) -> 0
B14: Pcs put into the shop, things new opening | D14: =SUM(E14:BD14) -> 0 | BF14: =SUM(E14:H14) -> 0 | BG14: =SUM(I14:L14) -> 0 | BH14: =SUM(M14:Q14) -> 0 | BI14: =SUM(R14:U14) -> 0 | BJ14: =SUM(V14:Y14) -> 0 | BK14: =SUM(Z14:AD14) -> 0 | BL14: =SUM(AE14:AH14) -> 0 | BM14: =SUM(AI14:AL14) -> 0 | BN14: =SUM(AM14:AQ14) -> 0 | BO14: =SUM(AR14:AU14) -> 0 | BP14: =SUM(AV14:AY14) -> 0 | BQ14: =SUM(AZ14:BD14) -> 0 | BR14: =SUM(BF14:BQ14) -> 0 | BS14: =SUM(BF14:BH14) -> 0 | BT14: =SUM(BI14:BK14) -> 0 | BU14: =SUM(BL14:BN14) -> 0 | BV14: =SUM(BO14:BQ14) -> 0 | BW14: =SUM(BF14:BK14) -> 0 | BX14: =SUM(BL14:BQ14) -> 0 | BY14: =IF(Info!$O$3="Q1",$BS14,IF(Info!$O$3="Q2",$BS14+$BT14,IF(Info!$O$3="Q3",$BS14+$BT14+$BU14,$BR14))) -> 0 | BZ14: =IF(Info!$O$3="Q1",$BS14,IF(Info!$O$3="Q2",$BT14,IF(Info!$O$3="Q3",$BU14,$BV14))) -> 0
B15: Pcs put into the shop, total new opening | D15: =SUM(E15:BD15) -> 0 | E15: =SUM(E7:E14) -> 0 | F15: =SUM(F7:F14) -> 0 | G15: =SUM(G7:G14) -> 0 | H15: =SUM(H7:H14) -> 0 | I15: =SUM(I7:I14) -> 0 | J15: =SUM(J7:J14) -> 0 | K15: =SUM(K7:K14) -> 0 | L15: =SUM(L7:L14) -> 0 | ... BD15: =SUM(BD7:BD14) -> 0 | BF15: =SUM(E15:H15) -> 0 | BG15: =SUM(I15:L15) -> 0 | BH15: =SUM(M15:Q15) -> 0 | BI15: =SUM(R15:U15) -> 0 | BJ15: =SUM(V15:Y15) -> 0 | BK15: =SUM(Z15:AD15) -> 0 | BL15: =SUM(AE15:AH15) -> 0 | BM15: =SUM(AI15:AL15) -> 0 | BN15: =SUM(AM15:AQ15) -> 0 | BO15: =SUM(AR15:AU15) -> 0 | BP15: =SUM(AV15:AY15) -> 0 | BQ15: =SUM(AZ15:BD15) -> 0 | BR15: =SUM(BF15:BQ15) -> 0 | BS15: =SUM(BF15:BH15) -> 0 | BT15: =SUM(BI15:BK15) -> 0 | BU15: =SUM(BL15:BN15) -> 0 | BV15: =SUM(BO15:BQ15) -> 0 | BW15: =SUM(BF15:BK15) -> 0 | BX15: =SUM(BL15:BQ15) -> 0 | BY15: =IF(Info!$O$3="Q1",$BS15,IF(Info!$O$3="Q2",$BS15+$BT15,IF(Info!$O$3="Q3",$BS15+$BT15+$BU15,$BR15))) -> 0 | BZ15: =IF(Info!$O$3="Q1",$BS15,IF(Info!$O$3="Q2",$BT15,IF(Info!$O$3="Q3",$BU15,$BV15))) -> 0
B16: Pcs put into the shop, shop A | D16: =SUM(E16:BD16) -> 0 | BF16: =SUM(E16:H16) -> 0 | BG16: =SUM(I16:L16) -> 0 | BH16: =SUM(M16:Q16) -> 0 | BI16: =SUM(R16:U16) -> 0 | BJ16: =SUM(V16:Y16) -> 0 | BK16: =SUM(Z16:AD16) -> 0 | BL16: =SUM(AE16:AH16) -> 0 | BM16: =SUM(AI16:AL16) -> 0 | BN16: =SUM(AM16:AQ16) -> 0 | BO16: =SUM(AR16:AU16) -> 0 | BP16: =SUM(AV16:AY16) -> 0 | BQ16: =SUM(AZ16:BD16) -> 0 | BR16: =SUM(BF16:BQ16) -> 0 | BS16: =SUM(BF16:BH16) -> 0 | BT16: =SUM(BI16:BK16) -> 0 | BU16: =SUM(BL16:BN16) -> 0 | BV16: =SUM(BO16:BQ16) -> 0 | BW16: =SUM(BF16:BK16) -> 0 | BX16: =SUM(BL16:BQ16) -> 0 | BY16: =IF(Info!$O$3="Q1",$BS16,IF(Info!$O$3="Q2",$BS16+$BT16,IF(Info!$O$3="Q3",$BS16+$BT16+$BU16,$BR16))) -> 0 | BZ16: =IF(Info!$O$3="Q1",$BS16,IF(Info!$O$3="Q2",$BT16,IF(Info!$O$3="Q3",$BU16,$BV16))) -> 0
B17: Pcs put into the shop, shop B | D17: =SUM(E17:BD17) -> 0 | BF17: =SUM(E17:H17) -> 0 | BG17: =SUM(I17:L17) -> 0 | BH17: =SUM(M17:Q17) -> 0 | BI17: =SUM(R17:U17) -> 0 | BJ17: =SUM(V17:Y17) -> 0 | BK17: =SUM(Z17:AD17) -> 0 | BL17: =SUM(AE17:AH17) -> 0 | BM17: =SUM(AI17:AL17) -> 0 | BN17: =SUM(AM17:AQ17) -> 0 | BO17: =SUM(AR17:AU17) -> 0 | BP17: =SUM(AV17:AY17) -> 0 | BQ17: =SUM(AZ17:BD17) -> 0 | BR17: =SUM(BF17:BQ17) -> 0 | BS17: =SUM(BF17:BH17) -> 0 | BT17: =SUM(BI17:BK17) -> 0 | BU17: =SUM(BL17:BN17) -> 0 | BV17: =SUM(BO17:BQ17) -> 0 | BW17: =SUM(BF17:BK17) -> 0 | BX17: =SUM(BL17:BQ17) -> 0 | BY17: =IF(Info!$O$3="Q1",$BS17,IF(Info!$O$3="Q2",$BS17+$BT17,IF(Info!$O$3="Q3",$BS17+$BT17+$BU17,$BR17))) -> 0 | BZ17: =IF(Info!$O$3="Q1",$BS17,IF(Info!$O$3="Q2",$BT17,IF(Info!$O$3="Q3",$BU17,$BV17))) -> 0
B18: Pcs put into the shop, shoes A | D18: =SUM(E18:BD18) -> 0 | BF18: =SUM(E18:H18) -> 0 | BG18: =SUM(I18:L18) -> 0 | BH18: =SUM(M18:Q18) -> 0 | BI18: =SUM(R18:U18) -> 0 | BJ18: =SUM(V18:Y18) -> 0 | BK18: =SUM(Z18:AD18) -> 0 | BL18: =SUM(AE18:AH18) -> 0 | BM18: =SUM(AI18:AL18) -> 0 | BN18: =SUM(AM18:AQ18) -> 0 | BO18: =SUM(AR18:AU18) -> 0 | BP18: =SUM(AV18:AY18) -> 0 | BQ18: =SUM(AZ18:BD18) -> 0 | BR18: =SUM(BF18:BQ18) -> 0 | BS18: =SUM(BF18:BH18) -> 0 | BT18: =SUM(BI18:BK18) -> 0 | BU18: =SUM(BL18:BN18) -> 0 | BV18: =SUM(BO18:BQ18) -> 0 | BW18: =SUM(BF18:BK18) -> 0 | BX18: =SUM(BL18:BQ18) -> 0 | BY18: =IF(Info!$O$3="Q1",$BS18,IF(Info!$O$3="Q2",$BS18+$BT18,IF(Info!$O$3="Q3",$BS18+$BT18+$BU18,$BR18))) -> 0 | BZ18: =IF(Info!$O$3="Q1",$BS18,IF(Info!$O$3="Q2",$BT18,IF(Info!$O$3="Q3",$BU18,$BV18))) -> 0
B19: Pcs put into the shop, shoes B | D19: =SUM(E19:BD19) -> 0 | BF19: =SUM(E19:H19) -> 0 | BG19: =SUM(I19:L19) -> 0 | BH19: =SUM(M19:Q19) -> 0 | BI19: =SUM(R19:U19) -> 0 | BJ19: =SUM(V19:Y19) -> 0 | BK19: =SUM(Z19:AD19) -> 0 | BL19: =SUM(AE19:AH19) -> 0 | BM19: =SUM(AI19:AL19) -> 0 | BN19: =SUM(AM19:AQ19) -> 0 | BO19: =SUM(AR19:AU19) -> 0 | BP19: =SUM(AV19:AY19) -> 0 | BQ19: =SUM(AZ19:BD19) -> 0 | BR19: =SUM(BF19:BQ19) -> 0 | BS19: =SUM(BF19:BH19) -> 0 | BT19: =SUM(BI19:BK19) -> 0 | BU19: =SUM(BL19:BN19) -> 0 | BV19: =SUM(BO19:BQ19) -> 0 | BW19: =SUM(BF19:BK19) -> 0 | BX19: =SUM(BL19:BQ19) -> 0 | BY19: =IF(Info!$O$3="Q1",$BS19,IF(Info!$O$3="Q2",$BS19+$BT19,IF(Info!$O$3="Q3",$BS19+$BT19+$BU19,$BR19))) -> 0 | BZ19: =IF(Info!$O$3="Q1",$BS19,IF(Info!$O$3="Q2",$BT19,IF(Info!$O$3="Q3",$BU19,$BV19))) -> 0
B20: Pcs put into the shop, HHR | D20: =SUM(E20:BD20) -> 0 | BF20: =SUM(E20:H20) -> 0 | BG20: =SUM(I20:L20) -> 0 | BH20: =SUM(M20:Q20) -> 0 | BI20: =SUM(R20:U20) -> 0 | BJ20: =SUM(V20:Y20) -> 0 | BK20: =SUM(Z20:AD20) -> 0 | BL20: =SUM(AE20:AH20) -> 0 | BM20: =SUM(AI20:AL20) -> 0 | BN20: =SUM(AM20:AQ20) -> 0 | BO20: =SUM(AR20:AU20) -> 0 | BP20: =SUM(AV20:AY20) -> 0 | BQ20: =SUM(AZ20:BD20) -> 0 | BR20: =SUM(BF20:BQ20) -> 0 | BS20: =SUM(BF20:BH20) -> 0 | BT20: =SUM(BI20:BK20) -> 0 | BU20: =SUM(BL20:BN20) -> 0 | BV20: =SUM(BO20:BQ20) -> 0 | BW20: =SUM(BF20:BK20) -> 0 | BX20: =SUM(BL20:BQ20) -> 0 | BY20: =IF(Info!$O$3="Q1",$BS20,IF(Info!$O$3="Q2",$BS20+$BT20,IF(Info!$O$3="Q3",$BS20+$BT20+$BU20,$BR20))) -> 0 | BZ20: =IF(Info!$O$3="Q1",$BS20,IF(Info!$O$3="Q2",$BT20,IF(Info!$O$3="Q3",$BU20,$BV20))) -> 0
B21: Pcs put into the shop, Mix Summer | D21: =SUM(E21:BD21) -> 0 | BF21: =SUM(E21:H21) -> 0 | BG21: =SUM(I21:L21) -> 0 | BH21: =SUM(M21:Q21) -> 0 | BI21: =SUM(R21:U21) -> 0 | BJ21: =SUM(V21:Y21) -> 0 | BK21: =SUM(Z21:AD21) -> 0 | BL21: =SUM(AE21:AH21) -> 0 | BM21: =SUM(AI21:AL21) -> 0 | BN21: =SUM(AM21:AQ21) -> 0 | BO21: =SUM(AR21:AU21) -> 0 | BP21: =SUM(AV21:AY21) -> 0 | BQ21: =SUM(AZ21:BD21) -> 0 | BR21: =SUM(BF21:BQ21) -> 0 | BS21: =SUM(BF21:BH21) -> 0 | BT21: =SUM(BI21:BK21) -> 0 | BU21: =SUM(BL21:BN21) -> 0 | BV21: =SUM(BO21:BQ21) -> 0 | BW21: =SUM(BF21:BK21) -> 0 | BX21: =SUM(BL21:BQ21) -> 0 | BY21: =IF(Info!$O$3="Q1",$BS21,IF(Info!$O$3="Q2",$BS21+$BT21,IF(Info!$O$3="Q3",$BS21+$BT21+$BU21,$BR21))) -> 0 | BZ21: =IF(Info!$O$3="Q1",$BS21,IF(Info!$O$3="Q2",$BT21,IF(Info!$O$3="Q3",$BU21,$BV21))) -> 0
B22: Pcs put into the shop, Mix Winter | D22: =SUM(E22:BD22) -> 0 | BF22: =SUM(E22:H22) -> 0 | BG22: =SUM(I22:L22) -> 0 | BH22: =SUM(M22:Q22) -> 0 | BI22: =SUM(R22:U22) -> 0 | BJ22: =SUM(V22:Y22) -> 0 | BK22: =SUM(Z22:AD22) -> 0 | BL22: =SUM(AE22:AH22) -> 0 | BM22: =SUM(AI22:AL22) -> 0 | BN22: =SUM(AM22:AQ22) -> 0 | BO22: =SUM(AR22:AU22) -> 0 | BP22: =SUM(AV22:AY22) -> 0 | BQ22: =SUM(AZ22:BD22) -> 0 | BR22: =SUM(BF22:BQ22) -> 0 | BS22: =SUM(BF22:BH22) -> 0 | BT22: =SUM(BI22:BK22) -> 0 | BU22: =SUM(BL22:BN22) -> 0 | BV22: =SUM(BO22:BQ22) -> 0 | BW22: =SUM(BF22:BK22) -> 0 | BX22: =SUM(BL22:BQ22) -> 0 | BY22: =IF(Info!$O$3="Q1",$BS22,IF(Info!$O$3="Q2",$BS22+$BT22,IF(Info!$O$3="Q3",$BS22+$BT22+$BU22,$BR22))) -> 0 | BZ22: =IF(Info!$O$3="Q1",$BS22,IF(Info!$O$3="Q2",$BT22,IF(Info!$O$3="Q3",$BU22,$BV22))) -> 0
B23: Pcs put into the shop, Handbag A | D23: =SUM(E23:BD23) -> 0 | BF23: =SUM(E23:H23) -> 0 | BG23: =SUM(I23:L23) -> 0 | BH23: =SUM(M23:Q23) -> 0 | BI23: =SUM(R23:U23) -> 0 | BJ23: =SUM(V23:Y23) -> 0 | BK23: =SUM(Z23:AD23) -> 0 | BL23: =SUM(AE23:AH23) -> 0 | BM23: =SUM(AI23:AL23) -> 0 | BN23: =SUM(AM23:AQ23) -> 0 | BO23: =SUM(AR23:AU23) -> 0 | BP23: =SUM(AV23:AY23) -> 0 | BQ23: =SUM(AZ23:BD23) -> 0 | BR23: =SUM(BF23:BQ23) -> 0 | BS23: =SUM(BF23:BH23) -> 0 | BT23: =SUM(BI23:BK23) -> 0 | BU23: =SUM(BL23:BN23) -> 0 | BV23: =SUM(BO23:BQ23) -> 0 | BW23: =SUM(BF23:BK23) -> 0 | BX23: =SUM(BL23:BQ23) -> 0 | BY23: =IF(Info!$O$3="Q1",$BS23,IF(Info!$O$3="Q2",$BS23+$BT23,IF(Info!$O$3="Q3",$BS23+$BT23+$BU23,$BR23))) -> 0 | BZ23: =IF(Info!$O$3="Q1",$BS23,IF(Info!$O$3="Q2",$BT23,IF(Info!$O$3="Q3",$BU23,$BV23))) -> 0
B24: Pcs put into the shop, Handbag B | D24: =SUM(E24:BD24) -> 0 | BF24: =SUM(E24:H24) -> 0 | BG24: =SUM(I24:L24) -> 0 | BH24: =SUM(M24:Q24) -> 0 | BI24: =SUM(R24:U24) -> 0 | BJ24: =SUM(V24:Y24) -> 0 | BK24: =SUM(Z24:AD24) -> 0 | BL24: =SUM(AE24:AH24) -> 0 | BM24: =SUM(AI24:AL24) -> 0 | BN24: =SUM(AM24:AQ24) -> 0 | BO24: =SUM(AR24:AU24) -> 0 | BP24: =SUM(AV24:AY24) -> 0 | BQ24: =SUM(AZ24:BD24) -> 0 | BR24: =SUM(BF24:BQ24) -> 0 | BS24: =SUM(BF24:BH24) -> 0 | BT24: =SUM(BI24:BK24) -> 0 | BU24: =SUM(BL24:BN24) -> 0 | BV24: =SUM(BO24:BQ24) -> 0 | BW24: =SUM(BF24:BK24) -> 0 | BX24: =SUM(BL24:BQ24) -> 0 | BY24: =IF(Info!$O$3="Q1",$BS24,IF(Info!$O$3="Q2",$BS24+$BT24,IF(Info!$O$3="Q3",$BS24+$BT24+$BU24,$BR24))) -> 0 | BZ24: =IF(Info!$O$3="Q1",$BS24,IF(Info!$O$3="Q2",$BT24,IF(Info!$O$3="Q3",$BU24,$BV24))) -> 0
B25: Pcs put into the shop, things | D25: =SUM(E25:BD25) -> 0 | BF25: =SUM(E25:H25) -> 0 | BG25: =SUM(I25:L25) -> 0 | BH25: =SUM(M25:Q25) -> 0 | BI25: =SUM(R25:U25) -> 0 | BJ25: =SUM(V25:Y25) -> 0 | BK25: =SUM(Z25:AD25) -> 0 | BL25: =SUM(AE25:AH25) -> 0 | BM25: =SUM(AI25:AL25) -> 0 | BN25: =SUM(AM25:AQ25) -> 0 | BO25: =SUM(AR25:AU25) -> 0 | BP25: =SUM(AV25:AY25) -> 0 | BQ25: =SUM(AZ25:BD25) -> 0 | BR25: =SUM(BF25:BQ25) -> 0 | BS25: =SUM(BF25:BH25) -> 0 | BT25: =SUM(BI25:BK25) -> 0 | BU25: =SUM(BL25:BN25) -> 0 | BV25: =SUM(BO25:BQ25) -> 0 | BW25: =SUM(BF25:BK25) -> 0 | BX25: =SUM(BL25:BQ25) -> 0 | BY25: =IF(Info!$O$3="Q1",$BS25,IF(Info!$O$3="Q2",$BS25+$BT25,IF(Info!$O$3="Q3",$BS25+$BT25+$BU25,$BR25))) -> 0 | BZ25: =IF(Info!$O$3="Q1",$BS25,IF(Info!$O$3="Q2",$BT25,IF(Info!$O$3="Q3",$BU25,$BV25))) -> 0
B26: Pcs put into the shop, Old extra | D26: =SUM(E26:BD26) -> 0 | BF26: =SUM(E26:H26) -> 0 | BG26: =SUM(I26:L26) -> 0 | BH26: =SUM(M26:Q26) -> 0 | BI26: =SUM(R26:U26) -> 0 | BJ26: =SUM(V26:Y26) -> 0 | BK26: =SUM(Z26:AD26) -> 0 | BL26: =SUM(AE26:AH26) -> 0 | BM26: =SUM(AI26:AL26) -> 0 | BN26: =SUM(AM26:AQ26) -> 0 | BO26: =SUM(AR26:AU26) -> 0 | BP26: =SUM(AV26:AY26) -> 0 | BQ26: =SUM(AZ26:BD26) -> 0 | BR26: =SUM(BF26:BQ26) -> 0 | BS26: =SUM(BF26:BH26) -> 0 | BT26: =SUM(BI26:BK26) -> 0 | BU26: =SUM(BL26:BN26) -> 0 | BV26: =SUM(BO26:BQ26) -> 0 | BW26: =SUM(BF26:BK26) -> 0 | BX26: =SUM(BL26:BQ26) -> 0 | BY26: =IF(Info!$O$3="Q1",$BS26,IF(Info!$O$3="Q2",$BS26+$BT26,IF(Info!$O$3="Q3",$BS26+$BT26+$BU26,$BR26))) -> 0 | BZ26: =IF(Info!$O$3="Q1",$BS26,IF(Info!$O$3="Q2",$BT26,IF(Info!$O$3="Q3",$BU26,$BV26))) -> 0
B27: Pcs put into the shop, total | D27: =SUM(E27:BD27) -> 0 | E27: =SUM(E15:E26) -> 0 | F27: =SUM(F15:F26) -> 0 | G27: =SUM(G15:G26) -> 0 | H27: =SUM(H15:H26) -> 0 | I27: =SUM(I15:I26) -> 0 | J27: =SUM(J15:J26) -> 0 | K27: =SUM(K15:K26) -> 0 | L27: =SUM(L15:L26) -> 0 | ... BD27: =SUM(BD15:BD26) -> 0 | BF27: =SUM(E27:H27) -> 0 | BG27: =SUM(I27:L27) -> 0 | BH27: =SUM(M27:Q27) -> 0 | BI27: =SUM(R27:U27) -> 0 | BJ27: =SUM(V27:Y27) -> 0 | BK27: =SUM(Z27:AD27) -> 0 | BL27: =SUM(AE27:AH27) -> 0 | BM27: =SUM(AI27:AL27) -> 0 | BN27: =SUM(AM27:AQ27) -> 0 | BO27: =SUM(AR27:AU27) -> 0 | BP27: =SUM(AV27:AY27) -> 0 | BQ27: =SUM(AZ27:BD27) -> 0 | BR27: =SUM(BF27:BQ27) -> 0 | BS27: =SUM(BF27:BH27) -> 0 | BT27: =SUM(BI27:BK27) -> 0 | BU27: =SUM(BL27:BN27) -> 0 | BV27: =SUM(BO27:BQ27) -> 0 | BW27: =SUM(BF27:BK27) -> 0 | BX27: =SUM(BL27:BQ27) -> 0 | BY27: =IF(Info!$O$3="Q1",$BS27,IF(Info!$O$3="Q2",$BS27+$BT27,IF(Info!$O$3="Q3",$BS27+$BT27+$BU27,$BR27))) -> 0 | BZ27: =IF(Info!$O$3="Q1",$BS27,IF(Info!$O$3="Q2",$BT27,IF(Info!$O$3="Q3",$BU27,$BV27))) -> 0
B28: Pcs put into the shop, total (excl. total new opening) | D28: =SUM(E28:BD28) -> 0 | E28: =E27-E15 -> 0 | F28: =F27-F15 -> 0 | G28: =G27-G15 -> 0 | H28: =H27-H15 -> 0 | I28: =I27-I15 -> 0 | J28: =J27-J15 -> 0 | K28: =K27-K15 -> 0 | L28: =L27-L15 -> 0 | ... BD28: =BD27-BD15 -> 0 | BF28: =SUM(E28:H28) -> 0 | BG28: =SUM(I28:L28) -> 0 | BH28: =SUM(M28:Q28) -> 0 | BI28: =SUM(R28:U28) -> 0 | BJ28: =SUM(V28:Y28) -> 0 | BK28: =SUM(Z28:AD28) -> 0 | BL28: =SUM(AE28:AH28) -> 0 | BM28: =SUM(AI28:AL28) -> 0 | BN28: =SUM(AM28:AQ28) -> 0 | BO28: =SUM(AR28:AU28) -> 0 | BP28: =SUM(AV28:AY28) -> 0 | BQ28: =SUM(AZ28:BD28) -> 0 | BR28: =SUM(BF28:BQ28) -> 0 | BS28: =SUM(BF28:BH28) -> 0 | BT28: =SUM(BI28:BK28) -> 0 | BU28: =SUM(BL28:BN28) -> 0 | BV28: =SUM(BO28:BQ28) -> 0 | BW28: =SUM(BF28:BK28) -> 0 | BX28: =SUM(BL28:BQ28) -> 0 | BY28: =IF(Info!$O$3="Q1",$BS28,IF(Info!$O$3="Q2",$BS28+$BT28,IF(Info!$O$3="Q3",$BS28+$BT28+$BU28,$BR28))) -> 0 | BZ28: =IF(Info!$O$3="Q1",$BS28,IF(Info!$O$3="Q2",$BT28,IF(Info!$O$3="Q3",$BU28,$BV28))) -> 0
B29: Pcs sold | D29: =SUM(E29:BD29) -> 0 | BF29: =SUM(E29:H29) -> 0 | BG29: =SUM(I29:L29) -> 0 | BH29: =SUM(M29:Q29) -> 0 | BI29: =SUM(R29:U29) -> 0 | BJ29: =SUM(V29:Y29) -> 0 | BK29: =SUM(Z29:AD29) -> 0 | BL29: =SUM(AE29:AH29) -> 0 | BM29: =SUM(AI29:AL29) -> 0 | BN29: =SUM(AM29:AQ29) -> 0 | BO29: =SUM(AR29:AU29) -> 0 | BP29: =SUM(AV29:AY29) -> 0 | BQ29: =SUM(AZ29:BD29) -> 0 | BR29: =SUM(BF29:BQ29) -> 0 | BS29: =SUM(BF29:BH29) -> 0 | BT29: =SUM(BI29:BK29) -> 0 | BU29: =SUM(BL29:BN29) -> 0 | BV29: =SUM(BO29:BQ29) -> 0 | BW29: =SUM(BF29:BK29) -> 0 | BX29: =SUM(BL29:BQ29) -> 0 | BY29: =IF(Info!$O$3="Q1",$BS29,IF(Info!$O$3="Q2",$BS29+$BT29,IF(Info!$O$3="Q3",$BS29+$BT29+$BU29,$BR29))) -> 0 | BZ29: =IF(Info!$O$3="Q1",$BS29,IF(Info!$O$3="Q2",$BT29,IF(Info!$O$3="Q3",$BU29,$BV29))) -> 0
